Workbook

Sheet SOFP-CuNonCu
B1: 01/01/YYYY - 31/12/YYYY | C1: 01/01/YYYY - 31/12/YYYY | D1: Source
A3: Statement of financial position
A4: Statement of financial position
A5: Statement of financial position
A6: Assets
A7: Non-current assets
A8: *Property, plant and equipment | B8: ='SOFP-Sub-CuNonCu'!B39 | C8: ='SOFP-Sub-CuNonCu'!C39
A9: *Investment property | B9: ='SOFP-Sub-CuNonCu'!B49 | C9: ='SOFP-Sub-CuNonCu'!C49
A10: Biological assets
A11: Right-of-use assets | B11: 19524288 | C11: 13076097 | D11: Page 16, Right-of-use assets
A12: Service concession assets
A13: *Intangible assets | B13: ='SOFP-Sub-CuNonCu'!B69 | C13: ='SOFP-Sub-CuNonCu'!C69
A14: *Investments in subsidiaries | B14: ='SOFP-Sub-CuNonCu'!B77 | C14: ='SOFP-Sub-CuNonCu'!C77
A15: *Investments in associates | B15: ='SOFP-Sub-CuNonCu'!B86 | C15: ='SOFP-Sub-CuNonCu'!C86
A16: *Investments in joint ventures | B16: ='SOFP-Sub-CuNonCu'!B95 | C16: ='SOFP-Sub-CuNonCu'!C95
A17: *Other investments | B17: 924204 | C17: 1008204 | D17: Page 16, Other assets (non-current). Placed here to ensure inclusion in Total Assets sum due to template B22 formula issue.
A18: *Trade and other non-current receivables | B18: ='SOFP-Sub-CuNonCu'!B120 | C18: ='SOFP-Sub-CuNonCu'!C120
A19: Contract assets
A20: Deferred tax assets | B20: 6998 | C20: 0 | D20: Page 16, Deferred tax assets
A21: *Derivative financial assets | B21: ='SOFP-Sub-CuNonCu'!B129 | C21: ='SOFP-Sub-CuNonCu'!C129
A22: *Other non-current assets | B22: ='SOFP-Sub-CuNonCu'!B198 | C22: ='SOFP-Sub-CuNonCu'!C198
A23: *Total non-current assets | B23: =1*B8+1*B9+1*B10+1*B11+1*B12+1*B13+1*B14+1*B15+1*B16+1*B17+1*B18+1*B19+1*B20+1*B21+1*B22 | C23: =1*C8+1*C9+1*C10+1*C11+1*C12+1*C13+1*C14+1*C15+1*C16+1*C17+1*C18+1*C19+1*C20+1*C21+1*C22
A24: Current assets
A25: *Inventories | B25: ='SOFP-Sub-CuNonCu'!B136 | C25: ='SOFP-Sub-CuNonCu'!C136
A26: Biological assets
A27: Other investments | B27: 5438139 | C27: 5329513 | D27: Page 16, Short term investments
A28: Current tax assets | B28: 497096 | C28: 2014561 | D28: Page 16, Current tax assets
A29: *Trade and other current receivables | B29: ='SOFP-Sub-CuNonCu'!B169 | C29: ='SOFP-Sub-CuNonCu'!C169
A30: Contract assets
A31: *Derivative financial assets | B31: ='SOFP-Sub-CuNonCu'!B178 | C31: ='SOFP-Sub-CuNonCu'!C178
A32: *Cash and cash equivalents | B32: ='SOFP-Sub-CuNonCu'!B193 | C32: ='SOFP-Sub-CuNonCu'!C193
A33: *Other current assets
A34: Total current assets other than assets held for sale | B34: =1*B25+1*B26+1*B27+1*B28+1*B29+1*B30+1*B31+1*B32+1*B33 | C34: =1*C25+1*C26+1*C27+1*C28+1*C29+1*C30+1*C31+1*C32+1*C33
A35: Non-current assets or disposal groups classified as held for sale or as held for distribution to owners
A36: *Total current assets | B36: =1*B25+1*B26+1*B27+1*B28+1*B29+1*B30+1*B31+1*B32+1*B33+1*B35 | C36: =1*C25+1*C26+1*C27+1*C28+1*C29+1*C30+1*C31+1*C32+1*C33+1*C35
A37: *Total assets | B37: =1*B8+1*B9+1*B11+1*B12+1*B13+1*B14+1*B15+1*B16+1*B17+1*B18+1*B19+1*B20+1*B21+1*B22+1*B25+1*B27+1*B28+1*B29+1*B30+1*B31+1*B32+1*B33+1*B35+1*B26+1*B10 | C37: =1*C8+1*C9+1*C11+1*C12+1*C13+1*C14+1*C15+1*C16+1*C17+1*C18+1*C19+1*C20+1*C21+1*C22+1*C25+1*C27+1*C28+1*C29+1*C30+1*C31+1*C32+1*C33+1*C35+1*C26+1*C10
A38: Equity and liabilities
A39: Equity
A40: *Issued capital | B40: ='SOFP-Sub-CuNonCu'!B203 | C40: ='SOFP-Sub-CuNonCu'!C203
A41: *Retained earnings | B41: 367463131 | C41: 334189137 | D41: Page 16, Retained earnings
A42: Treasury shares
A43: *Reserves | B43: ='SOFP-Sub-CuNonCu'!B222 | C43: ='SOFP-Sub-CuNonCu'!C222
A44: *Total equity attributable to owners | B44: =1*B40+1*B41+-1*B42+1*B43 | C44: =1*C40+1*C41+-1*C42+1*C43
A45: *Equity - other components | B45: ='SOFP-Sub-CuNonCu'!B229 | C45: ='SOFP-Sub-CuNonCu'!C229
A46: *Non-controlling interests | B46: 66971960 | C46: 64576642 | D46: Page 16, Non-controlling interests
A47: *Total equity | B47: =1*B40+1*B41+-1*B42+1*B43+1*B45+1*B46 | C47: =1*C40+1*C41+-1*C42+1*C43+1*C45+1*C46
A48: Liabilities
A49: Non-current liabilities
A50: Service concession liabilities
A51: *Borrowings | B51: ='SOFP-Sub-CuNonCu'!B271 | C51: ='SOFP-Sub-CuNonCu'!C271
A52: Lease liabilities | B52: 10704697 | C52: 4273776 | D52: Page 17, Lease liabilities
A53: *Employee benefit liabilities | B53: ='SOFP-Sub-CuNonCu'!B280 | C53: ='SOFP-Sub-CuNonCu'!C280
A54: *Provisions | B54: ='SOFP-Sub-CuNonCu'!B289 | C54: ='SOFP-Sub-CuNonCu'!C289
A55: *Trade and other non-current payables | B55: ='SOFP-Sub-CuNonCu'!B321 | C55: ='SOFP-Sub-CuNonCu'!C321
A56: Contract liabilities
A57: Deferred tax liabilities | B57: 22882200 | C57: 23954306 | D57: Page 17, Deferred tax liabilities
A58: *Derivative financial liabilities | B58: ='SOFP-Sub-CuNonCu'!B336 | C58: ='SOFP-Sub-CuNonCu'!C336
A59: Other non-current liabilities
A60: *Total non-current liabilities | B60: =1*B50+1*B51+1*B52+1*B53+1*B54+1*B55+1*B56+1*B57+1*B58+1*B59 | C60: =1*C50+1*C51+1*C52+1*C53+1*C54+1*C55+1*C56+1*C57+1*C58+1*C59
A61: Current liabilities
A62: *Borrowings | B62: ='SOFP-Sub-CuNonCu'!B383 | C62: ='SOFP-Sub-CuNonCu'!C383
A63: Lease liabilities | B63: 9017240 | C63: 9046505 | D63: Page 17, Lease liabilities
A64: *Employee benefit liabilities | B64: ='SOFP-Sub-CuNonCu'!B392 | C64: ='SOFP-Sub-CuNonCu'!C392
A65: *Provisions | B65: ='SOFP-Sub-CuNonCu'!B401 | C65: ='SOFP-Sub-CuNonCu'!C401
A66: Current tax liabilities | B66: 3270546 | C66: 325394 | D66: Page 17, Current tax liabilities
A67: *Trade and other current payables | B67: ='SOFP-Sub-CuNonCu'!B437 | C67: ='SOFP-Sub-CuNonCu'!C437
A68: Contract liabilities
A69: *Derivative financial liabilities | B69: ='SOFP-Sub-CuNonCu'!B452 | C69: ='SOFP-Sub-CuNonCu'!C452
A70: Other current liabilities
A71: Total current liabilities other than liabilities held for sale | B71: =1*B62+1*B63+1*B64+1*B65+1*B66+1*B67+1*B68+1*B69+1*B70 | C71: =1*C62+1*C63+1*C64+1*C65+1*C66+1*C67+1*C68+1*C69+1*C70
A72: *Liabilities included in disposal groups classified as held for sale
A73: *Total current liabilities | B73: =1*B62+1*B63+1*B64+1*B65+1*B66+1*B67+1*B68+1*B69+1*B70+1*B72 | C73: =1*C62+1*C63+1*C64+1*C65+1*C66+1*C67+1*C68+1*C69+1*C70+1*C72
A74: *Total liabilities | B74: =1*B60+1*B73 | C74: =1*C60+1*C73
A75: *Total equity and liabilities | B75: =1*B47+1*B74 | C75: =1*C47+1*C74

Sheet SOFP-Sub-CuNonCu
B1: 01/01/YYYY - 31/12/YYYY | C1: 01/01/YYYY - 31/12/YYYY | D1: Source
A3: Sub-classification of assets, liabilities and equity
A4: Statement on sub-classification of assets, liabilities and equity
A5: Statement on sub-classification of assets, liabilities and equity
A6: Sub-classification of assets, liabilities and equity
A7: Property, plant and equipment
A8: Land and buildings
A9: Land
A10: Freehold land
A11: Long term leasehold land | B11: 123176785 | C11: 124922976 | D11: Page 55, Leasehold land
A12: Short term leasehold land
A13: *Land | B13: =1*B10+1*B11+1*B12 | C13: =1*C10+1*C11+1*C12
A14: Buildings
A15: Building on freehold land | D15: Page 55, Freehold land and buildings
A16: Building on long term leasehold land | B16: 161844458 | C16: 166552509 | D16: Page 55, Leasehold buildings
A17: Building on short term leasehold land
A18: Leased properties
A19: Total buildings | B19: =1*B15+1*B16+1*B17+1*B18 | C19: =1*C15+1*C16+1*C17+1*C18
A20: *Total land and buildings | B20: =1*B13+1*B19 | C20: =1*C13+1*C19
A21: Vehicles
A22: Vessels
A23: Aircraft
A24: Motor vehicles | B24: 23259576 | C24: 20860498 | D24: Page 55, Motor vehicles
A25: Other vehicles
A26: *Total vehicles | B26: =1*B22+1*B23+1*B24+1*B25 | C26: =1*C22+1*C23+1*C24+1*C25
A27: Machinery
A28: Plant and equipment | B28: 26066561 | C28: 30273924 | D28: Page 55, Plant and machinery
A29: Office equipment, fixture and fittings | B29: 13010753 | C29: 12374699 | D29: Page 55, Office equipment, furniture and fittings
A30: Computer software and hardware
A31: Bearer plants
A32: Infrastructure and site facilities
A33: Mining assets
A34: Oil and gas assets
A35: Tangible exploration and evaluation assets
A36: Telecommunication equipments
A37: Construction in progress/Asset work-in progress
A38: Other property, plant and equipment | B38: 44612073 | C38: 21634508 | D38: Page 55, Air conditioners, office renovation and pallets
A39: *Total property, plant and equipment | B39: =1*B20+1*B26+1*B27+1*B28+1*B29+1*B30+1*B31+1*B32+1*B33+1*B34+1*B35+1*B36+1*B37+1*B38 | C39: =1*C20+1*C26+1*C27+1*C28+1*C29+1*C30+1*C31+1*C32+1*C33+1*C34+1*C35+1*C36+1*C37+1*C38
A40: Investment property
A41: Investment properties completed, at carrying value
A42: Freehold land and building
A43: Leasehold land and building
A44: Total investment properties completed, at carrying value | B44: =1*B42+1*B43 | C44: =1*C42+1*C43
A45: Investment properties under construction or development, at cost
A46: Building under construction
A47: Total investment properties under construction or development, at cost | B47: =1*B46 | C47: =1*C46
A48: Other investment property
A49: *Total investment properties | B49: =1*B44+1*B47+1*B48 | C49: =1*C44+1*C47+1*C48
A50: Biological assets
A51: Consumable biological assets
A52: Bearer biological assets
A53: Total biological assets | B53: =1*B51+1*B52 | C53: =1*C51+1*C52
A54: Intangible assets and goodwill
A55: Intangible assets other than goodwill
A56: Customer acquisition costs
A57: Brand names
A58: Customer relationships
A59: Copyrights, patents and other industrial property rights, service and operating rights
A60: Intangible assets under development
A61: Intangible exploration and evaluation assets
A62: Licences and franchises
A63: Recipes, formulae, models, designs and prototypes
A64: Computer software
A65: Small holder relationship
A66: Other intangible assets
A67: *Total intangible assets other than goodwill | B67: =1*B56+1*B57+1*B58+1*B59+1*B60+1*B61+1*B62+1*B63+1*B64+1*B65+1*B66 | C67: =1*C56+1*C57+1*C58+1*C59+1*C60+1*C61+1*C62+1*C63+1*C64+1*C65+1*C66
A68: Goodwill | B68: 81864054 | C68: 81864054 | D68: Page 16, Goodwill
A69: *Total intangible assets and goodwill | B69: =1*B67+1*B68 | C69: =1*C67+1*C68
A70: Investments in subsidiaries
A71: Unquoted shares, net of impairment losses
A72: Quoted shares in Malaysia
A73: Quoted shares outside Malaysia
A74: Fair value adjustments on loans and advances and financial guarantee
A75: Contributions to subsidiaries, net of impairment losses
A76: Other investments in subsidiaries
A77: *Total investments in subsidiaries | B77: =1*B71+1*B72+1*B73+1*B74+1*B75+1*B76 | C77: =1*C71+1*C72+1*C73+1*C74+1*C75+1*C76
A78: Investments in associates
A79: Unquoted shares, net of impairment losses | B79: 3000000 | C79: 3000000 | D79: Page 62, Note 9, Unquoted shares
A80: Quoted shares in Malaysia
A81: Quoted shares outside Malaysia
A82: Fair value adjustments on loans and advances and financial guarantee
A83: Share of post-acquisition profits and reserves | B83: 196691 | C83: 47985 | D83: Page 62, Note 9, Group's share of results
A84: Unrealised profit on transactions with associates
A85: Other investments in associates
A86: *Total investments in associates | B86: =1*B79+1*B80+1*B81+1*B82+1*B83+1*B84+1*B85 | C86: =1*C79+1*C80+1*C81+1*C82+1*C83+1*C84+1*C85
A87: Investments in joint ventures
A88: Unquoted shares, net of impairment losses | B88: 400000 | C88: 400000 | D88: Page 63, Note 10, Unquoted shares
A89: Quoted shares in Malaysia
A90: Quoted shares outside Malaysia
A91: Fair value adjustments on loans and advances and financial guarantee
A92: Share of post-acquisition profits and reserves | B92: -47780 | C92: -191020 | D92: Page 63, Note 10, Group's share of results
A93: Unrealised profit on transactions with joint ventures
A94: Other investments in joint ventures | B94: 3080000 | C94: 3080000 | D94: Page 63, Note 10, Equity contribution
A95: *Total investments in joint ventures | B95: =1*B88+1*B89+1*B90+1*B91+1*B92+1*B93+1*B94 | C95: =1*C88+1*C89+1*C90+1*C91+1*C92+1*C93+1*C94
A96: Trade and other non-current receivables
A97: Non-current trade receivables
A98: Trade receivables
A99: Trade receivables due from holding company
A100: Trade receivables due from subsidiaries
A101: Trade receivables from associates
...

Sheet SOPL-Function
B1: 01/01/YYYY - 31/12/YYYY | C1: 01/01/YYYY - 31/12/YYYY | D1: Source
A3: Statement of profit or loss, by function of expense
A4: Statement of Profit or Loss
A5: Statement of profit or loss
A6: Continuing operations
A7: *Revenue | B7: ='SOPL-Analysis-Function'!B40 | C7: ='SOPL-Analysis-Function'!C40
A8: *Cost of sales | B8: ='SOPL-Analysis-Function'!B47 | C8: ='SOPL-Analysis-Function'!C47
A9: *Gross profit | B9: =1*B7+-1*B8 | C9: =1*C7+-1*C8
A10: *Other income | B10: ='SOPL-Analysis-Function'!B90 | C10: ='SOPL-Analysis-Function'!C90
A11: Selling and distribution expenses
A12: *Administrative expenses | B12: 75369006 | C12: 71956154 | D12: Page 18, Total 77,098,623 less Analysis-Other-Expenses 5,142,469
A13: Research and development expense
A14: *Other expenses | B14: ='SOPL-Analysis-Function'!B134 | C14: ='SOPL-Analysis-Function'!C134
A15: *Profit (loss) from operating activities | B15: =1*B7+-1*B8+1*B10+-1*B11+-1*B12+-1*B13+-1*B14 | C15: =1*C7+-1*C8+1*C10+-1*C11+-1*C12+-1*C13+-1*C14
A16: *Finance income | B16: ='SOPL-Analysis-Function'!B138 | C16: ='SOPL-Analysis-Function'!C138
A17: *Finance costs | B17: 14396928 | C17: 18347594 | D17: Page 18
A18: Share of profit (loss) of associates and joint ventures accounted for using equity method | B18: 291946 | C18: -302060 | D18: Page 18
A19: Fair valuation gain (loss) arising from distribution of non-cash assets to owners
A20: *Profit (loss) before tax | B20: =1*B7+-1*B8+1*B10+-1*B11+-1*B12+-1*B13+-1*B14+1*B16+-1*B17+1*B18+1*B19 | C20: =1*C7+-1*C8+1*C10+-1*C11+-1*C12+-1*C13+-1*C14+1*C16+-1*C17+1*C18+1*C19
A21: *Tax expense | B21: 17020092 | C21: 10691638 | D21: Page 18
A22: Contribution of zakat
A23: *Profit (loss) from continuing operations | B23: =1*B20+-1*B21+-1*B22 | C23: =1*C20+-1*C21+-1*C22
A24: Discontinued operations
A25: Profit (loss) from discontinued operations, net of tax
A26: *Profit (loss) | B26: =1*B23+1*B25 | C26: =1*C23+1*C25
A27: Profit (loss), attributable to
A28: Profit (loss), attributable to owners of parent | B28: 41273994 | C28: 8891310 | D28: Page 19
A29: Profit (loss) attributable to equity other components
A30: Profit (loss), attributable to non-controlling interests | B30: 2395318 | C30: 1014833 | D30: Page 19
A31: *Total profit (loss) | B31: =1*B28+1*B29+1*B30 | C31: =1*C28+1*C29+1*C30
A32: Earnings per share
A33: Basic earnings per share
A34: Basic earnings (loss) per share from continuing operations | B34: 5.16 | C34: 1.11 | D34: Page 19
A35: Basic earnings (loss) per share from discontinued operations
A36: *Total basic earnings (loss) per share | B36: =1*B35 | C36: =1*C35
A37: Diluted earnings per share
A38: Diluted earnings (loss) per share from continuing operations
A39: Diluted earnings (loss) per share from discontinued operations
A40: *Total diluted earnings (loss) per share | B40: =1*B39 | C40: =1*C39

Sheet SOPL-Analysis-Function
B1: 01/01/YYYY - 31/12/YYYY | C1: 01/01/YYYY - 31/12/YYYY | D1: Source
A3: Analysis of profit or loss, by function of expense
A4: Analysis of profit or loss
A5: Statement of profit or loss
A6: Revenue
A7: Revenue from sale of goods
A8: Revenue from sale of broadband and telecommunication
A9: Revenue from property development
A10: Revenue from construction contracts
A11: Revenue from clean water, treatment and disposal of waste water
A12: Revenue from sale of food and beverage
A13: Revenue from sale of agricultural produce
A14: Revenue from sale of oil and gas products
A15: Revenue from sale of other goods
A16: Total revenue from sale of goods | B16: =1*B8+1*B9+1*B10+1*B11+1*B12+1*B13+1*B14+1*B15 | C16: =1*C8+1*C9+1*C10+1*C11+1*C12+1*C13+1*C14+1*C15
A17: Revenue from rendering of services
A18: Revenue from rendering of entertainment services
A19: Revenue from rendering of telecommunication services
A20: Revenue from rendering of transport services
A21: Revenue from rendering of information technology services
A22: Revenue from rendering of educational services
A23: Revenue from rendering of healthcare services
A24: Revenue from rendering of shipping and shipping related services
A25: Revenue from rendering of other services | B25: 946612167 | C25: 747438303 | D25: Page 18, Statement of Comprehensive Income
A26: Total revenue from rendering of services | B26: =1*B18+1*B19+1*B20+1*B21+1*B22+1*B23+1*B24+1*B25 | C26: =1*C18+1*C19+1*C20+1*C21+1*C22+1*C23+1*C24+1*C25
A27: Interest income | D27: Moving to Misc to ensure inclusion in total
A28: Interest income on loans, advances and financing
A29: Interest income on other financial assets
A30: Total interest income | B30: =1*B28+1*B29 | C30: =1*C28+1*C29
A31: Other fee and commission income
A32: Gross brokerage and other charges
A33: Underwriting commissions and fund management income
A34: Other fee and commission income
A35: Total other fee and commission income | B35: =1*B32+1*B33+1*B34 | C35: =1*C32+1*C33+1*C34
A36: Dividend income
A37: Rental income
A38: Royalty income
A39: Other revenue
A40: *Total revenue | B40: =1*B16+1*B26+1*B30+1*B35+1*B36+1*B37+1*B38+1*B39 | C40: =1*C16+1*C26+1*C30+1*C35+1*C36+1*C37+1*C38+1*C39
A41: Cost of sales
A42: Cost of inventories
A43: Construction contract costs
A44: Energy costs
A45: Property development costs
A46: Other cost of sales | B46: 795446580 | C46: 638136490 | D46: Page 18, Statement of Comprehensive Income
A47: *Total cost of sales | B47: =1*B42+1*B43+1*B44+1*B45+1*B46 | C47: =1*C42+1*C43+1*C44+1*C45+1*C46
A48: Other income
A49: Deferred income
A50: Bad debts recovered | B50: 818137 | C50: 69883 | D50: Page 76, Note 27
A51: Dividend income | B51: 36600 | D51: Page 76, Note 27
A52: Royalty/franchise income
A53: Write back of fuel cost
A54: Income from reimbursements under insurance policies
A55: Grant or incentives by Malaysian government or it's agencies | B55: 664800 | D55: Page 76, Note 27
A56: Grant or incentives by foreign government or it's agencies
A57: Contributions or donations by local contributor
A58: Contributions or donations by foreign contributor
A59: Contributions or donations by unknown contributor
A60: Foreign exchange gain
A61: Realised gain on foreign exchange | C61: 551992 | D61: Page 76, Note 27
A62: Unrealised gain on foreign exchange | C62: 1219222 | D62: Page 76, Note 27
A63: Total foreign exchange gain | B63: =1*B61+1*B62 | C63: =1*C61+1*C62
A64: Gain on disposal of subsidiaries, associates and joint ventures
A65: Gain on disposal of subsidiaries
A66: Gain on disposal of associates
A67: Gain on disposal of joint ventures
A68: Total gain on disposal of subsidiaries, associates and joint ventures | B68: =1*B65+1*B66+1*B67 | C68: =1*C65+1*C66+1*C67
A69: Gain on disposal from other investments
A70: Gains on disposals of property, plant and equipment | B70: 809323 | C70: 648816 | D70: Page 76, Note 27
A71: Gains on disposals of other non-current assets
A72: Other gains recognised in profit or loss, fair value measurement, assets | B72: 108626 | C72: 174436 | D72: Page 76, Note 27
A73: Reversal of impairment loss recognised in profit or loss
A74: Reversal of impairment loss on receivables
A75: Reversal of impairment in development expenditure
A76: Reversal of impairment in land held for property development
A77: Reversal of impairment in property, plant and equipment
A78: Reversal of impairment in other assets
A79: Total reversal of impairment loss recognised in profit or loss | B79: =1*B75+1*B76+1*B77+1*B78 | C79: =1*C75+1*C76+1*C77+1*C78
A80: Reversal of inventories written down to net realisable value
A81: Interest income
A82: Management fees
A83: Net deposits recognised
A84: Net fair value gain on derivatives
A85: Net fair value gain on recycle of forex reserve upon disposal of subsidiaries
A86: Other fee and commission
A87: Other rental income
A88: Rental income on land and buildings | B88: 24806 | C88: 23625 | D88: Page 76, Note 27
A89: Other miscellaneous income | B89: 1985623 | C89: 4356271 | D89: Note 27: Sundry 786,283 + Interest income 3,569,988
A90: *Total other income | B90: =1*B49+1*B50+1*B51+1*B52+1*B53+1*B54+1*B55+1*B56+1*B57+1*B58+1*B59+1*B63+1*B68+1*B69+1*B70+1*B71+1*B72+1*B99+1*B80+1*B81+1*B82+1*B85+1*B86+1*B87+1*B88+1*B89+1*B84+1*B83 | C90: =1*C49+1*C50+1*C51+1*C52+1*C53+1*C54+1*C55+1*C56+1*C57+1*C58+1*C59+1*C63+1*C68+1*C69+1*C70+1*C71+1*C72+1*C99+1*C80+1*C81+1*C82+1*C85+1*C86+1*C87+1*C88+1*C89+1*C84+1*C83
A91: Other expenses
A92: Auditor's remuneration
A93: Auditor's remuneration for audit services | B93: 254040 | C93: 259366 | D93: Page 77, Note 28
A94: Auditor's remuneration for other services | B94: 73670 | C94: 78970 | D94: Page 77, Note 28, Review 73,670 + Other 5,300
A95: *Total auditor's remuneration | B95: =1*B93+1*B94 | C95: =1*C93+1*C94
A96: Amortisation expense
A97: Depreciation, property, plant and equipment
A98: Natural disaster related expenses
A99: Loss on disposal of subsidiaries, associates and joint ventures
A100: Loss on disposal of subsidiaries
A101: Loss on disposal of associates
...

Sheet SOCI-NetOfTax
B1: 01/01/YYYY - 31/12/YYYY | C1: 01/01/YYYY - 31/12/YYYY | D1: Source
A3: Statement of comprehensive income, net of tax
A4: Comprehensive income net of tax [abstract]
A5: Statement of comprehensive income net of tax [line items]
A6: Statement of comprehensive income [abstract]
A7: Profit (loss) | B7: 43669312 | C7: 9906143 | D7: Page 18, Profit for the year, Group 2020
A8: Other comprehensive income [abstract]
A9: Components of other comprehensive income that will not be reclassified to profit or loss, net of tax [abstract]
A10: Other comprehensive income, net of tax, gains (losses) on revaluation of property, plant and equipment, right-of-use assets and intangible assets
A11: Total other comprehensive income, net of tax, gains (losses) on remeasurements of defined benefit plans
A12: Other comprehensive income, net of tax, gains (losses) from investments in equity instruments
A13: Other comprehensive income, net of tax, gains (losses) on other items
A14: Share of other comprehensive income of associates and joint ventures accounted for using equity method that will not be reclassified to profit or loss, net of tax
A15: Total other comprehensive income that will not be reclassified to profit or loss, net of tax | B15: =1*B12+1*B13+1*B14 | C15: =1*C12+1*C13+1*C14
A16: Components of other comprehensive income that will be reclassified to profit or loss, net of tax [abstract]
A17: Cash flow hedges [abstract]
A18: Gains (losses) on cash flow hedges, net of tax | B18: 0 | C18: 10941 | D18: Page 18, Fair value adjustment on cash flow hedge, Group 2020
A19: Reclassification adjustments on cash flow hedges, net of tax
A20: Other comprehensive income, net of tax, cash flow hedges | B20: =1*B18+1*B19 | C20: =1*C18+1*C19
A21: Hedges of net investment in foreign operations [abstract]
A22: Gains (losses) on hedges of net investments in foreign operations, net of tax
A23: Reclassification adjustments on hedges of net investments in foreign operations, net of tax
A24: Other comprehensive income, net of tax, hedges of net investments in foreign operations | B24: =1*B22+1*B23 | C24: =1*C22+1*C23
A25: Exchange differences on translation [abstract]
A26: Gains (losses) on exchange differences on translation of foreign operations, net of tax | B26: 643844 | C26: -602165 | D26: Page 18, Exchange difference on translation of foreign operation, Group 2020
A27: Reclassification adjustments on exchange differences on translation of foreign operations, net of tax
A28: Other comprehensive income, net of tax, exchange differences on translation of foreign operations
A29: Financial assets measured at fair value through other comprehensive income [abstract]
A30: Gains (losses) on financial assets measured at fair value through other comprehensive income, net of tax
A31: Reclassification adjustments on financial assets measured at fair value through other comprehensive income, net of tax
A32: Amounts removed from equity and adjusted against fair value of financial assets on reclassification out of fair value through other comprehensive income measurement category, net of tax
A33: Other comprehensive income, net of tax, financial assets measured at fair value through other comprehensive income | B33: =1*B26+1*B27+1*B28+1*B30+1*B31+1*B32 | C33: =1*C26+1*C27+1*C28+1*C30+1*C31+1*C32
A34: Share of other comprehensive income of associates and joint ventures accounted for using equity method that will be reclassified to profit or loss, net of tax
A35: Others comprehensive income, net of tax, gains (losses) on other items | B35: 643844 | C35: -591224 | D35: Page 18, Total other comprehensive income for the year, net of tax (reclassifiable), Group 2020. Comprises Exchange difference (602,165) and Cash flow hedge 10,941.
A36: Total other comprehensive income that will be reclassified to profit or loss, net of tax | B36: =1*B34+1*B35 | C36: =1*C34+1*C35
A37: Total other comprehensive income | B37: =1*B11+1*B15+1*B36 | C37: =1*C11+1*C15+1*C36
A38: Total comprehensive income | B38: =1*B7+1*B37 | C38: =1*C7+1*C37
A39: Comprehensive income attributable to [abstract]
A40: Total comprehensive income, attributable to owners of parent | D40: Page 19, Total comprehensive income attributable to Owners of the Company, Group 2020
A41: Total comprehensive income, attributable to non-controlling interests | D41: Page 19, Total comprehensive income attributable to Non-controlling interests, Group 2020
A42: Total comprehensive income | B42: =1*B40+1*B41 | C42: =1*C40+1*C41

Sheet SOCF-Indirect
B1: 01/01/YYYY - 31/12/YYYY | C1: 01/01/YYYY - 31/12/YYYY | D1: Source
A3: Statement of cash flows, indirect method
A4: Statement of cash flows
A5: Statement of cash flows
A6: Statement of cash flows
A7: Cash flows from (used in) operating activities
A8: *Profit (loss) before tax | B8: 60689404 | C8: 20597781 | D8: Page 22, Profit before tax
A9: *Total profit(loss) before tax | B9: =1*B8 | C9: =1*C8
A10: Adjustments to reconcile profit (loss)
A11: Adjustments for depreciation | B11: 39513711 | C11: 40680256 | D11: Page 22, Depreciation of PPE (31,002,867) + Depreciation of ROU assets (9,677,389)
A12: Adjustments for amortisation expense
A13: Adjustments for dividend income | B13: 36600 | C13: 0 | D13: Page 22, Dividend income
A14: Adjustments for equity settled share-based payment transactions
A15: Adjustments for changes in fair value of investment properties
A16: Adjustments for unrealised foreign exchange losses (gains) | B16: 2404500 | C16: -1219222 | D16: Page 22, Unrealised loss/(gain) on foreign exchange
A17: Adjustments for interest income | B17: 1201064 | C17: 3569988 | D17: Page 22, Interest income
A18: Adjustments for performance-based employee share scheme and other expenses
A19: Adjustments for share of profits of joint ventures (net of tax) | B19: -291946 | C19: 302060 | D19: Page 22, Share of results of associated company and joint venture (loss, so positive adjustment)
A20: Adjustments for share option expenses
A21: Adjustments for undistributed profits of associates
A22: Adjustments for finance costs | B22: 14396928 | C22: 18347594 | D22: Page 22, Interest expense
A23: Adjustments for finance income
A24: Short-term lease payments, payments for leases of low-value assets and variable lease payments not included in the measurement of the lease liability
A25: Adjustments for other non-current assets
A26: Adjustments for impairment loss (reversal of impairment loss) recognised in profit or loss
A27: Impairment (reversal of impairment) of property, plant and equipment
A28: Impairment (reversal of impairment) of investment properties
A29: Impairment (reversal of impairment) of prepaid lease rentals
A30: Impairment (reversal of impairment) of intangible assets
A31: Impairment (reversal of impairment) of investment in subsidiaries
A32: Impairment (reversal of impairment) of investment in associates
A33: Impairment (reversal of impairment) of investment in joint ventures
A34: Impairment (reversal of impairment) of other investments
A35: Impairment (reversal of impairment) of other financial assets or receivables | B35: 362401 | C35: 702780 | D35: Page 22, Allowance for doubtful debts
A36: Total adjustment for impairment (reversal of impairment) | B36: =1*B28+1*B29+1*B30+1*B31+1*B32+1*B33+1*B34+1*B35 | C36: =1*C28+1*C29+1*C30+1*C31+1*C32+1*C33+1*C34+1*C35
A37: Adjustments for losses (gains) on disposal of non-current assets
A38: (Gain) loss on disposal of property, plant and equipment | B38: -809323 | C38: -648816 | D38: Page 22, Gain on disposal of property, plant and equipment
A39: (Gain) loss on disposal of investment properties
A40: Total gain (loss) on disposal of non-current assets | B40: =1*B38+1*B39 | C40: =1*C38+1*C39
A41: (Gain) loss on disposal of subsidiaries | B41: 824860 | C41: 0 | D41: Page 22, Loss on derecognition of subsidiary
A42: (Gain) loss on disposal of associates
A43: (Gain) loss on disposal of joint ventures
A44: Gain on disposal of other investments
A45: Realised foreign currencies exchange gain transferred from equity
A46: Other adjustments for non-cash items
A47: Write–off:
A48: Write offs of property, plant and equipment | B48: 194208 | C48: 58618 | D48: Page 22, Property, plant and equipment written off
A49: Write offs of intangible assets
A50: Write offs of investments
A51: Write offs of inventories
A52: Write off of trade and other receivables | B52: 147213 | C52: 196771 | D52: Page 22, Bad debts written off
A53: Write offs of other financial assets
A54: Total write-off | B54: =1*B48+1*B49+1*B50+1*B51+1*B52+1*B53 | C54: =1*C48+1*C49+1*C50+1*C51+1*C52+1*C53
A55: Write back of expenses
A56: Other adjustments to reconcile profit (loss) | B56: -52461 | C56: -174436 | D56: Page 22, FV gain investments (-174,436)
A57: *Total adjustments to reconcile profit (loss) | B57: =1*B11+1*B12+-1*B13+1*B14+-1*B15+1*B16+-1*B17+1*B18+1*B19+1*B20+-1*B21+1*B22+-1*B23+-1*B24+1*B25+1*B56+-1*B60+-1*B41+-1*B42+-1*B43+-1*B44+-1*B45+1*B46+1*B54+1*B55+1*B56 | C57: =1*C11+1*C12+-1*C13+1*C14+-1*C15+1*C16+-1*C17+1*C18+1*C19+1*C20+-1*C21+1*C22+-1*C23+-1*C24+1*C25+1*C56+-1*C60+-1*C41+-1*C42+-1*C43+-1*C44+-1*C45+1*C46+1*C54+1*C55+1*C56
A58: *Operating surplus (deficit) before working capital changes | B58: =1*B9+1*B57 | C58: =1*C9+1*C57
A59: Changes in working capital
A60: Adjustments for decrease (increase) in inventories
A61: Adjustments for decrease (increase) in trade and other receivables | B61: 75654699 | C61: -3898981 | D61: Page 22, Changes in receivables (positive means decrease)
A62: Adjustments for increase (decrease) in trade and other payables | B62: -44479662 | C62: 6923397 | D62: Page 22, Changes in payables (negative means decrease)
A63: Adjustments for decrease (increase) in property development costs
A64: Adjustments for decrease (increase) in contract assets
A65: Adjustments for decrease (increase) in contract liabilities
A66: *Total changes in working capital | B66: =-1*B60+-1*B61+-1*B62+-1*B63+-1*B64+-1*B65 | C66: =-1*C60+-1*C61+-1*C62+-1*C63+-1*C64+-1*C65
A67: *Cash generated from (used in) operations | B67: =1*B58+1*B66 | C67: =1*C58+1*C66
A68: Dividends received
A69: Dividends paid
A70: Interest received | B70: 952139 | C70: 1540298 | D70: Page 22, Interest received
A71: Interest paid
A72: Payment to a retirement benefits scheme
A73: Income taxes refund (paid) | B73: -13636579 | C73: -3323074 | D73: Page 22, Net tax (paid)/refund
A74: Other cash inflows (outflows) from operating activities
A75: *Net cash flows from (used in) operating activities | B75: =1*B24+1*B68+1*B69+1*B70+1*B71+1*B72+1*B73+1*B74+1*B67 | C75: =1*C24+1*C68+1*C69+1*C70+1*C71+1*C72+1*C73+1*C74+1*C67
A76: Cash flows from (used in) investing activities
A77: Proceeds from disposal of subsidiaries
A78: Acquisition and subscription of shares in subsidiaries
A79: Proceeds from disposal of associates
A80: Acquisition and subscription of shares in associates
A81: Proceeds from disposal of joint ventures
A82: Acquisition and subscription of shares in joint ventures
A83: Cash receipts from repayment of advances and loans made to other parties, classified as investing activities
A84: Cash advances and loans made to other parties
A85: Deposit placed with investment brokers
A86: Other cash payments to acquire equity or debt instruments of other entities
A87: Other cash receipts from sales of equity or debt instruments of other entities
... A92: Proceeds from sales of other non-current assets
A93: Proceeds from sales of property, plant and equipment | B93: 989152 | C93: 1569714 | D93: Page 23, Proceeds from disposal of property, plant and equipment
A94: Proceeds from sale of prepaid lease payments
A95: Purchase of intangible assets
A96: Purchase of other non-current assets
A97: Purchase of property, plant and equipment | B97: 41100888 | C97: 8906592 | D97: Page 23, Purchase of property, plant and equipment
A98: Dividends received | B98: 36600 | C98: 0 | D98: Page 23, Dividends received
A99: Interest received | B99: 248925 | C99: 2029690 | D99: Page 23, Interest received
A100: Proceeds from sale of other investment | B100: 24000 | C100: 0 | D100: Page 23, Proceeds from disposal of other investment
A101: Purchase of other investment
A102: Development expenditure incurred
A103: Net repayment from joint ventures
A104: Net repayment from associates
A105: Capital distributions from associates
...

Sheet SOCIE
B1: 01/01/YYYY - 31/12/YYYY
B2: Issued capital | C2: Retained earnings | D2: Treasury shares | E2: Capital reserve | F2: Hedging reserve | G2: Foreign currency translation reserve | H2: Reserve of share-based payments | I2: Revaluation surplus | J2: Statutory reserve | K2: Warrant reserve | L2: Other non-distributable reserves | M2: Sub-total of non-distributable reserves | N2: Fair value reserve | O2: Reserve of non-current assets classified as held for sale | P2: Consolidation reserve | Q2: Warranty reserve | R2: Other distributable reserves | S2: Sub-Total of distributable reserves | T2: Reserves | U2: Equity attributable to owners | V2: Equity, others components | W2: Non-controlling interests | X2: Total
A3: Statement of changes in equity
A4: Statement of changes in equity
A5: Statement of changes in equity
A6: *Equity at beginning of period | B6: 100801317 | C6: 334189137 | M6: =SUM(E6:L6) | S6: =SUM(N6:R6) | T6: =M6+S6 | U6: =B6+C6+D6+T6 | X6: =U6+V6+W6
A7: *Impact of changes in accounting policies | M7: =SUM(E7:L7) | S7: =SUM(N7:R7) | T7: =M7+S7 | U7: =B7+C7+D7+T7 | X7: =U7+V7+W7
A8: *Equity at beginning of period, restated | B8: =B6+B7 | C8: =C6+C7 | D8: =D6+D7 | E8: =E6+E7 | F8: =F6+F7 | G8: =G6+G7 | H8: =H6+H7 | I8: =I6+I7 | ... L8: =L6+L7 | M8: =SUM(E8:L8) | N8: =N6+N7 | O8: =O6+O7 | P8: =P6+P7 | Q8: =Q6+Q7 | R8: =R6+R7 | S8: =SUM(N8:R8) | T8: =M8+S8 | U8: =B8+C8+D8+T8 | V8: =V6+V7 | W8: =W6+W7 | X8: =U8+V8+W8
A9: Changes in equity
A10: Comprehensive income
A11: *Profit (loss) | C11: 41273994 | M11: =SUM(E11:L11) | S11: =SUM(N11:R11) | T11: =M11+S11 | U11: =B11+C11+D11+T11 | X11: =U11+V11+W11
A12: *Total other comprehensive income | M12: =SUM(E12:L12) | S12: =SUM(N12:R12) | T12: =M12+S12 | U12: =B12+C12+D12+T12 | X12: =U12+V12+W12
A13: *Total comprehensive income | B13: =B11+B12 | C13: =C11+C12 | D13: =D11+D12 | E13: =E11+E12 | F13: =F11+F12 | G13: =G11+G12 | H13: =H11+H12 | I13: =I11+I12 | ... L13: =L11+L12 | M13: =SUM(E13:L13) | N13: =N11+N12 | O13: =O11+O12 | P13: =P11+P12 | Q13: =Q11+Q12 | R13: =R11+R12 | S13: =SUM(N13:R13) | T13: =M13+S13 | U13: =B13+C13+D13+T13 | V13: =V11+V12 | W13: =W11+W12 | X13: =U13+V13+W13
A14: Contributions by and distributions to owners
A15: Acquisition (dilution) of equity interest in subsidiaries | M15: =SUM(E15:L15) | S15: =SUM(N15:R15) | T15: =M15+S15 | U15: =B15+C15+D15+T15 | X15: =U15+V15+W15
A16: Arising from conversion of Irredeemable Convertible Unsecured Loan Stock (ICULS) | M16: =SUM(E16:L16) | S16: =SUM(N16:R16) | T16: =M16+S16 | U16: =B16+C16+D16+T16 | X16: =U16+V16+W16
A17: Dividends paid | C17: 8000000 | M17: =SUM(E17:L17) | S17: =SUM(N17:R17) | T17: =M17+S17 | U17: =B17+C17+D17+T17 | X17: =U17+V17+W17
A18: Issuance of shares | M18: =SUM(E18:L18) | S18: =SUM(N18:R18) | T18: =M18+S18 | U18: =B18+C18+D18+T18 | X18: =U18+V18+W18
A19: Issue of convertible notes, net of tax | M19: =SUM(E19:L19) | S19: =SUM(N19:R19) | T19: =M19+S19 | U19: =B19+C19+D19+T19 | X19: =U19+V19+W19
A20: Increase (decrease) through share-based payment transactions, equity | M20: =SUM(E20:L20) | S20: =SUM(N20:R20) | T20: =M20+S20 | U20: =B20+C20+D20+T20 | X20: =U20+V20+W20
A21: Treasury shares transactions | M21: =SUM(E21:L21) | S21: =SUM(N21:R21) | T21: =M21+S21 | U21: =B21+C21+D21+T21 | X21: =U21+V21+W21
A22: Other transactions with owners | M22: =SUM(E22:L22) | S22: =SUM(N22:R22) | T22: =M22+S22 | U22: =B22+C22+D22+T22 | X22: =U22+V22+W22
A23: Increase (decrease) through other changes, equity | M23: =SUM(E23:L23) | S23: =SUM(N23:R23) | T23: =M23+S23 | U23: =B23+C23+D23+T23 | X23: =U23+V23+W23
A24: *Total increase (decrease) in equity | B24: =1*B13+1*B15+1*B16+-1*B17+1*B18+1*B19+1*B20+1*B21+1*B22+1*B23 | C24: =1*C13+1*C15+1*C16+-1*C17+1*C18+1*C19+1*C20+1*C21+1*C22+1*C23 | D24: =1*D13+1*D15+1*D16+-1*D17+1*D18+1*D19+1*D20+1*D21+1*D22+1*D23 | E24: =1*E13+1*E15+1*E16+-1*E17+1*E18+1*E19+1*E20+1*E21+1*E22+1*E23 | F24: =1*F13+1*F15+1*F16+-1*F17+1*F18+1*F19+1*F20+1*F21+1*F22+1*F23 | G24: =1*G13+1*G15+1*G16+-1*G17+1*G18+1*G19+1*G20+1*G21+1*G22+1*G23 | H24: =1*H13+1*H15+1*H16+-1*H17+1*H18+1*H19+1*H20+1*H21+1*H22+1*H23 | I24: =1*I13+1*I15+1*I16+-1*I17+1*I18+1*I19+1*I20+1*I21+1*I22+1*I23 | ... L24: =1*L13+1*L15+1*L16+-1*L17+1*L18+1*L19+1*L20+1*L21+1*L22+1*L23 | M24: =SUM(E24:L24) | N24: =1*N13+1*N15+1*N16+-1*N17+1*N18+1*N19+1*N20+1*N21+1*N22+1*N23 | O24: =1*O13+1*O15+1*O16+-1*O17+1*O18+1*O19+1*O20+1*O21+1*O22+1*O23 | P24: =1*P13+1*P15+1*P16+-1*P17+1*P18+1*P19+1*P20+1*P21+1*P22+1*P23 | Q24: =1*Q13+1*Q15+1*Q16+-1*Q17+1*Q18+1*Q19+1*Q20+1*Q21+1*Q22+1*Q23 | R24: =1*R13+1*R15+1*R16+-1*R17+1*R18+1*R19+1*R20+1*R21+1*R22+1*R23 | S24: =SUM(N24:R24) | T24: =M24+S24 | U24: =B24+C24+D24+T24 | V24: =1*V13+1*V15+1*V16+-1*V17+1*V18+1*V19+1*V20+1*V21+1*V22+1*V23 | W24: =1*W13+1*W15+1*W16+-1*W17+1*W18+1*W19+1*W20+1*W21+1*W22+1*W23 | X24: =U24+V24+W24
A25: *Equity at end of period | B25: =B8+B24 | C25: =C8+C24 | D25: =D8+D24 | E25: =E8+E24 | F25: =F8+F24 | G25: =G8+G24 | H25: =H8+H24 | I25: =I8+I24 | ... L25: =L8+L24 | M25: =SUM(E25:L25) | N25: =N8+N24 | O25: =O8+O24 | P25: =P8+P24 | Q25: =Q8+Q24 | R25: =R8+R24 | S25: =SUM(N25:R25) | T25: =M25+S25 | U25: =B25+C25+D25+T25 | V25: =V8+V24 | W25: =W8+W24 | X25: =U25+V25+W25
A27: Statement of changes in equity
A28: Statement of changes in equity
A29: Statement of changes in equity
A30: *Equity at beginning of period | M30: =SUM(E30:L30) | S30: =SUM(N30:R30) | T30: =M30+S30 | U30: =B30+C30+D30+T30 | X30: =U30+V30+W30
A31: *Impact of changes in accounting policies | M31: =SUM(E31:L31) | S31: =SUM(N31:R31) | T31: =M31+S31 | U31: =B31+C31+D31+T31 | X31: =U31+V31+W31
A32: *Equity at beginning of period, restated | B32: =B30+B31 | C32: =C30+C31 | D32: =D30+D31 | E32: =E30+E31 | F32: =F30+F31 | G32: =G30+G31 | H32: =H30+H31 | I32: =I30+I31 | ... L32: =L30+L31 | M32: =SUM(E32:L32) | N32: =N30+N31 | O32: =O30+O31 | P32: =P30+P31 | Q32: =Q30+Q31 | R32: =R30+R31 | S32: =SUM(N32:R32) | T32: =M32+S32 | U32: =B32+C32+D32+T32 | V32: =V30+V31 | W32: =W30+W31 | X32: =U32+V32+W32
A33: Changes in equity
A34: Comprehensive income
A35: *Profit (loss) | M35: =SUM(E35:L35) | S35: =SUM(N35:R35) | T35: =M35+S35 | U35: =B35+C35+D35+T35 | X35: =U35+V35+W35
A36: *Total other comprehensive income | M36: =SUM(E36:L36) | S36: =SUM(N36:R36) | T36: =M36+S36 | U36: =B36+C36+D36+T36 | X36: =U36+V36+W36
A37: *Total comprehensive income | B37: =B35+B36 | C37: =C35+C36 | D37: =D35+D36 | E37: =E35+E36 | F37: =F35+F36 | G37: =G35+G36 | H37: =H35+H36 | I37: =I35+I36 | ... L37: =L35+L36 | M37: =SUM(E37:L37) | N37: =N35+N36 | O37: =O35+O36 | P37: =P35+P36 | Q37: =Q35+Q36 | R37: =R35+R36 | S37: =SUM(N37:R37) | T37: =M37+S37 | U37: =B37+C37+D37+T37 | V37: =V35+V36 | W37: =W35+W36 | X37: =U37+V37+W37
A38: Contributions by and distributions to owners
A39: Acquisition (dilution) of equity interest in subsidiaries | M39: =SUM(E39:L39) | S39: =SUM(N39:R39) | T39: =M39+S39 | U39: =B39+C39+D39+T39 | X39: =U39+V39+W39
A40: Arising from conversion of Irredeemable Convertible Unsecured Loan Stock (ICULS) | M40: =SUM(E40:L40) | S40: =SUM(N40:R40) | T40: =M40+S40 | U40: =B40+C40+D40+T40 | X40: =U40+V40+W40
A41: Dividends paid | C41: 5000000 | M41: =SUM(E41:L41) | S41: =SUM(N41:R41) | T41: =M41+S41 | U41: =B41+C41+D41+T41 | X41: =U41+V41+W41
A42: Issuance of shares | M42: =SUM(E42:L42) | S42: =SUM(N42:R42) | T42: =M42+S42 | U42: =B42+C42+D42+T42 | X42: =U42+V42+W42
A43: Issue of convertible notes, net of tax | M43: =SUM(E43:L43) | S43: =SUM(N43:R43) | T43: =M43+S43 | U43: =B43+C43+D43+T43 | X43: =U43+V43+W43
A44: Increase (decrease) through share-based payment transactions, equity | M44: =SUM(E44:L44) | S44: =SUM(N44:R44) | T44: =M44+S44 | U44: =B44+C44+D44+T44 | X44: =U44+V44+W44
A45: Treasury shares transactions | M45: =SUM(E45:L45) | S45: =SUM(N45:R45) | T45: =M45+S45 | U45: =B45+C45+D45+T45 | X45: =U45+V45+W45
A46: Other transactions with owners | M46: =SUM(E46:L46) | S46: =SUM(N46:R46) | T46: =M46+S46 | U46: =B46+C46+D46+T46 | X46: =U46+V46+W46
A47: Increase (decrease) through other changes, equity | M47: =SUM(E47:L47) | S47: =SUM(N47:R47) | T47: =M47+S47 | U47: =B47+C47+D47+T47 | X47: =U47+V47+W47
A48: *Total increase (decrease) in equity | B48: =1*B37+1*B39+1*B40+-1*B41+1*B42+1*B43+1*B44+1*B45+1*B46+1*B47 | C48: =1*C37+1*C39+1*C40+-1*C41+1*C42+1*C43+1*C44+1*C45+1*C46+1*C47 | D48: =1*D37+1*D39+1*D40+-1*D41+1*D42+1*D43+1*D44+1*D45+1*D46+1*D47 | E48: =1*E37+1*E39+1*E40+-1*E41+1*E42+1*E43+1*E44+1*E45+1*E46+1*E47 | F48: =1*F37+1*F39+1*F40+-1*F41+1*F42+1*F43+1*F44+1*F45+1*F46+1*F47 | G48: =1*G37+1*G39+1*G40+-1*G41+1*G42+1*G43+1*G44+1*G45+1*G46+1*G47 | H48: =1*H37+1*H39+1*H40+-1*H41+1*H42+1*H43+1*H44+1*H45+1*H46+1*H47 | I48: =1*I37+1*I39+1*I40+-1*I41+1*I42+1*I43+1*I44+1*I45+1*I46+1*I47 | ... L48: =1*L37+1*L39+1*L40+-1*L41+1*L42+1*L43+1*L44+1*L45+1*L46+1*L47 | M48: =SUM(E48:L48) | N48: =1*N37+1*N39+1*N40+-1*N41+1*N42+1*N43+1*N44+1*N45+1*N46+1*N47 | O48: =1*O37+1*O39+1*O40+-1*O41+1*O42+1*O43+1*O44+1*O45+1*O46+1*O47 | P48: =1*P37+1*P39+1*P40+-1*P41+1*P42+1*P43+1*P44+1*P45+1*P46+1*P47 | Q48: =1*Q37+1*Q39+1*Q40+-1*Q41+1*Q42+1*Q43+1*Q44+1*Q45+1*Q46+1*Q47 | R48: =1*R37+1*R39+1*R40+-1*R41+1*R42+1*R43+1*R44+1*R45+1*R46+1*R47 | S48: =SUM(N48:R48) | T48: =M48+S48 | U48: =B48+C48+D48+T48 | V48: =1*V37+1*V39+1*V40+-1*V41+1*V42+1*V43+1*V44+1*V45+1*V46+1*V47 | W48: =1*W37+1*W39+1*W40+-1*W41+1*W42+1*W43+1*W44+1*W45+1*W46+1*W47 | X48: =U48+V48+W48
A49: *Equity at end of period | B49: =B32+B48 | C49: =C32+C48 | D49: =D32+D48 | E49: =E32+E48 | F49: =F32+F48 | G49: =G32+G48 | H49: =H32+H48 | I49: =I32+I48 | ... L49: =L32+L48 | M49: =SUM(E49:L49) | N49: =N32+N48 | O49: =O32+O48 | P49: =P32+P48 | Q49: =Q32+Q48 | R49: =R32+R48 | S49: =SUM(N49:R49) | T49: =M49+S49 | U49: =B49+C49+D49+T49 | V49: =V32+V48 | W49: =W32+W48 | X49: =U49+V49+W49
