Workbook
Name CountryList: Data!$O$1:$O$246
Name CurrencyList: Data!$Q$1:$Q$172
Name NewCurrencyList: Data!$Q$1:$Q$172
Name ScaleList: [1]StartUp!$L$1:$L$5
Name ScaleList: [2]StartUp!$L$1:$L$5
Name UnitList: [1]StartUp!$K$1:$K$172
Name UnitList: [2]StartUp!$K$1:$K$172

Sheet Introduction

Sheet Content Page
B2: Content Page
B3: More Options (Document Actions)
B4: Financial Statements as per Malaysian Financial Reporting Standards - 1.0
B5: General
B6: Filing Information
B8: Disclosure
B9: Scope of filing
B10: Disclosure - Directors report
B11: Disclosure - Director business review
B12: Disclosure - Statement by directors
B13: Disclosure - Involvement in Stock Exchange
B14: Disclosure - Auditors report to members
... B30: Notes - Related party transactions

Sheet FilingInfo
A1: 529ff12d-e989-41d3-b834-6513adcedc61:~:AtleastOneValueInAnyLayout:~:True:~:<?xml version="1.0" encoding="utf-16"?>_x000D_ <Customization xmlns:xsi="http://www.w3.org/2001/XMLSchema-instance" xmlns:xsd="http://www.w3.org/2001/XMLSchema" ComparitiveDate="False" LayoutByDate="False" LayoutByCompany="False" ShowAllDomains="False" TotalDomain="True" DefaultDates="1" />:~:http://xbrl.ssm.com.my/role/ssm/rol_ssmt-dei-fs-mfrs_2022-12-31/ssmt-dei-fs-mfrs_2022-12-31_role-010000:~:None
D2: FS-MFRS Filing Information
D3: * denotes mandatory items to be reported | E3: Edit Filing Information
C5: 9113df73-46c5-408f-9235-ab46a26a4c6e:~:FilingInfo_1:~:NotMandatory:~:False:~:0:~:True:~:<?xml version="1.0" encoding="utf-16"?>_x000D_ <Customization xmlns:xsi="http://www.w3.org/2001/XMLSchema-instance" xmlns:xsd="http://www.w3.org/2001/XMLSchema" ComparitiveDate="False" LayoutByDate="False" LayoutByCompany="False" ShowAllDomains="False" TotalDomain="True" DefaultDates="1" />:~:LytLin:~::~:False:~:True:~:ssmt-dei-cor_2022-12-31.xsd#ssmt-dei_FilingInformationAbstract@http://www.xbrl.org/2003/role/label:~:
C8: #LAYOUTSCSR# | D8: #PRIM# | F8: #TABLE# | G8: #LAYOUTECSR#
C9: #TABLE#
A10: ssmt-dei-cor_2022-12-31.xsd#ssmt-dei_FilingInformationAbstract | D10: Filing Information
A11: ssmt-dei-cor_2022-12-31.xsd#ssmt-dei_GeneralFilingInformationAbstract | D11: General Filing Information
A12: ssmt-dei-cor_2022-12-31.xsd#ssmt-dei_NewCompanyRegistrationNumber | D12: *New Company registration number | E12: 197501000529
A13: ssmt-dei-cor_2022-12-31.xsd#ssmt-dei_CompanyRegistrationNumber | D13: Company registration number
A14: ssmt-dei-cor_2022-12-31.xsd#ssmt-dei_NameOfReportingEntity | D14: *Name of company | E14: AMWAY (MALAYSIA) SDN BHD
A15: ssmt-dei-cor_2022-12-31.xsd#ssmt-dei_FormerNameOfCompany | D15: Former name of the company
A16: ssmt-dei-cor_2022-12-31.xsd#ssmt-dei_OriginOfCompany | D16: *Origin of company | E16: Incorporated in Malaysia
A17: ssmt-dei-cor_2022-12-31.xsd#ssmt-dei_StatusOfCompany | D17: *Status of company | E17: Private company
A18: ssmt-dei-cor_2022-12-31.xsd#ssmt-dei_TypeOfCompany | D18: *Types of company | E18: Company limited by shares
A19: ssmt-dei-cor_2022-12-31.xsd#ssmt-dei_ApplicationOfSubmission | D19: *Application of submission | E19: Ordinary filing
A20: ssmt-dei-cor_2022-12-31.xsd#ssmt-dei_StatutoryDeclarationForRectification | D20: Statutory Declaration for rectification
A21: ssmt-dei-cor_2022-12-31.xsd#ssmt-dei_CourtOrderReferenceNumber | D21: Court Order reference number
A22: ssmt-dei-cor_2022-12-31.xsd#ssmt-dei_DisclosureOfFinancialStatementsPreparationForCurrentSubmission | D22: *Disclosure of financial statements preparation for current submission | E22: Subsequent preparation of financial statements
A23: ssmt-dei-cor_2022-12-31.xsd#ssmt-dei_CompanyCurrentFinancialYearStartDate | D23: *Company's current financial year start date | E23: 01/01/2024
A24: ssmt-dei-cor_2022-12-31.xsd#ssmt-dei_CompanyCurrentFinancialYearEndDate | D24: *Company's current financial year end date | E24: 31/12/2024
A25: ssmt-dei-cor_2022-12-31.xsd#ssmt-dei_CompanyPreviousFinancialYearStartDate | D25: Company's previous financial year start date | E25: 01/01/2023
A26: ssmt-dei-cor_2022-12-31.xsd#ssmt-dei_CompanyPreviousFinancialYearEndDate | D26: Company's previous financial year end date | E26: 31/12/2023
A27: ssmt-dei-cor_2022-12-31.xsd#ssmt-dei_StatusOfCarryingOnBusinessDuringFinancialYear | D27: *Status of carrying on business during the financial year | E27: Carrying on business activities
A28: ssmt-dei-cor_2022-12-31.xsd#ssmt-dei_DisclosureOfFinancialStatementsAuditStatus | D28: *Disclosure of financial statements audit status | E28: Audited
A29: ssmt-dei-cor_2022-12-31.xsd#ssmt-dei_AuditExemptionCategory | D29: Audit exemption category
A30: ssmt-dei-cor_2022-12-31.xsd#ssmt-dei_BasisOfAccountingStandardsAppliedToPrepareFinancialStatements | D30: *Basis of accounting standards applied to prepare the financial statements | E30: Malaysian Financial Reporting Standards
A31: ssmt-dei-cor_2022-12-31.xsd#ssmt-dei_DisclosureOfOtherAccountingStandardsApplied | D31: Disclosure of other accounting standards applied
A32: ssmt-dei-cor_2022-12-31.xsd#ssmt-dei_TypeOfSubmission | D32: *Type of submission | E32: FS-MFRS
A33: ssmt-dei-ee-mfrs_2022-12-31.xsd#ssmt-dei-ee-mfrs_NatureOfFinancialStatements | D33: *Nature of financial statements | E33: Separate
A34: ssmt-dei-cor_2022-12-31.xsd#ssmt-dei_DescriptionOfPresentationCurrency | D34: *Description of presentation currency | E34: Malaysian Ringgit (MYR)
A35: ssmt-dei-cor_2022-12-31.xsd#ssmt-dei_DescriptionOfFunctionalCurrency | D35: Description of functional currency
A36: ssmt-dei-cor_2022-12-31.xsd#ssmt-dei_LevelOfRoundingUsedInFinancialStatements | D36: *Level of rounding used in financial statements | E36: In thousands ('000')
A37: ssmt-dei-cor_2022-12-31.xsd#ssmt-dei_NameAndVersionOfSoftwareUsedToGenerateXBRLFile | D37: *Name and version of software used to generate XBRL file | E37: MBRS_Preparation_Tool v2.2
A38: ssmt-dei-cor_2022-12-31.xsd#ssmt-dei_TaxonomyVersion | D38: *Taxonomy version | E38: SSMxT_2022v1.0
C39: #TABLE#
C40: #LAYOUTSCER# | G40: #LAYOUTECER#

Sheet SOF
A1: c6385edc-8d86-45a1-a751-bbee2d4934b0:~:AtleastOneValueInAnyLayout:~:True:~:<?xml version="1.0" encoding="utf-16"?>_x000D_ <Customization xmlns:xsi="http://www.w3.org/2001/XMLSchema-instance" xmlns:xsd="http://www.w3.org/2001/XMLSchema" ComparitiveDate="False" LayoutByDate="False" LayoutByCompany="False" ShowAllDomains="True" TotalDomain="False" DefaultDates="1" />:~:http://xbrl.ssm.com.my/role/ssm/rol_ssmt-fs-mfrs_2022-12-31/ssmt-fs-mfrs_2022-12-31_role-020000:~:None
D2: FS-MFRS Scope of filing
D3: * denotes mandatory items to be reported
C5: 2020b569-fbf5-4c8c-8b47-a5af94d1af0e:~:SOF_1:~:NotMandatory:~:False:~:0:~:True:~:<?xml version="1.0" encoding="utf-16"?>_x000D_ <Customization xmlns:xsi="http://www.w3.org/2001/XMLSchema-instance" xmlns:xsd="http://www.w3.org/2001/XMLSchema" ComparitiveDate="False" LayoutByDate="False" LayoutByCompany="False" ShowAllDomains="True" TotalDomain="False" DefaultDates="1" />:~:LytLin:~::~:False:~:True:~:ssmt-cor_2022-12-31.xsd#ssmt_DisclosureOnScopeOfFilingAbstract@http://www.xbrl.org/2003/role/label:~:
C8: #LAYOUTSCSR# | D8: #PRIM# | F8: #TABLE# | G8: #LAYOUTECSR#
C9: #STDTENDTDATE# | E9: =TEXT(DATE(MID(E10,7,4),MID(E10,4,2),MID(E10,1,2)),"dd/MM/yyyy")&" - "&TEXT(DATE(MID(E11,7,4),MID(E11,4,2),MID(E11,1,2)),"dd/MM/yyyy") -> 01/01/2024 - 31/12/2024
C10: #STDT# | E10: =StartUp!$D$8 -> 01/01/2024
C11: #ENDT# | E11: =StartUp!$D$9 -> 31/12/2024
C12: #TABLE#
A13: ssmt-cor_2022-12-31.xsd#ssmt_DisclosureOnScopeOfFilingAbstract | D13: Disclosure on scope of filing
A14: ssmt-cor_2022-12-31.xsd#ssmt_ParticularsOfFinancialStatementsAndReportsAbstract | D14: Particulars of Financial Statements and Reports
A15: ssmt-cor_2022-12-31.xsd#ssmt_DateOfFinancialStatementsApprovedByBoardOfDirectors | D15: *Date of financial statements approved by Board of Directors
A16: ssmt-cor_2022-12-31.xsd#ssmt_DateOfCirculationOfFinancialStatementsAndReportsToMembers | D16: *Date of circulation of financial statements and reports to members
A17: ssmt-cor_2022-12-31.xsd#ssmt_DateOfFinancialStatementsAndReportsOfDirectorsAndAuditorsLaidInAnnualGeneralMeeting | D17: Date of financial statements and reports of the directors and auditors (if applicable) laid in annual general meeting
A18: ssmt-cor_2022-12-31.xsd#ssmt_DateOfStatutoryDeclaration | D18: *Date of Statutory Declaration
A19: ssmt-cor_2022-12-31.xsd#ssmt_DisclosureOnWhetherCompanysSharesAreTradedOnAnyOfficialStockExchange | D19: Disclosure on whether company's shares are traded on any official stock exchange | E19: Listed
A20: ssmt-cor_2022-12-31.xsd#ssmt_DisclosureOfRegulationAppliedDuringIncorporationOfCompany | D20: Disclosure of the regulation applied during incorporation of the company
A21: ssmt-cor_2022-12-31.xsd#ssmt_DisclosureOnWhetherCompanyInvolvedAsManagementCompanyUnderInterestSchemeAct2016 | D21: Disclosure on whether company involved as management company under Interest Scheme Act 2016
A22: ssmt-cor_2022-12-31.xsd#ssmt_DisclosureOfWhetherCompanyRegulatedByBankNegaraMalaysiaAtFinancialYearEnd | D22: Disclosure of whether company regulated by Bank Negara Malaysia at the financial year end | E22: Company not regulated by Bank Negara Malaysia
C23: #TABLE#
C24: #LAYOUTSCER# | G24: #LAYOUTECER#
C28: e84081cf-ebb2-4f52-aba7-69a29a01f856:~:SOF_2:~:NotMandatory:~:False:~:1:~:True:~:<?xml version="1.0" encoding="utf-16"?>_x000D_ <Customization xmlns:xsi="http://www.w3.org/2001/XMLSchema-instance" xmlns:xsd="http://www.w3.org/2001/XMLSchema" ComparitiveDate="False" LayoutByDate="False" LayoutByCompany="False" ShowAllDomains="True" TotalDomain="False" DefaultDates="1" />:~:LytHyc:~:ssmt-cor_2022-12-31.xsd#ssmt_NatureOfBusinessTable:~:False:~:True:~:ssmt-cor_2022-12-31.xsd#ssmt_DisclosureOnScopeOfFilingAbstract@http://www.xbrl.org/2003/role/label::ssmt-cor_2022-12-31.xsd#ssmt_DetailsOfPrincipalActivitiesOfBusinessAbstract@http://www.xbrl.org/2003/role/label::ssmt-cor_2022-12-31.xsd#ssmt_NatureOfBusinessLineItems@http://www.xbrl.org/2003/role/label:~:ssmt-cor_2022-12-31.xsd#ssmt_NatureOfBusinessTable
E29: ssmt-cor_2022-12-31.xsd#ssmt_MSICCode | F29: ssmt-cor_2022-12-31.xsd#ssmt_DescriptionOfBusiness
D30: ssmt-cor_2022-12-31.xsd#ssmt_NatureOfBusinessTable::ssmt-cor_2022-12-31.xsd#ssmt_NatureOfBusinessAxis
C31: #LAYOUTSCSR# | D31: #DOM# | G31: #TABLE# | H31: #LAYOUTECSR#
C32: #PRIM# | E32: *MSIC Code | F32: *Description of business
C33: #STDTENDTDATE# | E33: =TEXT(DATE(MID(E34,7,4),MID(E34,4,2),MID(E34,1,2)),"dd/MM/yyyy")&" - "&TEXT(DATE(MID(E35,7,4),MID(E35,4,2),MID(E35,1,2)),"dd/MM/yyyy") -> 01/01/2024 - 31/12/2024 | F33: =TEXT(DATE(MID(F34,7,4),MID(F34,4,2),MID(F34,1,2)),"dd/MM/yyyy")&" - "&TEXT(DATE(MID(F35,7,4),MID(F35,4,2),MID(F35,1,2)),"dd/MM/yyyy") -> 01/01/2024 - 31/12/2024
C34: #STDT# | E34: =StartUp!$D$8 -> 01/01/2024 | F34: =StartUp!$D$8 -> 01/01/2024
C35: #ENDT# | E35: =StartUp!$D$9 -> 31/12/2024 | F35: =StartUp!$D$9 -> 31/12/2024
C36: #TABLE#
B37: ssmt-cor_2022-12-31.xsd#ssmt_NatureOfBusinessTable::ssmt-cor_2022-12-31.xsd#ssmt_NatureOfBusinessAxis::ssmt-cor_2022-12-31.xsd#ssmt_BusinessOneMember | D37: Business 1
B38: ssmt-cor_2022-12-31.xsd#ssmt_NatureOfBusinessTable::ssmt-cor_2022-12-31.xsd#ssmt_NatureOfBusinessAxis::ssmt-cor_2022-12-31.xsd#ssmt_BusinessTwoMember | D38: Business 2
B39: ssmt-cor_2022-12-31.xsd#ssmt_NatureOfBusinessTable::ssmt-cor_2022-12-31.xsd#ssmt_NatureOfBusinessAxis::ssmt-cor_2022-12-31.xsd#ssmt_BusinessThreeMember | D39: Business 3
C40: #TABLE#
C41: #LAYOUTSCER# | H41: #LAYOUTECER#
C45: 2fb1de5a-7652-43fb-9d2d-73c5a08a683b:~:SOF_3:~:NotMandatory:~:False:~:2:~:True:~:<?xml version="1.0" encoding="utf-16"?>_x000D_ <Customization xmlns:xsi="http://www.w3.org/2001/XMLSchema-instance" xmlns:xsd="http://www.w3.org/2001/XMLSchema" ComparitiveDate="False" LayoutByDate="False" LayoutByCompany="False" ShowAllDomains="True" TotalDomain="False" DefaultDates="1" />:~:LytLin:~::~:False:~:True:~:ssmt-cor_2022-12-31.xsd#ssmt_DisclosureOnScopeOfFilingAbstract@http://www.xbrl.org/2003/role/label:~:
C48: #LAYOUTSCSR# | D48: #PRIM# | F48: #TABLE# | G48: #LAYOUTECSR#
C49: #STDTENDTDATE# | E49: =TEXT(DATE(MID(E50,7,4),MID(E50,4,2),MID(E50,1,2)),"dd/MM/yyyy")&" - "&TEXT(DATE(MID(E51,7,4),MID(E51,4,2),MID(E51,1,2)),"dd/MM/yyyy") -> 01/01/2024 - 31/12/2024
C50: #STDT# | E50: =StartUp!$D$8 -> 01/01/2024
C51: #ENDT# | E51: =StartUp!$D$9 -> 31/12/2024
C52: #TABLE#
A53: ssmt-cor_2022-12-31.xsd#ssmt_DisclosureOnScopeOfFilingAbstract | D53: Disclosure on scope of filing
A54: ssmt-cor_2022-12-31.xsd#ssmt_ApprovedApplicationFromRegistrarOrMinisterAbstract | D54: Approved Application From The Registrar Or Minister
A55: ssmt-cor_2022-12-31.xsd#ssmt_DescriptionOnWhetherCompanyHadAppliedForAnyExemptionWaiverReliefOrExtensionOfTimeWithRegardToAnnualReturnOrFinancialStatementsAndReportsFromRegistrarOrMinister | D55: Description on whether company had applied for any exemption, waiver, relief or extension of time with regards to annual return or financial statements and reports from Registrar or Minister | E55: No
A56: ssmt-cor_2022-12-31.xsd#ssmt_DescriptionOnWhetherCompanyHadAppliedForExemptionFromCoincidingForeignSubsidiaryFinancialYearEndWithHoldingCompany | D56: *Description on whether company had applied for exemption from coinciding foreign subsidiary financial year end with holding company
A57: ssmt-cor_2022-12-31.xsd#ssmt_DescriptionOnWhetherCompanyHadAppliedFromFilingFinancialStatementsAndReportsInFullXBRLFormat | D57: *Description on whether company had applied for exemption from filing financial statements and reports in full XBRL format.
A58: ssmt-cor_2022-12-31.xsd#ssmt_DescriptionOnWhetherCompanyHadAppliedToWaiveLodgementOfForeignStatementsByForeignCompany | D58: *Description on whether company had applied to waive lodgement of financial statements by foreign company
A59: ssmt-cor_2022-12-31.xsd#ssmt_DescriptionOnWhetherCompanyHadAppliedForReliefFromRequirementsAsToFormAndContentsOfDirectorsReport | D59: *Description on whether company had applied for relief from requirements as to form and contents of Director's report
A60: ssmt-cor_2022-12-31.xsd#ssmt_DescriptionOnWhetherCompanyHadAppliedForReliefFromRequirementsAsToFormAndContentsOfFinancialStatements | D60: *Description on whether company had applied for relief from requirements as to form and contents of financial statements
A61: ssmt-cor_2022-12-31.xsd#ssmt_DescriptionOnWhetherCompanyHadAppliedForExtensionOfTimeForCirculationOfFinancialStatementsAndReports | D61: *Description on whether company had applied for extension of time for circulation of financial statements and reports
A62: ssmt-cor_2022-12-31.xsd#ssmt_DescriptionOnWhetherCompanyHadAppliedForExtensionOfTimeToLodgeFinancialStatementsAndReports | D62: *Description on whether company had applied for extension of time to lodge financial statements and reports
A63: ssmt-cor_2022-12-31.xsd#ssmt_DescriptionOnWhetherCompanyHadAppliedForExtensionOfTimeForHoldingAnnualGeneralMeeting | D63: *Description on whether company had applied for extension of time for circulation and holding annual general meeting
A64: ssmt-cor_2022-12-31.xsd#ssmt_DescriptionOnWhetherCompanyHadAppliedForExtensionOfTimeToLodgeAnnualReturn | D64: *Description on whether company had applied for extension of time to lodge annual return
A65: ssmt-cor_2022-12-31.xsd#ssmt_DescriptionOnWhetherCompanyHadAppliedAnyExemptionWaiverReliefOrExtensionOfTimeWithRegardsToFinancialStatementsAndReportsOrAnnualReturnToMinister | D65: *Description on whether company had applied any exemption, waiver, relief or extension of time with regards to annual return or financial statements and reports to Minister
A66: ssmt-cor_2022-12-31.xsd#ssmt_MethodUsedForPreparingStatementOfFinancialPosition | D66: Method used for preparing Statement of Financial Position | E66: Current-Noncurrent
A67: ssmt-cor_2022-12-31.xsd#ssmt_MethodUsedForPreparingStatementOfProfitOrLoss | D67: Method used for preparing Statement of Profit or Loss | E67: Function of expense
A68: ssmt-cor_2022-12-31.xsd#ssmt_MethodUsedForPreparingStatementOfComprehensiveIncome | D68: Method used for preparing Statement of Comprehensive Income | E68: Before tax
A69: ssmt-cor_2022-12-31.xsd#ssmt_MethodUsedForPreparingStatementOfCashFlows | D69: Method used for preparing Statement of Cash Flows | E69: Indirect
A70: ssmt-cor_2022-12-31.xsd#ssmt_ChangesFromSubsequentXBRLFinancialStatementFilingAbstract | D70: Changes From Subsequent XBRL Financial Statements Filing
A71: ssmt-cor_2022-12-31.xsd#ssmt_DisclosureOnWhetherComparativePeriodValuesAreRestated | D71: *Disclosure on whether comparative period values are restated | E71: No
A72: ssmt-cor_2022-12-31.xsd#ssmt_DisclosureOnWhetherOpeningStatementChangedDueToChangesInAccountingStandards | D72: *Disclosure on whether opening statements changed due to changes in accounting standards
A73: ssmt-cor_2022-12-31.xsd#ssmt_DisclosureOnWhetherReclassificationOfPreviousFinancialStatementsChangedDueToChangesInAccountingStandards | D73: *Disclosure on whether reclassification of previous financial statements changed due to changes in accounting standards
A74: ssmt-cor_2022-12-31.xsd#ssmt_DisclosureOnWhetherCompanyChangedDurationOfFinancialReportingPeriod | D74: *Description on whether company changed the duration of financial reporting period
C75: #TABLE#
C76: #LAYOUTSCER# | G76: #LAYOUTECER#

Sheet DirectorsRep
A1: 89b682df-712f-4e49-99ae-3acf6481ec99:~:AtleastOneValueInAnyLayout:~:True:~:<?xml version="1.0" encoding="utf-16"?>_x000D_ <Customization xmlns:xsi="http://www.w3.org/2001/XMLSchema-instance" xmlns:xsd="http://www.w3.org/2001/XMLSchema" ComparitiveDate="False" LayoutByDate="False" LayoutByCompany="False" ShowAllDomains="False" TotalDomain="True" DefaultDates="1" />:~:http://xbrl.ssm.com.my/role/ssm/rol_ssmt-fs-mfrs_2022-12-31/ssmt-fs-mfrs_2022-12-31_role-120000:~:None
D2: FS-MFRS Disclosure - Directors report
D3: * denotes mandatory items to be reported
C5: 13a921b6-de34-4a64-8117-dc7f972fcf23:~:DirectorsRep_1:~:NotMandatory:~:False:~:0:~:True:~:<?xml version="1.0" encoding="utf-16"?>_x000D_ <Customization xmlns:xsi="http://www.w3.org/2001/XMLSchema-instance" xmlns:xsd="http://www.w3.org/2001/XMLSchema" ComparitiveDate="False" LayoutByDate="False" LayoutByCompany="False" ShowAllDomains="False" TotalDomain="True" DefaultDates="1" />:~:LytLin:~::~:False:~:True:~:ssmt-cor_2022-12-31.xsd#ssmt_DisclosureOnDirectorsReportAbstract@http://www.xbrl.org/2003/role/label:~:
C8: #LAYOUTSCSR# | D8: #PRIM# | F8: #TABLE# | G8: #LAYOUTECSR#
C9: #STDTENDTDATE# | E9: =TEXT(DATE(MID(E10,7,4),MID(E10,4,2),MID(E10,1,2)),"dd/MM/yyyy")&" - "&TEXT(DATE(MID(E11,7,4),MID(E11,4,2),MID(E11,1,2)),"dd/MM/yyyy") -> 01/01/2024 - 31/12/2024
C10: #STDT# | E10: =StartUp!$D$8 -> 01/01/2024
C11: #ENDT# | E11: =StartUp!$D$9 -> 31/12/2024
C12: #TABLE#
A13: ssmt-cor_2022-12-31.xsd#ssmt_DisclosureOnDirectorsReportAbstract | D13: Disclosure on directors report
A14: ssmt-cor_2022-12-31.xsd#ssmt_DirectorsReportAbstract | D14: Director's Report
A15: ssmt-cor_2022-12-31.xsd#ssmt_DisclosureOfDirectorsReportExplanatory | D15: *Disclosure of Director's Report
A16: ssmt-cor_2022-12-31.xsd#ssmt_NumberOfDirectorsSigningDirectorsReport | D16: *Number of directors signing Director's report
A17: ssmt-cor_2022-12-31.xsd#ssmt_NameOfFirstDirectorWhoSignedDirectorsReport | D17: *Name of first director who signed Director's report
A18: ssmt-cor_2022-12-31.xsd#ssmt_TypeOfIdentificationOfFirstDirectorWhoSignedDirectorsReport | D18: *Type of identification of first director who signed director's report
A19: ssmt-cor_2022-12-31.xsd#ssmt_IdentificationNumberOfFirstDirectorWhoSignedDirectorsReport | D19: *Identification number of the first director who signed director's report
A20: ssmt-cor_2022-12-31.xsd#ssmt_NameOfSecondDirectorWhoSignedDirectorsReport | D20: Name of second director who signed the director's report
A21: ssmt-cor_2022-12-31.xsd#ssmt_TypeOfIdentificationOfSecondDirectorWhoSignedDirectorsReport | D21: Type of identification of second director who signed Director's report
A22: ssmt-cor_2022-12-31.xsd#ssmt_IdentificationNumberOfSecondDirectorWhoSignedDirectorsReport | D22: Identification number of the second director who signed director's report
A23: ssmt-cor_2022-12-31.xsd#ssmt_NameOfThirdDirectorWhoSignedDirectorsReport | D23: Name of third director who signed the director's report
A24: ssmt-cor_2022-12-31.xsd#ssmt_TypeOfIdentificationOfThirdDirectorWhoSignedDirectorsReport | D24: Type of identification of third director who signed Director's report
... A36: ssmt-cor_2022-12-31.xsd#ssmt_DateOfSigningDirectorsReport | D36: *Date of signing director's report
C37: #TABLE#
C38: #LAYOUTSCER# | G38: #LAYOUTECER#

Sheet DirectorsBussRev
A1: 6afd2ff7-526b-4c4e-8a46-10a5234226a2:~:AtleastOneValueInAnyLayout:~:True:~:<?xml version="1.0" encoding="utf-16"?>_x000D_ <Customization xmlns:xsi="http://www.w3.org/2001/XMLSchema-instance" xmlns:xsd="http://www.w3.org/2001/XMLSchema" ComparitiveDate="False" LayoutByDate="False" LayoutByCompany="False" ShowAllDomains="False" TotalDomain="True" DefaultDates="1" />:~:http://xbrl.ssm.com.my/role/ssm/rol_ssmt-fs-mfrs_2022-12-31/ssmt-fs-mfrs_2022-12-31_role-120200:~:None
D2: FS-MFRS Disclosure - Director business review
D3: * denotes mandatory items to be reported
C5: fc01c29c-f543-4291-afce-4e8c7f2f2fa9:~:DirectorsBussRev_1:~:NotMandatory:~:False:~:0:~:True:~:<?xml version="1.0" encoding="utf-16"?>_x000D_ <Customization xmlns:xsi="http://www.w3.org/2001/XMLSchema-instance" xmlns:xsd="http://www.w3.org/2001/XMLSchema" ComparitiveDate="False" LayoutByDate="False" LayoutByCompany="False" ShowAllDomains="False" TotalDomain="True" DefaultDates="1" />:~:LytLin:~::~:False:~:True:~:ssmt-cor_2022-12-31.xsd#ssmt_DisclosureOnDirectorsBusinessReviewAbstract@http://www.xbrl.org/2003/role/label:~:
C8: #LAYOUTSCSR# | D8: #PRIM# | F8: #TABLE# | G8: #LAYOUTECSR#
C9: #STDTENDTDATE# | E9: =TEXT(DATE(MID(E10,7,4),MID(E10,4,2),MID(E10,1,2)),"dd/MM/yyyy")&" - "&TEXT(DATE(MID(E11,7,4),MID(E11,4,2),MID(E11,1,2)),"dd/MM/yyyy") -> 01/01/2024 - 31/12/2024
C10: #STDT# | E10: =StartUp!$D$8 -> 01/01/2024
C11: #ENDT# | E11: =StartUp!$D$9 -> 31/12/2024
C12: #TABLE#
A13: ssmt-cor_2022-12-31.xsd#ssmt_DisclosureOnDirectorsBusinessReviewAbstract | D13: Disclosure on directors business review
A14: ssmt-cor_2022-12-31.xsd#ssmt_DisclosureOfStatementByDirectorsForBusinessReviewExplanatory | D14: Disclosure of statement by directors for business review
A15: ssmt-cor_2022-12-31.xsd#ssmt_DisclosureOfBusinessReviewEitherOnEnvironmentEmployeesOrSocialAndCommunityIssues | D15: Disclosure of business review either on environmental, employees or social and community issues
A16: ssmt-cor_2022-12-31.xsd#ssmt_EnvironmentalMatters | D16: Environmental matters
A17: ssmt-cor_2022-12-31.xsd#ssmt_CompanysEmployees | D17: Company's employees
A18: ssmt-cor_2022-12-31.xsd#ssmt_SocialAndCommunityIssues | D18: Social and community issues
A19: ssmt-cor_2022-12-31.xsd#ssmt_Others | D19: Others
A20: ssmt-cor_2022-12-31.xsd#ssmt_DisclosureOfOtherBusinessReviewApplied | D20: Disclosure of other business review applied
A21: ssmt-cor_2022-12-31.xsd#ssmt_DetailsOfCompanyEmployeesAbstract | D21: Details of company's employees
A22: ssmt-cor_2022-12-31.xsd#ssmt_NumberOfEmployees | D22: *Number of employees
C23: #TABLE#
C24: #LAYOUTSCER# | G24: #LAYOUTECER#

Sheet StatOfDirectors
A1: 478c4afb-57d6-43a8-b34d-80bb9ccf96ee:~:AtleastOneValueInAnyLayout:~:True:~:<?xml version="1.0" encoding="utf-16"?>_x000D_ <Customization xmlns:xsi="http://www.w3.org/2001/XMLSchema-instance" xmlns:xsd="http://www.w3.org/2001/XMLSchema" ComparitiveDate="False" LayoutByDate="False" LayoutByCompany="False" ShowAllDomains="False" TotalDomain="True" DefaultDates="1" />:~:http://xbrl.ssm.com.my/role/ssm/rol_ssmt-fs-mfrs_2022-12-31/ssmt-fs-mfrs_2022-12-31_role-120100:~:None
D2: FS-MFRS Disclosure - Statement by directors
D3: * denotes mandatory items to be reported
C5: f0b350e2-fc54-40bd-bf29-d3e422671aed:~:StatOfDirectors_1:~:NotMandatory:~:False:~:0:~:True:~:<?xml version="1.0" encoding="utf-16"?>_x000D_ <Customization xmlns:xsi="http://www.w3.org/2001/XMLSchema-instance" xmlns:xsd="http://www.w3.org/2001/XMLSchema" ComparitiveDate="False" LayoutByDate="False" LayoutByCompany="False" ShowAllDomains="False" TotalDomain="True" DefaultDates="1" />:~:LytLin:~::~:False:~:True:~:ssmt-cor_2022-12-31.xsd#ssmt_DisclosureOnStatementByDirectorsAbstract@http://www.xbrl.org/2003/role/label:~:
C8: #LAYOUTSCSR# | D8: #PRIM# | F8: #TABLE# | G8: #LAYOUTECSR#
C9: #STDTENDTDATE# | E9: =TEXT(DATE(MID(E10,7,4),MID(E10,4,2),MID(E10,1,2)),"dd/MM/yyyy")&" - "&TEXT(DATE(MID(E11,7,4),MID(E11,4,2),MID(E11,1,2)),"dd/MM/yyyy") -> 01/01/2024 - 31/12/2024
C10: #STDT# | E10: =StartUp!$D$8 -> 01/01/2024
C11: #ENDT# | E11: =StartUp!$D$9 -> 31/12/2024
C12: #TABLE#
A13: ssmt-cor_2022-12-31.xsd#ssmt_DisclosureOnStatementByDirectorsAbstract | D13: Disclosure on statement by directors
A14: ssmt-cor_2022-12-31.xsd#ssmt_StatementOfDirectorsAbstract | D14: Statement by Directors
A15: ssmt-cor_2022-12-31.xsd#ssmt_DisclosureOfStatementByDirectorsExplanatory | D15: *Disclosure of Statement by Directors
A16: ssmt-cor_2022-12-31.xsd#ssmt_DisclosureOfDirectorsOpinionThatFinancialStatementsOrConsolidatedFinancialStatementsAreDrawnInAccordanceWithAccountingStandards | D16: *Disclosure of directors opinion that the financial statements or consolidated financial statements are drawn up in accordance with approved accounting standards and reflect true and give true and fair view of financial position and performance of the company and the group
A17: ssmt-cor_2022-12-31.xsd#ssmt_NumberOfDirectorsSigningStatementByDirectors | D17: *Number of directors signing Statement by Directors
A18: ssmt-cor_2022-12-31.xsd#ssmt_NameOfFirstDirectorWhoSignedStatementByDirectors | D18: *Name of first director who signed Statement by Directors
A19: ssmt-cor_2022-12-31.xsd#ssmt_DisclosureWhetherFirstDirectorIsAlsoPrimarilyResponsibleForFinancialManagementOfCompany | D19: *Disclosure whether the first director is also primarily responsible for financial management of the company
A20: ssmt-cor_2022-12-31.xsd#ssmt_TypeOfIdentificationOfFirstDirectorWhoSignedStatementByDirectors | D20: *Type of identification of first director who signed Statement by Directors
A21: ssmt-cor_2022-12-31.xsd#ssmt_IdentificationNumberOfFirstDirectorWhoSignedStatementByDirectors | D21: *Identification number of the first director who signed Statement by Directors
A22: ssmt-cor_2022-12-31.xsd#ssmt_NameOfSecondDirectorWhoSignedStatementByDirectors | D22: Name of second director who signed Statement by Directors
A23: ssmt-cor_2022-12-31.xsd#ssmt_DisclosureWhetherSecondDirectorIsAlsoPrimarilyResponsibleForFinancialManagementOfCompany | D23: Disclosure whether the second director is also primarily responsible for financial management of the company
A24: ssmt-cor_2022-12-31.xsd#ssmt_TypeOfIdentificationNumberOfSecondDirectorWhoSignedStatementByDirectors | D24: Type of identification of second director who signed Statement by Directors
... A41: ssmt-cor_2022-12-31.xsd#ssmt_DateOfSigningStatementByDirectors | D41: *Date of signing statement by directors
C42: #TABLE#
C43: #LAYOUTSCER# | G43: #LAYOUTECER#

Sheet InvolInSE
A1: 3fe565c1-c031-4ec7-9463-cf017f8b82af:~:AtleastOneValueInAnyLayout:~:True:~:<?xml version="1.0" encoding="utf-16"?>_x000D_ <Customization xmlns:xsi="http://www.w3.org/2001/XMLSchema-instance" xmlns:xsd="http://www.w3.org/2001/XMLSchema" ComparitiveDate="False" LayoutByDate="False" LayoutByCompany="False" ShowAllDomains="False" TotalDomain="True" DefaultDates="1" />:~:http://xbrl.ssm.com.my/role/ssm/rol_ssmt-fs-mfrs_2022-12-31/ssmt-fs-mfrs_2022-12-31_role-110000:~:None
D2: FS-MFRS Disclosure - Involvement in Stock Exchange
D3: * denotes mandatory items to be reported(PLEASE IGNORE IF COMPANY NOT-LISTED)
C5: 4077ddfd-f5ed-4932-9436-b025d0f11874:~:InvolInSE_1:~:NotMandatory:~:False:~:0:~:True:~:<?xml version="1.0" encoding="utf-16"?>_x000D_ <Customization xmlns:xsi="http://www.w3.org/2001/XMLSchema-instance" xmlns:xsd="http://www.w3.org/2001/XMLSchema" ComparitiveDate="False" LayoutByDate="False" LayoutByCompany="False" ShowAllDomains="False" TotalDomain="True" DefaultDates="1" />:~:LytLin:~::~:False:~:True:~:ssmt-cor_2022-12-31.xsd#ssmt_DisclosureOnInvolvementInStockExchangeAbstract@http://www.xbrl.org/2003/role/label:~:
C8: #LAYOUTSCSR# | D8: #PRIM# | F8: #TABLE# | G8: #LAYOUTECSR#
C9: #STDTENDTDATE# | E9: =TEXT(DATE(MID(E10,7,4),MID(E10,4,2),MID(E10,1,2)),"dd/MM/yyyy")&" - "&TEXT(DATE(MID(E11,7,4),MID(E11,4,2),MID(E11,1,2)),"dd/MM/yyyy") -> 01/01/2024 - 31/12/2024
C10: #STDT# | E10: =StartUp!$D$8 -> 01/01/2024
C11: #ENDT# | E11: =StartUp!$D$9 -> 31/12/2024
C12: #TABLE#
A13: ssmt-cor_2022-12-31.xsd#ssmt_DisclosureOnInvolvementInStockExchangeAbstract | D13: Disclosure on involvement in stock exchange
A14: ssmt-cor_2022-12-31.xsd#ssmt_DateOfCompanyListedOnStockExchange | D14: *Date of company listed in Stock Exchange
A15: ssmt-cor_2022-12-31.xsd#ssmt_TypeOfExchangeOnWhichCompanyIsListed | D15: *Type of exchange on which company is listed
A16: ssmt-cor_2022-12-31.xsd#ssmt_DisclosureOfForeignStockExchange | D16: Disclosure of foreign stock exchange
A17: ssmt-cor_2022-12-31.xsd#ssmt_TypeOfMarketListedOnBursaMalaysia | D17: Type of market listed in Bursa Malaysia
A18: ssmt-cor_2022-12-31.xsd#ssmt_DisclosureOfSecuritiesListingOnShariahCompliantSecuritiesList | D18: *Disclosure of securities listing on Shari’ah compliant Securities list
A19: ssmt-cor_2022-12-31.xsd#ssmt_ExplanationOfOtherSecuritiesListedOnShariahComplaintSecuritiesList | D19: Explanation of other securities listed on Shari’ah compliant Securities list
A20: ssmt-cor_2022-12-31.xsd#ssmt_DateOfDelistingOfShares | D20: Date of delisting of shares
A21: ssmt-cor_2022-12-31.xsd#ssmt_TypeOfExchangeFromWhichSharesWereDelisted | D21: Type of exchange from which shares were delisted
A22: ssmt-cor_2022-12-31.xsd#ssmt_DisclosureOfForeignStockExchangeWhichCompanyWereDelisted | D22: Disclosure of foreign stock exchange which the company were delisted
C23: #TABLE#
C24: #LAYOUTSCER# | G24: #LAYOUTECER#

Sheet AuditReport
A1: 535ddd76-6156-4b07-a746-c5e13fd8d5ba:~:AtleastOneValueInAnyLayout:~:True:~:<?xml version="1.0" encoding="utf-16"?>_x000D_ <Customization xmlns:xsi="http://www.w3.org/2001/XMLSchema-instance" xmlns:xsd="http://www.w3.org/2001/XMLSchema" ComparitiveDate="False" LayoutByDate="False" LayoutByCompany="False" ShowAllDomains="False" TotalDomain="True" DefaultDates="1" />:~:http://xbrl.ssm.com.my/role/ssm/rol_ssmt-fs-mfrs_2022-12-31/ssmt-fs-mfrs_2022-12-31_role-130000:~:None
D2: FS-MFRS Disclosure - Auditors report to members
D3: * denotes mandatory items to be reported
D4: Auditor's details are mandatory to be reported only if 'Audited' is selected in the Filing Information
C5: bd4ef598-d3ef-4ad8-a6e6-f28d1446ee17:~:AuditReport_1:~:NotMandatory:~:False:~:0:~:True:~:<?xml version="1.0" encoding="utf-16"?>_x000D_ <Customization xmlns:xsi="http://www.w3.org/2001/XMLSchema-instance" xmlns:xsd="http://www.w3.org/2001/XMLSchema" ComparitiveDate="False" LayoutByDate="False" LayoutByCompany="False" ShowAllDomains="False" TotalDomain="True" DefaultDates="1" />:~:LytLin:~::~:False:~:True:~:ssmt-cor_2022-12-31.xsd#ssmt_DisclosureOnAuditorsReportToMembersAbstract@http://www.xbrl.org/2003/role/label:~:
C8: #LAYOUTSCSR# | D8: #PRIM# | F8: #TABLE# | G8: #LAYOUTECSR#
C9: #STDTENDTDATE# | E9: =TEXT(DATE(MID(E10,7,4),MID(E10,4,2),MID(E10,1,2)),"dd/MM/yyyy")&" - "&TEXT(DATE(MID(E11,7,4),MID(E11,4,2),MID(E11,1,2)),"dd/MM/yyyy") -> 01/01/2024 - 31/12/2024
C10: #STDT# | E10: =StartUp!$D$8 -> 01/01/2024
C11: #ENDT# | E11: =StartUp!$D$9 -> 31/12/2024
C12: #TABLE#
A13: ssmt-cor_2022-12-31.xsd#ssmt_DisclosureOnAuditorsReportToMembersAbstract | D13: Disclosure on auditors report to members
A14: ssmt-cor_2022-12-31.xsd#ssmt_AuditorsReportAbstract | D14: Auditor's report
A15: ssmt-cor_2022-12-31.xsd#ssmt_DisclosureOfAuditorsReportToMembersExplanatory | D15: *Disclosure of auditor's report to members
A16: ssmt-cor_2022-12-31.xsd#ssmt_TypeOfAuditorsOpinion | D16: *Type of auditor's opinion
A17: ssmt-cor_2022-12-31.xsd#ssmt_DateOfSigningAuditorsReport | D17: *Date of signing auditor's report
C18: #TABLE#
C19: #LAYOUTSCER# | G19: #LAYOUTECER#
C23: fb3d0ad8-129c-44d2-be07-233aa4d03efc:~:AuditReport_2:~:NotMandatory:~:False:~:1:~:True:~:<?xml version="1.0" encoding="utf-16"?>_x000D_ <Customization xmlns:xsi="http://www.w3.org/2001/XMLSchema-instance" xmlns:xsd="http://www.w3.org/2001/XMLSchema" ComparitiveDate="False" LayoutByDate="False" LayoutByCompany="False" ShowAllDomains="False" TotalDomain="True" DefaultDates="1" />:~:LytHyc:~:ssmt-cor_2022-12-31.xsd#ssmt_AuditorsInformationTable:~:False:~:True:~:ssmt-cor_2022-12-31.xsd#ssmt_DisclosureOnAuditorsReportToMembersAbstract@http://www.xbrl.org/2003/role/label::ssmt-cor_2022-12-31.xsd#ssmt_AuditorsInformationAbstract@http://www.xbrl.org/2003/role/label::ssmt-cor_2022-12-31.xsd#ssmt_AuditorsInformationLineitem@http://www.xbrl.org/2003/role/label:~:ssmt-cor_2022-12-31.xsd#ssmt_AuditorsInformationTable
E24: ssmt-cor_2022-12-31.xsd#ssmt_LicenseNumberOfAuditor | F24: ssmt-cor_2022-12-31.xsd#ssmt_NameOfAuditorSigningReport | G24: ssmt-cor_2022-12-31.xsd#ssmt_RegistrationNumberOfAuditFirm | H24: ssmt-cor_2022-12-31.xsd#ssmt_NameOfAuditFirm | I24: ssmt-cor_2022-12-31.xsd#ssmt_AddressOne | J24: ssmt-cor_2022-12-31.xsd#ssmt_AddressTwo | K24: ssmt-cor_2022-12-31.xsd#ssmt_AddressThree | L24: ssmt-cor_2022-12-31.xsd#ssmt_PostcodeOfAuditFirm | M24: ssmt-cor_2022-12-31.xsd#ssmt_TownWhereAuditFirmIsLocated | N24: ssmt-cor_2022-12-31.xsd#ssmt_StateWhereAuditFirmIsLocated
D25: ssmt-cor_2022-12-31.xsd#ssmt_AuditorsInformationTable::ssmt-cor_2022-12-31.xsd#ssmt_AuditorsCountAxis
C26: #LAYOUTSCSR# | D26: #DOM# | O26: #TABLE# | P26: #LAYOUTECSR#
C27: #PRIM# | E27: *License number of auditor | F27: *Name of auditor signing report | G27: *Registration number of audit firm | H27: *Name of audit firm | I27: *Address line 1 | J27: Address line 2 | K27: Address line 3 | L27: *Postcode | M27: *Town | N27: *State
C28: #STDTENDTDATE# | E28: =TEXT(DATE(MID(E29,7,4),MID(E29,4,2),MID(E29,1,2)),"dd/MM/yyyy")&" - "&TEXT(DATE(MID(E30,7,4),MID(E30,4,2),MID(E30,1,2)),"dd/MM/yyyy") -> 01/01/2024 - 31/12/2024 | F28: =TEXT(DATE(MID(F29,7,4),MID(F29,4,2),MID(F29,1,2)),"dd/MM/yyyy")&" - "&TEXT(DATE(MID(F30,7,4),MID(F30,4,2),MID(F30,1,2)),"dd/MM/yyyy") -> 01/01/2024 - 31/12/2024 | G28: =TEXT(DATE(MID(G29,7,4),MID(G29,4,2),MID(G29,1,2)),"dd/MM/yyyy")&" - "&TEXT(DATE(MID(G30,7,4),MID(G30,4,2),MID(G30,1,2)),"dd/MM/yyyy") -> 01/01/2024 - 31/12/2024 | H28: =TEXT(DATE(MID(H29,7,4),MID(H29,4,2),MID(H29,1,2)),"dd/MM/yyyy")&" - "&TEXT(DATE(MID(H30,7,4),MID(H30,4,2),MID(H30,1,2)),"dd/MM/yyyy") -> 01/01/2024 - 31/12/2024 | I28: =TEXT(DATE(MID(I29,7,4),MID(I29,4,2),MID(I29,1,2)),"dd/MM/yyyy")&" - "&TEXT(DATE(MID(I30,7,4),MID(I30,4,2),MID(I30,1,2)),"dd/MM/yyyy") -> 01/01/2024 - 31/12/2024 | J28: =TEXT(DATE(MID(J29,7,4),MID(J29,4,2),MID(J29,1,2)),"dd/MM/yyyy")&" - "&TEXT(DATE(MID(J30,7,4),MID(J30,4,2),MID(J30,1,2)),"dd/MM/yyyy") -> 01/01/2024 - 31/12/2024 | K28: =TEXT(DATE(MID(K29,7,4),MID(K29,4,2),MID(K29,1,2)),"dd/MM/yyyy")&" - "&TEXT(DATE(MID(K30,7,4),MID(K30,4,2),MID(K30,1,2)),"dd/MM/yyyy") -> 01/01/2024 - 31/12/2024 | L28: =TEXT(DATE(MID(L29,7,4),MID(L29,4,2),MID(L29,1,2)),"dd/MM/yyyy")&" - "&TEXT(DATE(MID(L30,7,4),MID(L30,4,2),MID(L30,1,2)),"dd/MM/yyyy") -> 01/01/2024 - 31/12/2024 | ... N28: =TEXT(DATE(MID(N29,7,4),MID(N29,4,2),MID(N29,1,2)),"dd/MM/yyyy")&" - "&TEXT(DATE(MID(N30,7,4),MID(N30,4,2),MID(N30,1,2)),"dd/MM/yyyy") -> 01/01/2024 - 31/12/2024
C29: #STDT# | E29: =StartUp!$D$8 -> 01/01/2024 | F29: =StartUp!$D$8 -> 01/01/2024 | G29: =StartUp!$D$8 -> 01/01/2024 | H29: =StartUp!$D$8 -> 01/01/2024 | I29: =StartUp!$D$8 -> 01/01/2024 | J29: =StartUp!$D$8 -> 01/01/2024 | K29: =StartUp!$D$8 -> 01/01/2024 | L29: =StartUp!$D$8 -> 01/01/2024 | ... N29: =StartUp!$D$8 -> 01/01/2024
C30: #ENDT# | E30: =StartUp!$D$9 -> 31/12/2024 | F30: =StartUp!$D$9 -> 31/12/2024 | G30: =StartUp!$D$9 -> 31/12/2024 | H30: =StartUp!$D$9 -> 31/12/2024 | I30: =StartUp!$D$9 -> 31/12/2024 | J30: =StartUp!$D$9 -> 31/12/2024 | K30: =StartUp!$D$9 -> 31/12/2024 | L30: =StartUp!$D$9 -> 31/12/2024 | ... N30: =StartUp!$D$9 -> 31/12/2024
C31: #TABLE# | E31: Insert only the first four digit from the full auditor's license number. e.g. XXXX/XX/XX(J/PH) | G31: Insert AF and the audit firm's four digit number from the full audit firm's number. e.g. AFXXXX
B32: 0 | D32: 0001
C33: #TABLE#
C34: #LAYOUTSCER# | P34: #LAYOUTECER#

Sheet SOFP-CuNonCu
A1: aba851e9-d688-4d30-856c-4f1919c2c24a:~:AtleastOneValueInAnyLayout:~:True:~:<?xml version="1.0" encoding="utf-16"?>_x000D_ <Customization xmlns:xsi="http://www.w3.org/2001/XMLSchema-instance" xmlns:xsd="http://www.w3.org/2001/XMLSchema" ComparitiveDate="False" LayoutByDate="False" LayoutByCompany="False" ShowAllDomains="False" TotalDomain="True" DefaultDates="2" />:~:http://xbrl.ssm.com.my/role/ssm/rol_ssmt-fs-mfrs_2022-12-31/ssmt-fs-mfrs_2022-12-31_role-200100x:~:None
D2: FS-MFRS Statement of financial position, by current/non-current method
D3: * denotes mandatory items to be reported
C5: 659bf83e-5dc1-467d-87cc-ef264eff1111:~:SOFP-CuNonCu_1_TBLYT:~:NotMandatory:~:False:~:0:~:True:~:<?xml version="1.0" encoding="utf-16"?>_x000D_ <Customization xmlns:xsi="http://www.w3.org/2001/XMLSchema-instance" xmlns:xsd="http://www.w3.org/2001/XMLSchema" ComparitiveDate="False" LayoutByDate="False" LayoutByCompany="False" ShowAllDomains="False" TotalDomain="True" DefaultDates="2" />:~:LytTxb:~::~:False:~:True:~:ssmt-cor_2022-12-31.xsd#ssmt_DisclosureOnStatementOfFinancialPositionAbstract@http://www.xbrl.org/2003/role/label:~:
C8: #LAYOUTSCSR# | D8: #PRIM# | F8: #TABLE# | G8: #LAYOUTECSR#
C9: #TABLE#
A10: ssmt-cor_2022-12-31.xsd#ssmt_DisclosureOnStatementOfFinancialPositionAbstract | D10: Disclosure on statement of financial position
C11: #TABLE#
C12: #LAYOUTSCER# | G12: #LAYOUTECER#
C15: df5a5fa2-5402-4eb0-8545-d71421aa44fb:~:SOFP-CuNonCu_2:~:NotMandatory:~:True:~:1:~:True:~:<?xml version="1.0" encoding="utf-16"?>_x000D_ <Customization xmlns:xsi="http://www.w3.org/2001/XMLSchema-instance" xmlns:xsd="http://www.w3.org/2001/XMLSchema" ComparitiveDate="False" LayoutByDate="False" LayoutByCompany="False" ShowAllDomains="False" TotalDomain="True" DefaultDates="2" />:~:LytHyc:~:ssmt-cor_2022-12-31.xsd#ssmt_StatementOfFinancialPositionTable:~:False:~:True:~:ssmt-cor_2022-12-31.xsd#ssmt_DisclosureOnStatementOfFinancialPositionAbstract@http://www.xbrl.org/2003/role/label::ssmt-cor_2022-12-31.xsd#ssmt_StatementOfFinancialPositionAbstract@http://www.xbrl.org/2003/role/label::ssmt-cor_2022-12-31.xsd#ssmt_StatementOfFinancialPositionLineItems@http://www.xbrl.org/2003/role/label:~:ssmt-cor_2022-12-31.xsd#ssmt_StatementOfFinancialPositionTable
C18: #LAYOUTSCSR# | D18: #PRIM# | G18: #TABLE# | H18: #LAYOUTECSR#
C19: #STDTENDTDATE# | E19: =TEXT(DATE(MID(E21,7,4),MID(E21,4,2),MID(E21,1,2)),"dd/MM/yyyy")&" - "&TEXT(DATE(MID(E22,7,4),MID(E22,4,2),MID(E22,1,2)),"dd/MM/yyyy") -> 01/01/2024 - 31/12/2024 | F19: =TEXT(DATE(MID(F21,7,4),MID(F21,4,2),MID(F21,1,2)),"dd/MM/yyyy")&" - "&TEXT(DATE(MID(F22,7,4),MID(F22,4,2),MID(F22,1,2)),"dd/MM/yyyy") -> 01/01/2023 - 31/12/2023
C20: #UNITSCALE# | E20: =StartUp!$E$8 -> MYR'000 | F20: =StartUp!$E$8 -> MYR'000
C21: #STDT# | E21: =StartUp!$D$8 -> 01/01/2024 | F21: =StartUp!$D$10 -> 01/01/2023
C22: #ENDT# | E22: =StartUp!$D$9 -> 31/12/2024 | F22: =StartUp!$D$11 -> 31/12/2023
C23: #TABLE#
A24: ssmt-cor_2022-12-31.xsd#ssmt_StatementOfFinancialPositionAbstract | D24: Statement of financial position
A25: ssmt-cor_2022-12-31.xsd#ssmt_StatementOfFinancialPositionLineItems | D25: Statement of financial position
A26: full_ifrs-cor_2022-03-24.xsd#ifrs-full_AssetsAbstract | D26: Assets
A27: full_ifrs-cor_2022-03-24.xsd#ifrs-full_NoncurrentAssetsAbstract | D27: Non-current assets
A28: full_ifrs-cor_2022-03-24.xsd#ifrs-full_PropertyPlantAndEquipment | D28: *Property, plant and equipment | E28: ='SOFP-Sub-CuNonCu'!E59 -> 1000000 | F28: ='SOFP-Sub-CuNonCu'!F59 -> 0 | G28: See details
A29: full_ifrs-cor_2022-03-24.xsd#ifrs-full_InvestmentProperty | D29: *Investment property | E29: ='SOFP-Sub-CuNonCu'!E69 -> 0 | F29: ='SOFP-Sub-CuNonCu'!F69 -> 0 | G29: See details
A30: ssmt-mfrs-cor_2022-12-31.xsd#ssmt-mfrs_NoncurrentBiologicalAssets@http://xbrl.ssm.com.my/role/ssm/lab_rol_ssmt-fs-mfrs_2022-12-31/ReportingLabel | D30: Biological assets
A31: full_ifrs-cor_2022-03-24.xsd#ifrs-full_RightofuseAssets@http://xbrl.ssm.com.my/role/ssm/lab_rol_ssmt-fs-mfrs_2022-12-31/ReportingLabel | D31: Right-of-use assets
A32: ssmt-mfrs-cor_2022-12-31.xsd#ssmt-mfrs_NoncurrentServiceConcessionAssets@http://xbrl.ssm.com.my/role/ssm/lab_rol_ssmt-fs-mfrs_2022-12-31/ReportingLabel | D32: Service concession assets
A33: full_ifrs-cor_2022-03-24.xsd#ifrs-full_IntangibleAssetsAndGoodwill@http://xbrl.ssm.com.my/role/ssm/lab_rol_ssmt-fs-mfrs_2022-12-31/ReportingLabel | D33: *Intangible assets | E33: ='SOFP-Sub-CuNonCu'!E89 -> 0 | F33: ='SOFP-Sub-CuNonCu'!F89 -> 0 | G33: See details
A34: full_ifrs-cor_2022-03-24.xsd#ifrs-full_InvestmentsInSubsidiaries@http://xbrl.ssm.com.my/role/ssm/lab_rol_ssmt-fs-mfrs_2022-12-31/ReportingLabel | D34: *Investments in subsidiaries | E34: ='SOFP-Sub-CuNonCu'!E97 -> 0 | F34: ='SOFP-Sub-CuNonCu'!F97 -> 0 | G34: See details
A35: full_ifrs-cor_2022-03-24.xsd#ifrs-full_InvestmentsInAssociates@http://xbrl.ssm.com.my/role/ssm/lab_rol_ssmt-fs-mfrs_2022-12-31/ReportingLabel | D35: *Investments in associates | E35: ='SOFP-Sub-CuNonCu'!E106 -> 0 | F35: ='SOFP-Sub-CuNonCu'!F106 -> 0 | G35: See details
A36: full_ifrs-cor_2022-03-24.xsd#ifrs-full_InvestmentsInJointVentures@http://xbrl.ssm.com.my/role/ssm/lab_rol_ssmt-fs-mfrs_2022-12-31/ReportingLabel | D36: *Investments in joint ventures | E36: ='SOFP-Sub-CuNonCu'!E115 -> 0 | F36: ='SOFP-Sub-CuNonCu'!F115 -> 0 | G36: See details
A37: full_ifrs-cor_2022-03-24.xsd#ifrs-full_NoncurrentInvestmentsOtherThanInvestmentsAccountedForUsingEquityMethod@http://xbrl.ssm.com.my/role/ssm/lab_rol_ssmt-fs-mfrs_2022-12-31/ReportingLabel | D37: *Other investments
A38: full_ifrs-cor_2022-03-24.xsd#ifrs-full_NoncurrentReceivables | D38: *Trade and other non-current receivables | E38: ='SOFP-Sub-CuNonCu'!E140 -> 0 | F38: ='SOFP-Sub-CuNonCu'!F140 -> 0 | G38: See details
A39: full_ifrs-cor_2022-03-24.xsd#ifrs-full_NoncurrentContractAssets@http://xbrl.ssm.com.my/role/ssm/lab_rol_ssmt-fs-mfrs_2022-12-31/ReportingLabel | D39: Contract assets
A40: full_ifrs-cor_2022-03-24.xsd#ifrs-full_DeferredTaxAssets | D40: Deferred tax assets
A41: full_ifrs-cor_2022-03-24.xsd#ifrs-full_NoncurrentDerivativeFinancialAssets@http://xbrl.ssm.com.my/role/ssm/lab_rol_ssmt-fs-mfrs_2022-12-31/ReportingLabel | D41: *Derivative financial assets | E41: ='SOFP-Sub-CuNonCu'!E149 -> 0 | F41: ='SOFP-Sub-CuNonCu'!F149 -> 0 | G41: See details
A42: full_ifrs-cor_2022-03-24.xsd#ifrs-full_OtherNoncurrentAssets | D42: *Other non-current assets | E42: ='SOFP-Sub-CuNonCu'!E218 -> 0 | F42: ='SOFP-Sub-CuNonCu'!F218 -> 0 | G42: See details
A43: full_ifrs-cor_2022-03-24.xsd#ifrs-full_NoncurrentAssets@http://www.xbrl.org/2003/role/totalLabel | D43: *Total non-current assets | E43: =1*E28+1*E29+1*E30+1*E31+1*E32+1*E33+1*E34+1*E35+1*E36+1*E37+1*E38+1*E39+1*E40+1*E41+1*E42 -> 1000000 | F43: =1*F28+1*F29+1*F30+1*F31+1*F32+1*F33+1*F34+1*F35+1*F36+1*F37+1*F38+1*F39+1*F40+1*F41+1*F42 -> 0
A44: full_ifrs-cor_2022-03-24.xsd#ifrs-full_CurrentAssetsAbstract | D44: Current assets
A45: full_ifrs-cor_2022-03-24.xsd#ifrs-full_InventoriesTotal | D45: *Inventories | E45: ='SOFP-Sub-CuNonCu'!E156 -> 0 | F45: ='SOFP-Sub-CuNonCu'!F156 -> 0 | G45: See details
A46: ssmt-mfrs-cor_2022-12-31.xsd#ssmt-mfrs_CurrentBiologicalAssets@http://xbrl.ssm.com.my/role/ssm/lab_rol_ssmt-fs-mfrs_2022-12-31/ReportingLabel | D46: Biological assets
A47: full_ifrs-cor_2022-03-24.xsd#ifrs-full_CurrentInvestments@http://xbrl.ssm.com.my/role/ssm/lab_rol_ssmt-fs-mfrs_2022-12-31/ReportingLabel | D47: Other investments
A48: full_ifrs-cor_2022-03-24.xsd#ifrs-full_CurrentTaxAssetsCurrent@http://xbrl.ssm.com.my/role/ssm/lab_rol_ssmt-fs-mfrs_2022-12-31/ReportingLabel | D48: Current tax assets
A49: full_ifrs-cor_2022-03-24.xsd#ifrs-full_TradeAndOtherCurrentReceivables | D49: *Trade and other current receivables | E49: ='SOFP-Sub-CuNonCu'!E189 -> 0 | F49: ='SOFP-Sub-CuNonCu'!F189 -> 0 | G49: See details
A50: full_ifrs-cor_2022-03-24.xsd#ifrs-full_CurrentContractAssets@http://xbrl.ssm.com.my/role/ssm/lab_rol_ssmt-fs-mfrs_2022-12-31/ReportingLabel | D50: Contract assets
A51: full_ifrs-cor_2022-03-24.xsd#ifrs-full_CurrentDerivativeFinancialAssets@http://xbrl.ssm.com.my/role/ssm/lab_rol_ssmt-fs-mfrs_2022-12-31/ReportingLabel | D51: *Derivative financial assets | E51: ='SOFP-Sub-CuNonCu'!E198 -> 0 | F51: ='SOFP-Sub-CuNonCu'!F198 -> 0 | G51: See details
A52: ssmt-cor_2022-12-31.xsd#ssmt_CashAndBankBalances@http://xbrl.ssm.com.my/role/ssm/lab_rol_ssmt-fs-mfrs_2022-12-31/ReportingLabel | D52: *Cash and cash equivalents | E52: ='SOFP-Sub-CuNonCu'!E213 -> 0 | F52: ='SOFP-Sub-CuNonCu'!F213 -> 0 | G52: See details
A53: full_ifrs-cor_2022-03-24.xsd#ifrs-full_OtherCurrentAssets | D53: *Other current assets
A54: full_ifrs-cor_2022-03-24.xsd#ifrs-full_CurrentAssetsOtherThanAssetsOrDisposalGroupsClassifiedAsHeldForSaleOrAsHeldForDistributionToOwners@http://xbrl.ssm.com.my/role/ssm/fs/mfrs/lab_rol_ssmt-fs-mfrs_2022-12-31/ReportingTotalLabel | D54: Total current assets other than assets held for sale | E54: =1*E45+1*E46+1*E47+1*E48+1*E49+1*E50+1*E51+1*E52+1*E53 -> 0 | F54: =1*F45+1*F46+1*F47+1*F48+1*F49+1*F50+1*F51+1*F52+1*F53 -> 0
A55: full_ifrs-cor_2022-03-24.xsd#ifrs-full_NoncurrentAssetsOrDisposalGroupsClassifiedAsHeldForSaleOrAsHeldForDistributionToOwners | D55: Non-current assets or disposal groups classified as held for sale or as held for distribution to owners
A56: full_ifrs-cor_2022-03-24.xsd#ifrs-full_CurrentAssets@http://www.xbrl.org/2003/role/totalLabel | D56: *Total current assets | E56: =1*E45+1*E46+1*E47+1*E48+1*E49+1*E50+1*E51+1*E52+1*E53+1*E55 -> 0 | F56: =1*F45+1*F46+1*F47+1*F48+1*F49+1*F50+1*F51+1*F52+1*F53+1*F55 -> 0
A57: full_ifrs-cor_2022-03-24.xsd#ifrs-full_Assets@http://www.xbrl.org/2003/role/totalLabel | D57: *Total assets | E57: =1*E28+1*E29+1*E31+1*E32+1*E33+1*E34+1*E35+1*E36+1*E37+1*E38+1*E39+1*E40+1*E41+1*E42+1*E45+1*E47+1*E48+1*E49+1*E50+1*E51+1*E52+1*E53+1*E55+1*E46+1*E30 -> 1000000 | F57: =1*F28+1*F29+1*F31+1*F32+1*F33+1*F34+1*F35+1*F36+1*F37+1*F38+1*F39+1*F40+1*F41+1*F42+1*F45+1*F47+1*F48+1*F49+1*F50+1*F51+1*F52+1*F53+1*F55+1*F46+1*F30 -> 0
A58: full_ifrs-cor_2022-03-24.xsd#ifrs-full_EquityAndLiabilitiesAbstract | D58: Equity and liabilities
A59: full_ifrs-cor_2022-03-24.xsd#ifrs-full_EquityAbstract | D59: Equity
A60: full_ifrs-cor_2022-03-24.xsd#ifrs-full_IssuedCapital | D60: *Issued capital | E60: ='SOFP-Sub-CuNonCu'!E223 -> 0 | F60: ='SOFP-Sub-CuNonCu'!F223 -> 0 | G60: See details
A61: full_ifrs-cor_2022-03-24.xsd#ifrs-full_RetainedEarnings | D61: *Retained earnings
A62: full_ifrs-cor_2022-03-24.xsd#ifrs-full_TreasuryShares | D62: Treasury shares
A63: full_ifrs-cor_2022-03-24.xsd#ifrs-full_OtherReserves@http://xbrl.ssm.com.my/role/ssm/lab_rol_ssmt-fs-mfrs_2022-12-31/ReportingLabel | D63: *Reserves | E63: ='SOFP-Sub-CuNonCu'!E242 -> 0 | F63: ='SOFP-Sub-CuNonCu'!F242 -> 0 | G63: See details
A64: full_ifrs-cor_2022-03-24.xsd#ifrs-full_EquityAttributableToOwnersOfParent@http://xbrl.ssm.com.my/role/ssm/fs/mfrs/lab_rol_ssmt-fs-mfrs_2022-12-31/ReportingTotalLabel | D64: *Total equity attributable to owners | E64: =1*E60+1*E61+-1*E62+1*E63 -> 0 | F64: =1*F60+1*F61+-1*F62+1*F63 -> 0
A65: ssmt-mfrs-cor_2022-12-31.xsd#ssmt-mfrs_OtherComponentsOfEquity@http://xbrl.ssm.com.my/role/ssm/lab_rol_ssmt-fs-mfrs_2022-12-31/ReportingLabel | D65: *Equity - other components | E65: ='SOFP-Sub-CuNonCu'!E249 -> 0 | F65: ='SOFP-Sub-CuNonCu'!F249 -> 0 | G65: See details
A66: full_ifrs-cor_2022-03-24.xsd#ifrs-full_NoncontrollingInterests | D66: *Non-controlling interests
A67: full_ifrs-cor_2022-03-24.xsd#ifrs-full_Equity@http://www.xbrl.org/2003/role/totalLabel | D67: *Total equity | E67: =1*E60+1*E61+-1*E62+1*E63+1*E65+1*E66 -> 0 | F67: =1*F60+1*F61+-1*F62+1*F63+1*F65+1*F66 -> 0
A68: full_ifrs-cor_2022-03-24.xsd#ifrs-full_LiabilitiesAbstract | D68: Liabilities
A69: full_ifrs-cor_2022-03-24.xsd#ifrs-full_NoncurrentLiabilitiesAbstract | D69: Non-current liabilities
A70: ssmt-mfrs-cor_2022-12-31.xsd#ssmt-mfrs_NoncurrentServiceConcessionLiabilities@http://xbrl.ssm.com.my/role/ssm/lab_rol_ssmt-fs-mfrs_2022-12-31/ReportingLabel | D70: Service concession liabilities
A71: full_ifrs-cor_2022-03-24.xsd#ifrs-full_LongtermBorrowings@http://xbrl.ssm.com.my/role/ssm/lab_rol_ssmt-fs-mfrs_2022-12-31/ReportingLabel | D71: *Borrowings | E71: ='SOFP-Sub-CuNonCu'!E291 -> 0 | F71: ='SOFP-Sub-CuNonCu'!F291 -> 0 | G71: See details
A72: ssmt-mfrs-cor_2022-12-31.xsd#ssmt-mfrs_NoncurrentFinanceLeaseLiabilities@http://xbrl.ssm.com.my/role/ssm/lab_rol_ssmt-fs-mfrs_2022-12-31/ReportingLabel | D72: Lease liabilities
A73: full_ifrs-cor_2022-03-24.xsd#ifrs-full_NoncurrentProvisionsForEmployeeBenefits@http://xbrl.ssm.com.my/role/ssm/lab_rol_ssmt-fs-mfrs_2022-12-31/ReportingLabel | D73: *Employee benefit liabilities | E73: ='SOFP-Sub-CuNonCu'!E300 -> 0 | F73: ='SOFP-Sub-CuNonCu'!F300 -> 0 | G73: See details
A74: full_ifrs-cor_2022-03-24.xsd#ifrs-full_NoncurrentProvisions@http://xbrl.ssm.com.my/role/ssm/lab_rol_ssmt-fs-mfrs_2022-12-31/ReportingLabel | D74: *Provisions | E74: ='SOFP-Sub-CuNonCu'!E309 -> 0 | F74: ='SOFP-Sub-CuNonCu'!F309 -> 0 | G74: See details
A75: full_ifrs-cor_2022-03-24.xsd#ifrs-full_NoncurrentPayables | D75: *Trade and other non-current payables | E75: ='SOFP-Sub-CuNonCu'!E341 -> 0 | F75: ='SOFP-Sub-CuNonCu'!F341 -> 0 | G75: See details
A76: full_ifrs-cor_2022-03-24.xsd#ifrs-full_NoncurrentContractLiabilities@http://xbrl.ssm.com.my/role/ssm/lab_rol_ssmt-fs-mfrs_2022-12-31/ReportingLabel | D76: Contract liabilities
A77: full_ifrs-cor_2022-03-24.xsd#ifrs-full_DeferredTaxLiabilities | D77: Deferred tax liabilities
A78: full_ifrs-cor_2022-03-24.xsd#ifrs-full_NoncurrentDerivativeFinancialLiabilities@http://xbrl.ssm.com.my/role/ssm/lab_rol_ssmt-fs-mfrs_2022-12-31/ReportingLabel | D78: *Derivative financial liabilities | E78: ='SOFP-Sub-CuNonCu'!E356 -> 0 | F78: ='SOFP-Sub-CuNonCu'!F356 -> 0 | G78: See details
A79: full_ifrs-cor_2022-03-24.xsd#ifrs-full_OtherNoncurrentLiabilities | D79: Other non-current liabilities
A80: full_ifrs-cor_2022-03-24.xsd#ifrs-full_NoncurrentLiabilities@http://www.xbrl.org/2003/role/totalLabel | D80: Total non-current liabilities | E80: =1*E70+1*E71+1*E72+1*E73+1*E74+1*E75+1*E76+1*E77+1*E78+1*E79 -> 0 | F80: =1*F70+1*F71+1*F72+1*F73+1*F74+1*F75+1*F76+1*F77+1*F78+1*F79 -> 0
A81: full_ifrs-cor_2022-03-24.xsd#ifrs-full_CurrentLiabilitiesAbstract | D81: Current liabilities
A82: full_ifrs-cor_2022-03-24.xsd#ifrs-full_CurrentPortionOfLongtermBorrowings@http://xbrl.ssm.com.my/role/ssm/lab_rol_ssmt-fs-mfrs_2022-12-31/ReportingLabel | D82: *Borrowings | E82: ='SOFP-Sub-CuNonCu'!E403 -> 0 | F82: ='SOFP-Sub-CuNonCu'!F403 -> 0 | G82: See details
A83: ssmt-mfrs-cor_2022-12-31.xsd#ssmt-mfrs_CurrentFinanceLeaseLiabilities@http://xbrl.ssm.com.my/role/ssm/lab_rol_ssmt-fs-mfrs_2022-12-31/ReportingLabel | D83: Lease liabilities
A84: full_ifrs-cor_2022-03-24.xsd#ifrs-full_CurrentProvisionsForEmployeeBenefits@http://xbrl.ssm.com.my/role/ssm/lab_rol_ssmt-fs-mfrs_2022-12-31/ReportingLabel | D84: *Employee benefit liabilities | E84: ='SOFP-Sub-CuNonCu'!E412 -> 0 | F84: ='SOFP-Sub-CuNonCu'!F412 -> 0 | G84: See details
A85: full_ifrs-cor_2022-03-24.xsd#ifrs-full_CurrentProvisions@http://xbrl.ssm.com.my/role/ssm/lab_rol_ssmt-fs-mfrs_2022-12-31/ReportingLabel | D85: *Provisions | E85: ='SOFP-Sub-CuNonCu'!E421 -> 0 | F85: ='SOFP-Sub-CuNonCu'!F421 -> 0 | G85: See details
A86: full_ifrs-cor_2022-03-24.xsd#ifrs-full_CurrentTaxLiabilitiesCurrent@http://xbrl.ssm.com.my/role/ssm/lab_rol_ssmt-fs-mfrs_2022-12-31/ReportingLabel | D86: Current tax liabilities
A87: full_ifrs-cor_2022-03-24.xsd#ifrs-full_TradeAndOtherCurrentPayables | D87: *Trade and other current payables | E87: ='SOFP-Sub-CuNonCu'!E457 -> 0 | F87: ='SOFP-Sub-CuNonCu'!F457 -> 0 | G87: See details
A88: full_ifrs-cor_2022-03-24.xsd#ifrs-full_CurrentContractLiabilities@http://xbrl.ssm.com.my/role/ssm/lab_rol_ssmt-fs-mfrs_2022-12-31/ReportingLabel | D88: Contract liabilities
A89: full_ifrs-cor_2022-03-24.xsd#ifrs-full_CurrentDerivativeFinancialLiabilities@http://xbrl.ssm.com.my/role/ssm/lab_rol_ssmt-fs-mfrs_2022-12-31/ReportingLabel | D89: *Derivative financial liabilities | E89: ='SOFP-Sub-CuNonCu'!E472 -> 1100 | F89: ='SOFP-Sub-CuNonCu'!F472 -> 0 | G89: See details
A90: full_ifrs-cor_2022-03-24.xsd#ifrs-full_OtherCurrentLiabilities | D90: Other current liabilities
A91: full_ifrs-cor_2022-03-24.xsd#ifrs-full_CurrentLiabilitiesOtherThanLiabilitiesIncludedInDisposalGroupsClassifiedAsHeldForSale@http://xbrl.ssm.com.my/role/ssm/fs/mfrs/lab_rol_ssmt-fs-mfrs_2022-12-31/ReportingTotalLabel | D91: Total current liabilities other than liabilities held for sale | E91: =1*E82+1*E83+1*E84+1*E85+1*E86+1*E87+1*E88+1*E89+1*E90 -> 1100 | F91: =1*F82+1*F83+1*F84+1*F85+1*F86+1*F87+1*F88+1*F89+1*F90 -> 0
A92: full_ifrs-cor_2022-03-24.xsd#ifrs-full_LiabilitiesIncludedInDisposalGroupsClassifiedAsHeldForSale | D92: *Liabilities included in disposal groups classified as held for sale
A93: full_ifrs-cor_2022-03-24.xsd#ifrs-full_CurrentLiabilities@http://www.xbrl.org/2003/role/totalLabel | D93: *Total current liabilities | E93: =1*E82+1*E83+1*E84+1*E85+1*E86+1*E87+1*E88+1*E89+1*E90+1*E92 -> 1100 | F93: =1*F82+1*F83+1*F84+1*F85+1*F86+1*F87+1*F88+1*F89+1*F90+1*F92 -> 0
A94: full_ifrs-cor_2022-03-24.xsd#ifrs-full_Liabilities@http://www.xbrl.org/2003/role/totalLabel | D94: *Total liabilities | E94: =1*E70+1*E71+1*E72+1*E73+1*E74+1*E75+1*E76+1*E77+1*E78+1*E79+1*E82+1*E83+1*E84+1*E85+1*E86+1*E87+1*E88+1*E89+1*E90+1*E92 -> 1100 | F94: =1*F70+1*F71+1*F72+1*F73+1*F74+1*F75+1*F76+1*F77+1*F78+1*F79+1*F82+1*F83+1*F84+1*F85+1*F86+1*F87+1*F88+1*F89+1*F90+1*F92 -> 0
A95: full_ifrs-cor_2022-03-24.xsd#ifrs-full_EquityAndLiabilities@http://www.xbrl.org/2003/role/totalLabel | D95: *Total equity and liabilities | E95: =1*E67+1*E94 -> 1100 | F95: =1*F67+1*F94 -> 0
C96: #TABLE#
C97: #LAYOUTSCER# | H97: #LAYOUTECER#

Sheet SOFP-Sub-CuNonCu
A1: c34185e3-d692-47ad-8a98-d791585875b8:~:AtleastOneValueInAnyLayout:~:True:~:<?xml version="1.0" encoding="utf-16"?>_x000D_ <Customization xmlns:xsi="http://www.w3.org/2001/XMLSchema-instance" xmlns:xsd="http://www.w3.org/2001/XMLSchema" ComparitiveDate="False" LayoutByDate="False" LayoutByCompany="False" ShowAllDomains="False" TotalDomain="True" DefaultDates="2" />:~:http://xbrl.ssm.com.my/role/ssm/rol_ssmt-fs-mfrs_2022-12-31/ssmt-fs-mfrs_2022-12-31_role-200200x:~:None
D2: FS-MFRS Sub-classification of assets, liabilities and equity, by current/non-current method
D3: * denotes mandatory items to be reported
C5: b9877f0c-4ab2-476f-b54d-a35a3e867c6a:~:SOFP-Sub-CuNonCu_1_TBLYT:~:NotMandatory:~:False:~:0:~:True:~:<?xml version="1.0" encoding="utf-16"?>_x000D_ <Customization xmlns:xsi="http://www.w3.org/2001/XMLSchema-instance" xmlns:xsd="http://www.w3.org/2001/XMLSchema" ComparitiveDate="False" LayoutByDate="False" LayoutByCompany="False" ShowAllDomains="False" TotalDomain="True" DefaultDates="2" />:~:LytTxb:~::~:False:~:True:~:ssmt-mfrs-cor_2022-12-31.xsd#ssmt-mfrs_DisclosureOnSubclassificationOfAssetsLiabilitiesAndEquityAbstract@http://www.xbrl.org/2003/role/label:~:
C8: #LAYOUTSCSR# | D8: #PRIM# | F8: #TABLE# | G8: #LAYOUTECSR#
C9: #TABLE#
A10: ssmt-mfrs-cor_2022-12-31.xsd#ssmt-mfrs_DisclosureOnSubclassificationOfAssetsLiabilitiesAndEquityAbstract | D10: Disclosure on sub-classification of assets, liabilities and equity
C11: #TABLE#
C12: #LAYOUTSCER# | G12: #LAYOUTECER#
C15: bee4d44c-2d67-4d65-9d5f-8f366adca267:~:SOFP-Sub-CuNonCu_2:~:NotMandatory:~:True:~:1:~:True:~:<?xml version="1.0" encoding="utf-16"?>_x000D_ <Customization xmlns:xsi="http://www.w3.org/2001/XMLSchema-instance" xmlns:xsd="http://www.w3.org/2001/XMLSchema" ComparitiveDate="False" LayoutByDate="False" LayoutByCompany="False" ShowAllDomains="False" TotalDomain="True" DefaultDates="2" />:~:LytHyc:~:ssmt-mfrs-cor_2022-12-31.xsd#ssmt-mfrs_StatementOnSubclassificationOfAssetsLiabilitiesAndEquityTable:~:False:~:True:~:ssmt-mfrs-cor_2022-12-31.xsd#ssmt-mfrs_DisclosureOnSubclassificationOfAssetsLiabilitiesAndEquityAbstract@http://www.xbrl.org/2003/role/label::ssmt-mfrs-cor_2022-12-31.xsd#ssmt-mfrs_StatementOnSubclassificationOfAssetsLiabilitiesAndEquityAbstract@http://www.xbrl.org/2003/role/label::ssmt-mfrs-cor_2022-12-31.xsd#ssmt-mfrs_StatementOnSubclassificationOfAssetsLiabilitiesAndEquityLineItems@http://www.xbrl.org/2003/role/label:~:ssmt-mfrs-cor_2022-12-31.xsd#ssmt-mfrs_StatementOnSubclassificationOfAssetsLiabilitiesAndEquityTable
C18: #LAYOUTSCSR# | D18: #PRIM# | G18: #TABLE# | H18: #LAYOUTECSR#
C19: #STDTENDTDATE# | E19: =TEXT(DATE(MID(E21,7,4),MID(E21,4,2),MID(E21,1,2)),"dd/MM/yyyy")&" - "&TEXT(DATE(MID(E22,7,4),MID(E22,4,2),MID(E22,1,2)),"dd/MM/yyyy") -> 01/01/2024 - 31/12/2024 | F19: =TEXT(DATE(MID(F21,7,4),MID(F21,4,2),MID(F21,1,2)),"dd/MM/yyyy")&" - "&TEXT(DATE(MID(F22,7,4),MID(F22,4,2),MID(F22,1,2)),"dd/MM/yyyy") -> 01/01/2023 - 31/12/2023
C20: #UNITSCALE# | E20: =StartUp!$E$8 -> MYR'000 | F20: =StartUp!$E$8 -> MYR'000
C21: #STDT# | E21: =StartUp!$D$8 -> 01/01/2024 | F21: =StartUp!$D$10 -> 01/01/2023
C22: #ENDT# | E22: =StartUp!$D$9 -> 31/12/2024 | F22: =StartUp!$D$11 -> 31/12/2023
C23: #TABLE#
A24: ssmt-mfrs-cor_2022-12-31.xsd#ssmt-mfrs_StatementOnSubclassificationOfAssetsLiabilitiesAndEquityAbstract | D24: Statement on sub-classification of assets, liabilities and equity
A25: ssmt-mfrs-cor_2022-12-31.xsd#ssmt-mfrs_StatementOnSubclassificationOfAssetsLiabilitiesAndEquityLineItems | D25: Statement on sub-classification of assets, liabilities and equity
A26: ssmt-mfrs-cor_2022-12-31.xsd#ssmt-mfrs_SubclassificationOfAssetsLiabilitiesAndEquityAbstract | D26: Sub-classification of assets, liabilities and equity
A27: full_ifrs-cor_2022-03-24.xsd#ifrs-full_PropertyPlantAndEquipmentAbstract | D27: Property, plant and equipment
A28: full_ifrs-cor_2022-03-24.xsd#ifrs-full_LandAndBuildingsAbstract | D28: Land and buildings
A29: ssmt-mfrs-cor_2022-12-31.xsd#ssmt-mfrs_LandAbstract | D29: Land
A30: ssmt-mfrs-cor_2022-12-31.xsd#ssmt-mfrs_FreeholdLand | D30: Freehold land
A31: ssmt-mfrs-cor_2022-12-31.xsd#ssmt-mfrs_LongtermLeaseholdLand | D31: Long term leasehold land
A32: ssmt-mfrs-cor_2022-12-31.xsd#ssmt-mfrs_ShorttermLeaseholdLand | D32: Short term leasehold land
A33: full_ifrs-cor_2022-03-24.xsd#ifrs-full_Land@http://www.xbrl.org/2003/role/totalLabel | D33: Total land | E33: =1*E30+1*E31+1*E32 -> 0 | F33: =1*F30+1*F31+1*F32 -> 0
A34: ssmt-mfrs-cor_2022-12-31.xsd#ssmt-mfrs_BuildingAbstract | D34: Buildings
A35: ssmt-mfrs-cor_2022-12-31.xsd#ssmt-mfrs_BuildingOnFreeholdLand | D35: Building on freehold land | E35: 1000000
A36: ssmt-mfrs-cor_2022-12-31.xsd#ssmt-mfrs_BuildingOnLongtermLeaseholdLand | D36: Building on long term leasehold land
A37: ssmt-mfrs-cor_2022-12-31.xsd#ssmt-mfrs_BuildingOnShorttermLeaseholdLand | D37: Building on short term leasehold land
A38: ssmt-mfrs-cor_2022-12-31.xsd#ssmt-mfrs_LeasedProperties | D38: Leased properties
A39: full_ifrs-cor_2022-03-24.xsd#ifrs-full_Buildings@http://xbrl.ssm.com.my/role/ssm/fs/mfrs/lab_rol_ssmt-fs-mfrs_2022-12-31/ReportingTotalLabel | D39: Total buildings | E39: =1*E35+1*E36+1*E37+1*E38 -> 1000000 | F39: =1*F35+1*F36+1*F37+1*F38 -> 0
A40: full_ifrs-cor_2022-03-24.xsd#ifrs-full_LandAndBuildings@http://www.xbrl.org/2003/role/totalLabel | D40: Total land and buildings | E40: =1*E33+1*E39 -> 1000000 | F40: =1*F33+1*F39 -> 0
A41: full_ifrs-cor_2022-03-24.xsd#ifrs-full_VehiclesAbstract | D41: Vehicles
A42: ssmt-mfrs-cor_2022-12-31.xsd#ssmt-mfrs_Vessels | D42: Vessels
A43: full_ifrs-cor_2022-03-24.xsd#ifrs-full_Aircraft | D43: Aircraft
A44: full_ifrs-cor_2022-03-24.xsd#ifrs-full_MotorVehicles | D44: Motor vehicles
A45: ssmt-mfrs-cor_2022-12-31.xsd#ssmt-mfrs_OtherVehicles | D45: Other vehicles
A46: full_ifrs-cor_2022-03-24.xsd#ifrs-full_Vehicles@http://www.xbrl.org/2003/role/totalLabel | D46: Total vehicles | E46: =1*E42+1*E43+1*E44+1*E45 -> 0 | F46: =1*F42+1*F43+1*F44+1*F45 -> 0
A47: full_ifrs-cor_2022-03-24.xsd#ifrs-full_Machinery | D47: Machinery
A48: ssmt-mfrs-cor_2022-12-31.xsd#ssmt-mfrs_PlantAndEquipment | D48: Plant and equipment
A49: ssmt-mfrs-cor_2022-12-31.xsd#ssmt-mfrs_OfficeEquipmentFixtureAndFittings | D49: Office equipment, fixture and fittings
A50: ssmt-mfrs-cor_2022-12-31.xsd#ssmt-mfrs_ComputerSoftwareAndHardware | D50: Computer software and hardware
A51: full_ifrs-cor_2022-03-24.xsd#ifrs-full_BearerPlants | D51: Bearer plants
A52: ssmt-mfrs-cor_2022-12-31.xsd#ssmt-mfrs_InfrastructureAndSiteFacilities | D52: Infrastructure and site facilities
A53: full_ifrs-cor_2022-03-24.xsd#ifrs-full_MiningAssets | D53: Mining assets
A54: full_ifrs-cor_2022-03-24.xsd#ifrs-full_OilAndGasAssets | D54: Oil and gas assets
A55: ssmt-mfrs-cor_2022-12-31.xsd#ssmt-mfrs_TangibleExplorationAndEvaluationAssets | D55: Tangible exploration and evaluation assets
A56: ssmt-mfrs-cor_2022-12-31.xsd#ssmt-mfrs_TelecommunicationEquipments | D56: Telecommunication equipments
A57: full_ifrs-cor_2022-03-24.xsd#ifrs-full_ConstructionInProgress@http://xbrl.ssm.com.my/role/ssm/lab_rol_ssmt-fs-mfrs_2022-12-31/ReportingLabel | D57: Construction in progress/Asset work-in progress
A58: full_ifrs-cor_2022-03-24.xsd#ifrs-full_OtherPropertyPlantAndEquipment | D58: Other property, plant and equipment
A59: full_ifrs-cor_2022-03-24.xsd#ifrs-full_PropertyPlantAndEquipment@http://www.xbrl.org/2003/role/totalLabel | D59: *Total property, plant and equipment | E59: =1*E40+1*E46+1*E47+1*E48+1*E49+1*E50+1*E51+1*E52+1*E53+1*E54+1*E55+1*E56+1*E57+1*E58 -> 1000000 | F59: =1*F40+1*F46+1*F47+1*F48+1*F49+1*F50+1*F51+1*F52+1*F53+1*F54+1*F55+1*F56+1*F57+1*F58 -> 0 | G59: See details
A60: full_ifrs-cor_2022-03-24.xsd#ifrs-full_InvestmentPropertyAbstract | D60: Investment property
A61: ssmt-mfrs-cor_2022-12-31.xsd#ssmt-mfrs_InvestmentPropertiesCompletedAtFairValueAbstract@http://xbrl.ssm.com.my/role/ssm/lab_rol_ssmt-fs-mfrs_2022-12-31/ReportingLabel | D61: Investment properties completed, at carrying value
A62: ssmt-mfrs-cor_2022-12-31.xsd#ssmt-mfrs_InvestmentPropertyFreeholdLandAndBuilding | D62: Freehold land and building
A63: ssmt-mfrs-cor_2022-12-31.xsd#ssmt-mfrs_InvestmentPropertyLeaseholdLandAndBuilding | D63: Leasehold land and building
A64: full_ifrs-cor_2022-03-24.xsd#ifrs-full_InvestmentPropertyCompleted@http://xbrl.ssm.com.my/role/ssm/fs/mfrs/lab_rol_ssmt-fs-mfrs_2022-12-31/ReportingTotalLabel | D64: Total investment properties completed, at carrying value | E64: =1*E62+1*E63 -> 0 | F64: =1*F62+1*F63 -> 0
A65: ssmt-mfrs-cor_2022-12-31.xsd#ssmt-mfrs_InvestmentPropertiesUnderConstructionOrDevelopmentAtCostAbstract | D65: Investment properties under construction or development, at cost
A66: ssmt-mfrs-cor_2022-12-31.xsd#ssmt-mfrs_InvestmentPropertyBuildingUnderConstruction | D66: Building under construction
A67: full_ifrs-cor_2022-03-24.xsd#ifrs-full_InvestmentPropertyUnderConstructionOrDevelopment@http://xbrl.ssm.com.my/role/ssm/fs/mfrs/lab_rol_ssmt-fs-mfrs_2022-12-31/ReportingTotalLabel | D67: Total investment properties under construction or development, at cost | E67: =1*E66 -> 0 | F67: =1*F66 -> 0
A68: ssmt-mfrs-cor_2022-12-31.xsd#ssmt-mfrs_OtherInvestmentProperty | D68: Other investment property
A69: full_ifrs-cor_2022-03-24.xsd#ifrs-full_InvestmentProperty@http://xbrl.ssm.com.my/role/ssm/fs/mfrs/lab_rol_ssmt-fs-mfrs_2022-12-31/ReportingTotalLabel | D69: *Total investment properties | E69: =1*E64+1*E67+1*E68 -> 0 | F69: =1*F64+1*F67+1*F68 -> 0 | G69: See details
A70: ssmt-mfrs-cor_2022-12-31.xsd#ssmt-mfrs_BiologicalAssetsAbstract | D70: Biological assets
A71: ssmt-mfrs-cor_2022-12-31.xsd#ssmt-mfrs_ConsumableBiologicalAssets | D71: Consumable biological assets
A72: ssmt-mfrs-cor_2022-12-31.xsd#ssmt-mfrs_BearerBiologicalAssets | D72: Bearer biological assets
A73: full_ifrs-cor_2022-03-24.xsd#ifrs-full_BiologicalAssets@http://xbrl.ssm.com.my/role/ssm/fs/mfrs/lab_rol_ssmt-fs-mfrs_2022-12-31/ReportingTotalLabel | D73: Total biological assets | E73: =1*E71+1*E72 -> 0 | F73: =1*F71+1*F72 -> 0
A74: full_ifrs-cor_2022-03-24.xsd#ifrs-full_IntangibleAssetsAndGoodwillAbstract | D74: Intangible assets and goodwill
A75: full_ifrs-cor_2022-03-24.xsd#ifrs-full_IntangibleAssetsOtherThanGoodwillAbstract | D75: Intangible assets other than goodwill
A76: full_ifrs-cor_2022-03-24.xsd#ifrs-full_CustomerrelatedIntangibleAssetsRecognisedAsOfAcquisitionDate@http://xbrl.ssm.com.my/role/ssm/lab_rol_ssmt-fs-mfrs_2022-12-31/ReportingLabel | D76: Customer acquisition costs
A77: full_ifrs-cor_2022-03-24.xsd#ifrs-full_BrandNames | D77: Brand names
A78: ssmt-mfrs-cor_2022-12-31.xsd#ssmt-mfrs_CustomerRelationships | D78: Customer relationships
A79: full_ifrs-cor_2022-03-24.xsd#ifrs-full_CopyrightsPatentsAndOtherIndustrialPropertyRightsServiceAndOperatingRights | D79: Copyrights, patents and other industrial property rights, service and operating rights
A80: full_ifrs-cor_2022-03-24.xsd#ifrs-full_IntangibleAssetsUnderDevelopment | D80: Intangible assets under development
A81: full_ifrs-cor_2022-03-24.xsd#ifrs-full_IntangibleExplorationAndEvaluationAssets | D81: Intangible exploration and evaluation assets
A82: full_ifrs-cor_2022-03-24.xsd#ifrs-full_LicencesAndFranchises | D82: Licences and franchises
A83: full_ifrs-cor_2022-03-24.xsd#ifrs-full_RecipesFormulaeModelsDesignsAndPrototypes | D83: Recipes, formulae, models, designs and prototypes
A84: full_ifrs-cor_2022-03-24.xsd#ifrs-full_ComputerSoftware | D84: Computer software
A85: ssmt-mfrs-cor_2022-12-31.xsd#ssmt-mfrs_SmallHolderRelationship | D85: Small holder relationship
A86: full_ifrs-cor_2022-03-24.xsd#ifrs-full_OtherIntangibleAssets | D86: Other intangible assets
A87: full_ifrs-cor_2022-03-24.xsd#ifrs-full_IntangibleAssetsOtherThanGoodwill@http://www.xbrl.org/2003/role/totalLabel | D87: Total intangible assets other than goodwill | E87: =1*E76+1*E77+1*E78+1*E79+1*E80+1*E81+1*E82+1*E83+1*E84+1*E85+1*E86 -> 0 | F87: =1*F76+1*F77+1*F78+1*F79+1*F80+1*F81+1*F82+1*F83+1*F84+1*F85+1*F86 -> 0
A88: full_ifrs-cor_2022-03-24.xsd#ifrs-full_Goodwill | D88: Goodwill
A89: full_ifrs-cor_2022-03-24.xsd#ifrs-full_IntangibleAssetsAndGoodwill@http://www.xbrl.org/2003/role/totalLabel | D89: *Total intangible assets and goodwill | E89: =1*E87+1*E88 -> 0 | F89: =1*F87+1*F88 -> 0 | G89: See details
A90: ssmt-mfrs-cor_2022-12-31.xsd#ssmt-mfrs_InvestmentsInSubsidiariesAbstract | D90: Investments in subsidiaries
A91: ssmt-mfrs-cor_2022-12-31.xsd#ssmt-mfrs_InvestmentInSubsidiariesUnquotedSharesInMalaysiaNetOfImpairmentLosses@http://xbrl.ssm.com.my/role/ssm/lab_rol_ssmt-fs-mfrs_2022-12-31/ReportingLabel | D91: Unquoted shares, net of impairment losses
A92: ssmt-mfrs-cor_2022-12-31.xsd#ssmt-mfrs_InvestmentInSubsidiariesQuotedSharesInMalaysia@http://xbrl.ssm.com.my/role/ssm/lab_rol_ssmt-fs-mfrs_2022-12-31/ReportingLabel | D92: Quoted shares in Malaysia
A93: ssmt-mfrs-cor_2022-12-31.xsd#ssmt-mfrs_InvestmentInSubsidiariesQuotedSharesOutsideMalaysia@http://xbrl.ssm.com.my/role/ssm/lab_rol_ssmt-fs-mfrs_2022-12-31/ReportingLabel | D93: Quoted shares outside Malaysia
A94: ssmt-mfrs-cor_2022-12-31.xsd#ssmt-mfrs_InvestmentInSubsidiariesFairValueAdjustmentsOnLoansAndAdvancesAndFinancialGuarantee@http://xbrl.ssm.com.my/role/ssm/lab_rol_ssmt-fs-mfrs_2022-12-31/ReportingLabel | D94: Fair value adjustments on loans and advances and financial guarantee
A95: ssmt-mfrs-cor_2022-12-31.xsd#ssmt-mfrs_ContributionsToSubsidiariesNetOfImpairmentLosses | D95: Contributions to subsidiaries, net of impairment losses
A96: ssmt-mfrs-cor_2022-12-31.xsd#ssmt-mfrs_InvestmentsInSubsidiariesOtherInvestmentsNetOfImpairmentLosses@http://xbrl.ssm.com.my/role/ssm/lab_rol_ssmt-fs-mfrs_2022-12-31/ReportingLabel | D96: Other investments in subsidiaries
A97: full_ifrs-cor_2022-03-24.xsd#ifrs-full_InvestmentsInSubsidiaries@http://xbrl.ssm.com.my/role/ssm/fs/mfrs/lab_rol_ssmt-fs-mfrs_2022-12-31/ReportingTotalLabel | D97: *Total investments in subsidiaries | E97: =1*E91+1*E92+1*E93+1*E94+1*E95+1*E96 -> 0 | F97: =1*F91+1*F92+1*F93+1*F94+1*F95+1*F96 -> 0 | G97: See details
A98: ssmt-mfrs-cor_2022-12-31.xsd#ssmt-mfrs_InvestmentsInAssociatesAbstract | D98: Investments in associates
A99: ssmt-mfrs-cor_2022-12-31.xsd#ssmt-mfrs_InvestmentInAssociatesUnquotedSharesInMalaysiaNetOfImpairmentLosses@http://xbrl.ssm.com.my/role/ssm/lab_rol_ssmt-fs-mfrs_2022-12-31/ReportingLabel | D99: Unquoted shares, net of impairment losses
A100: ssmt-mfrs-cor_2022-12-31.xsd#ssmt-mfrs_InvestmentInAssociatesQuotedSharesInMalaysia@http://xbrl.ssm.com.my/role/ssm/lab_rol_ssmt-fs-mfrs_2022-12-31/ReportingLabel | D100: Quoted shares in Malaysia
A101: ssmt-mfrs-cor_2022-12-31.xsd#ssmt-mfrs_InvestmentInAssociatesQuotedSharesOutsideMalaysia@http://xbrl.ssm.com.my/role/ssm/lab_rol_ssmt-fs-mfrs_2022-12-31/ReportingLabel | D101: Quoted shares outside Malaysia
A102: ssmt-mfrs-cor_2022-12-31.xsd#ssmt-mfrs_InvestmentInAssociatesFairValueAdjustmentsOnLoansAndAdvancesAndFinancialGuarantee@http://xbrl.ssm.com.my/role/ssm/lab_rol_ssmt-fs-mfrs_2022-12-31/ReportingLabel | D102: Fair value adjustments on loans and advances and financial guarantee
A103: ssmt-mfrs-cor_2022-12-31.xsd#ssmt-mfrs_InvestmentsInAssociatesShareOfPostAcquisitionProfitsAndReserves | D103: Share of post-acquisition profits and reserves
A104: ssmt-mfrs-cor_2022-12-31.xsd#ssmt-mfrs_InvestmentInAssociatesUnrealisedProfitOnTransactionsWithAssociates@http://xbrl.ssm.com.my/role/ssm/lab_rol_ssmt-fs-mfrs_2022-12-31/ReportingLabel | D104: Unrealised profit on transactions with associates
A105: ssmt-mfrs-cor_2022-12-31.xsd#ssmt-mfrs_InvestmentsInAssociatesOtherInvestmentsNetOfImpairmentLosses@http://xbrl.ssm.com.my/role/ssm/lab_rol_ssmt-fs-mfrs_2022-12-31/ReportingLabel | D105: Other investments in associates
A106: full_ifrs-cor_2022-03-24.xsd#ifrs-full_InvestmentsInAssociates@http://xbrl.ssm.com.my/role/ssm/fs/mfrs/lab_rol_ssmt-fs-mfrs_2022-12-31/ReportingTotalLabel | D106: *Total investments in associates | E106: =1*E99+1*E100+1*E101+1*E102+1*E103+1*E104+1*E105 -> 0 | F106: =1*F99+1*F100+1*F101+1*F102+1*F103+1*F104+1*F105 -> 0 | G106: See details
A107: ssmt-mfrs-cor_2022-12-31.xsd#ssmt-mfrs_InvestmentsInJointVentureAbstract | D107: Investments in joint ventures
...

Sheet SOPL-Function
A1: e626cc5a-923a-4892-95e5-46c3f6ce1818:~:AtleastOneValueInAnyLayout:~:True:~:<?xml version="1.0" encoding="utf-16"?>_x000D_ <Customization xmlns:xsi="http://www.w3.org/2001/XMLSchema-instance" xmlns:xsd="http://www.w3.org/2001/XMLSchema" ComparitiveDate="False" LayoutByDate="False" LayoutByCompany="False" ShowAllDomains="False" TotalDomain="True" DefaultDates="2" />:~:http://xbrl.ssm.com.my/role/ssm/rol_ssmt-fs-mfrs_2022-12-31/ssmt-fs-mfrs_2022-12-31_role-300100x:~:None
D2: FS-MFRS Statement of profit or loss, by function of expense
D3: * denotes mandatory items to be reported
C5: 51d9dbc9-4f1f-49fa-bd4a-66bd69bffe70:~:SOPL-Function_1_TBLYT:~:NotMandatory:~:False:~:0:~:True:~:<?xml version="1.0" encoding="utf-16"?>_x000D_ <Customization xmlns:xsi="http://www.w3.org/2001/XMLSchema-instance" xmlns:xsd="http://www.w3.org/2001/XMLSchema" ComparitiveDate="False" LayoutByDate="False" LayoutByCompany="False" ShowAllDomains="False" TotalDomain="True" DefaultDates="2" />:~:LytTxb:~::~:False:~:True:~:ssmt-cor_2022-12-31.xsd#ssmt_DisclosureOnStatementOfProfitOrLossAbstract@http://www.xbrl.org/2003/role/label:~:
C8: #LAYOUTSCSR# | D8: #PRIM# | F8: #TABLE# | G8: #LAYOUTECSR#
C9: #TABLE#
A10: ssmt-cor_2022-12-31.xsd#ssmt_DisclosureOnStatementOfProfitOrLossAbstract | D10: Disclosure on statement of profit or loss
C11: #TABLE#
C12: #LAYOUTSCER# | G12: #LAYOUTECER#
C15: 1dd880d0-8b74-4382-a51d-a00d3dbba064:~:SOPL-Function_2:~:NotMandatory:~:True:~:1:~:True:~:<?xml version="1.0" encoding="utf-16"?>_x000D_ <Customization xmlns:xsi="http://www.w3.org/2001/XMLSchema-instance" xmlns:xsd="http://www.w3.org/2001/XMLSchema" ComparitiveDate="False" LayoutByDate="False" LayoutByCompany="False" ShowAllDomains="False" TotalDomain="True" DefaultDates="2" />:~:LytHyc:~:ssmt-cor_2022-12-31.xsd#ssmt_StatementOfProfitOrLossTable:~:False:~:True:~:ssmt-cor_2022-12-31.xsd#ssmt_DisclosureOnStatementOfProfitOrLossAbstract@http://www.xbrl.org/2003/role/label::ssmt-cor_2022-12-31.xsd#ssmt_StatementOfProfitOrLossAbstract@http://www.xbrl.org/2003/role/label::ssmt-cor_2022-12-31.xsd#ssmt_StatementOfProfitOrLossLineItems@http://www.xbrl.org/2003/role/label:~:ssmt-cor_2022-12-31.xsd#ssmt_StatementOfProfitOrLossTable
C18: #LAYOUTSCSR# | D18: #PRIM# | G18: #TABLE# | H18: #LAYOUTECSR#
C19: #STDTENDTDATE# | E19: =TEXT(DATE(MID(E21,7,4),MID(E21,4,2),MID(E21,1,2)),"dd/MM/yyyy")&" - "&TEXT(DATE(MID(E22,7,4),MID(E22,4,2),MID(E22,1,2)),"dd/MM/yyyy") -> 01/01/2024 - 31/12/2024 | F19: =TEXT(DATE(MID(F21,7,4),MID(F21,4,2),MID(F21,1,2)),"dd/MM/yyyy")&" - "&TEXT(DATE(MID(F22,7,4),MID(F22,4,2),MID(F22,1,2)),"dd/MM/yyyy") -> 01/01/2023 - 31/12/2023
C20: #UNITSCALE# | E20: =StartUp!$E$8 -> MYR'000 | F20: =StartUp!$E$8 -> MYR'000
C21: #STDT# | E21: =StartUp!$D$8 -> 01/01/2024 | F21: =StartUp!$D$10 -> 01/01/2023
C22: #ENDT# | E22: =StartUp!$D$9 -> 31/12/2024 | F22: =StartUp!$D$11 -> 31/12/2023
C23: #TABLE#
A24: ssmt-cor_2022-12-31.xsd#ssmt_StatementOfProfitOrLossAbstract | D24: Statement of Profit or Loss
A25: ssmt-cor_2022-12-31.xsd#ssmt_StatementOfProfitOrLossLineItems | D25: Statement of profit or loss
A26: ssmt-mfrs-cor_2022-12-31.xsd#ssmt-mfrs_ContinuingOperationsAbstract | D26: Continuing operations
A27: full_ifrs-cor_2022-03-24.xsd#ifrs-full_Revenue | D27: *Revenue | E27: ='SOPL-Analysis-Function'!E60 -> 0 | F27: ='SOPL-Analysis-Function'!F60 -> 0 | G27: See details
A28: full_ifrs-cor_2022-03-24.xsd#ifrs-full_CostOfSales | D28: *Cost of sales | E28: ='SOPL-Analysis-Function'!E67 -> 0 | F28: ='SOPL-Analysis-Function'!F67 -> 0 | G28: See details
A29: full_ifrs-cor_2022-03-24.xsd#ifrs-full_GrossProfit@http://www.xbrl.org/2009/role/netLabel | D29: *Gross profit | E29: =1*E27+-1*E28 -> 0 | F29: =1*F27+-1*F28 -> 0
A30: full_ifrs-cor_2022-03-24.xsd#ifrs-full_OtherIncome | D30: *Other income | E30: ='SOPL-Analysis-Function'!E110 -> 0 | F30: ='SOPL-Analysis-Function'!F110 -> 0 | G30: See details
A31: ssmt-mfrs-cor_2022-12-31.xsd#ssmt-mfrs_SellingAndDistributionExpenses | D31: Selling and distribution expenses
A32: full_ifrs-cor_2022-03-24.xsd#ifrs-full_AdministrativeExpense | D32: *Administrative expenses
A33: full_ifrs-cor_2022-03-24.xsd#ifrs-full_ResearchAndDevelopmentExpense | D33: Research and development expense
A34: full_ifrs-cor_2022-03-24.xsd#ifrs-full_OtherExpenseByFunction@http://xbrl.ssm.com.my/role/ssm/lab_rol_ssmt-fs-mfrs_2022-12-31/ReportingLabel | D34: *Other expenses | E34: ='SOPL-Analysis-Function'!E154 -> 0 | F34: ='SOPL-Analysis-Function'!F154 -> 0 | G34: See details
A35: full_ifrs-cor_2022-03-24.xsd#ifrs-full_ProfitLossFromOperatingActivities@http://www.xbrl.org/2003/role/totalLabel | D35: Profit (loss) from operating activities | E35: =1*E27+-1*E28+1*E30+-1*E31+-1*E32+-1*E33+-1*E34 -> 0 | F35: =1*F27+-1*F28+1*F30+-1*F31+-1*F32+-1*F33+-1*F34 -> 0
A36: full_ifrs-cor_2022-03-24.xsd#ifrs-full_FinanceIncome | D36: *Finance income | E36: ='SOPL-Analysis-Function'!E158 -> 0 | F36: ='SOPL-Analysis-Function'!F158 -> 0 | G36: See details
A37: full_ifrs-cor_2022-03-24.xsd#ifrs-full_FinanceCosts | D37: *Finance costs
A38: full_ifrs-cor_2022-03-24.xsd#ifrs-full_ShareOfProfitLossOfAssociatesAndJointVenturesAccountedForUsingEquityMethod | D38: Share of profit (loss) of associates and joint ventures accounted for using equity method
A39: ssmt-mfrs-cor_2022-12-31.xsd#ssmt-mfrs_FairValuationGainLossArisingFromDistributionOfNoncashAssetsToOwners | D39: Fair valuation gain (loss) arising from distribution of non-cash assets to owners
A40: full_ifrs-cor_2022-03-24.xsd#ifrs-full_ProfitLossBeforeTax@http://www.xbrl.org/2003/role/totalLabel | D40: *Profit (loss) before tax | E40: =1*E27+-1*E28+1*E30+-1*E31+-1*E32+-1*E33+-1*E34+1*E36+-1*E37+1*E38+1*E39 -> 0 | F40: =1*F27+-1*F28+1*F30+-1*F31+-1*F32+-1*F33+-1*F34+1*F36+-1*F37+1*F38+1*F39 -> 0
A41: full_ifrs-cor_2022-03-24.xsd#ifrs-full_IncomeTaxExpenseContinuingOperations@http://xbrl.ssm.com.my/role/ssm/lab_rol_ssmt-fs-mfrs_2022-12-31/ReportingLabel | D41: *Tax expense
A42: ssmt-mfrs-cor_2022-12-31.xsd#ssmt-mfrs_ContributionOfZakat | D42: Contribution of zakat
A43: full_ifrs-cor_2022-03-24.xsd#ifrs-full_ProfitLossFromContinuingOperations@http://www.xbrl.org/2003/role/totalLabel | D43: *Profit (loss) from continuing operations | E43: =1*E40+-1*E41+-1*E42 -> 0 | F43: =1*F40+-1*F41+-1*F42 -> 0
A44: ssmt-mfrs-cor_2022-12-31.xsd#ssmt-mfrs_DiscontinuedOperationsAbstract | D44: Discontinued operations
A45: full_ifrs-cor_2022-03-24.xsd#ifrs-full_ProfitLossFromDiscontinuedOperations@http://xbrl.ssm.com.my/role/ssm/lab_rol_ssmt-fs-mfrs_2022-12-31/ReportingLabel | D45: Profit (loss) from discontinued operations, net of tax
A46: full_ifrs-cor_2022-03-24.xsd#ifrs-full_ProfitLoss@http://www.xbrl.org/2003/role/totalLabel | D46: *Profit (loss) | E46: =1*E43+1*E45 -> 0 | F46: =1*F43+1*F45 -> 0 | G46: See details
A47: full_ifrs-cor_2022-03-24.xsd#ifrs-full_ProfitLossAttributableToAbstract | D47: Profit (loss), attributable to
A48: full_ifrs-cor_2022-03-24.xsd#ifrs-full_ProfitLossAttributableToOwnersOfParent | D48: Profit (loss), attributable to owners of parent
A49: ssmt-mfrs-cor_2022-12-31.xsd#ssmt-mfrs_ProfitLossAttributableToOtherComponentsOfEquity | D49: Profit (loss) attributable to equity other components
A50: full_ifrs-cor_2022-03-24.xsd#ifrs-full_ProfitLossAttributableToNoncontrollingInterests | D50: Profit (loss), attributable to non-controlling interests
A51: full_ifrs-cor_2022-03-24.xsd#ifrs-full_ProfitLoss@http://xbrl.ssm.com.my/role/ssm/fs/mfrs/lab_rol_ssmt-fs-mfrs_2022-12-31/ReportingTotalLabel | D51: *Total profit (loss) | E51: =1*E48+1*E49+1*E50 -> 0 | F51: =1*F48+1*F49+1*F50 -> 0 | G51: See details
A52: full_ifrs-cor_2022-03-24.xsd#ifrs-full_EarningsPerShareAbstract | D52: Earnings per share
A53: full_ifrs-cor_2022-03-24.xsd#ifrs-full_BasicEarningsPerShareAbstract | D53: Basic earnings per share
A54: full_ifrs-cor_2022-03-24.xsd#ifrs-full_BasicEarningsLossPerShareFromContinuingOperations | D54: Basic earnings (loss) per share from continuing operations
A55: full_ifrs-cor_2022-03-24.xsd#ifrs-full_BasicEarningsLossPerShareFromDiscontinuedOperations | D55: Basic earnings (loss) per share from discontinued operations
A56: full_ifrs-cor_2022-03-24.xsd#ifrs-full_BasicEarningsLossPerShare@http://www.xbrl.org/2003/role/totalLabel | D56: Total basic earnings (loss) per share | E56: =1*E54+1*E55 -> 0 | F56: =1*F54+1*F55 -> 0
A57: full_ifrs-cor_2022-03-24.xsd#ifrs-full_DilutedEarningsPerShareAbstract | D57: Diluted earnings per share
A58: full_ifrs-cor_2022-03-24.xsd#ifrs-full_DilutedEarningsLossPerShareFromContinuingOperations | D58: Diluted earnings (loss) per share from continuing operations
A59: full_ifrs-cor_2022-03-24.xsd#ifrs-full_DilutedEarningsLossPerShareFromDiscontinuedOperations | D59: Diluted earnings (loss) per share from discontinued operations
A60: full_ifrs-cor_2022-03-24.xsd#ifrs-full_DilutedEarningsLossPerShare@http://www.xbrl.org/2003/role/totalLabel | D60: Total diluted earnings (loss) per share | E60: =1*E58+1*E59 -> 0 | F60: =1*F58+1*F59 -> 0
C61: #TABLE#
C62: #LAYOUTSCER# | H62: #LAYOUTECER#

Sheet SOPL-Analysis-Function
A1: eadafe3e-14c4-402f-a1ac-c5a41983981f:~:AtleastOneValueInAnyLayout:~:True:~:<?xml version="1.0" encoding="utf-16"?>_x000D_ <Customization xmlns:xsi="http://www.w3.org/2001/XMLSchema-instance" xmlns:xsd="http://www.w3.org/2001/XMLSchema" ComparitiveDate="False" LayoutByDate="False" LayoutByCompany="False" ShowAllDomains="False" TotalDomain="True" DefaultDates="2" />:~:http://xbrl.ssm.com.my/role/ssm/rol_ssmt-fs-mfrs_2022-12-31/ssmt-fs-mfrs_2022-12-31_role-300200x:~:None
D2: FS-MFRS Analysis of profit or loss, by function of expense
D3: * denotes mandatory items to be reported
C5: d9ddaf2b-8017-4ca0-abda-c2a797dc7ff4:~:SOPL-Analysis-Function_1_TBLYT:~:NotMandatory:~:False:~:0:~:True:~:<?xml version="1.0" encoding="utf-16"?>_x000D_ <Customization xmlns:xsi="http://www.w3.org/2001/XMLSchema-instance" xmlns:xsd="http://www.w3.org/2001/XMLSchema" ComparitiveDate="False" LayoutByDate="False" LayoutByCompany="False" ShowAllDomains="False" TotalDomain="True" DefaultDates="2" />:~:LytTxb:~::~:False:~:True:~:ssmt-mfrs-cor_2022-12-31.xsd#ssmt-mfrs_DisclosureOnStatementOfProfitOrLossAbstract@http://www.xbrl.org/2003/role/label:~:
C8: #LAYOUTSCSR# | D8: #PRIM# | F8: #TABLE# | G8: #LAYOUTECSR#
C9: #TABLE#
A10: ssmt-mfrs-cor_2022-12-31.xsd#ssmt-mfrs_DisclosureOnStatementOfProfitOrLossAbstract | D10: Disclosure on statement of profit or loss
C11: #TABLE#
C12: #LAYOUTSCER# | G12: #LAYOUTECER#
C15: b359ba42-7d42-49c8-a7b7-2e491646c7b4:~:SOPL-Analysis-Function_2:~:NotMandatory:~:True:~:1:~:True:~:<?xml version="1.0" encoding="utf-16"?>_x000D_ <Customization xmlns:xsi="http://www.w3.org/2001/XMLSchema-instance" xmlns:xsd="http://www.w3.org/2001/XMLSchema" ComparitiveDate="False" LayoutByDate="False" LayoutByCompany="False" ShowAllDomains="False" TotalDomain="True" DefaultDates="2" />:~:LytHyc:~:ssmt-mfrs-cor_2022-12-31.xsd#ssmt-mfrs_StatementOfProfitOrLossTable:~:False:~:True:~:ssmt-mfrs-cor_2022-12-31.xsd#ssmt-mfrs_DisclosureOnStatementOfProfitOrLossAbstract@http://www.xbrl.org/2003/role/label::ssmt-mfrs-cor_2022-12-31.xsd#ssmt-mfrs_AnalysisOfProfitOrLossAbstract@http://www.xbrl.org/2003/role/label::ssmt-mfrs-cor_2022-12-31.xsd#ssmt-mfrs_StatementOfProfitOrLossLineItems@http://www.xbrl.org/2003/role/label:~:ssmt-mfrs-cor_2022-12-31.xsd#ssmt-mfrs_StatementOfProfitOrLossTable
C18: #LAYOUTSCSR# | D18: #PRIM# | G18: #TABLE# | H18: #LAYOUTECSR#
C19: #STDTENDTDATE# | E19: =TEXT(DATE(MID(E21,7,4),MID(E21,4,2),MID(E21,1,2)),"dd/MM/yyyy")&" - "&TEXT(DATE(MID(E22,7,4),MID(E22,4,2),MID(E22,1,2)),"dd/MM/yyyy") -> 01/01/2024 - 31/12/2024 | F19: =TEXT(DATE(MID(F21,7,4),MID(F21,4,2),MID(F21,1,2)),"dd/MM/yyyy")&" - "&TEXT(DATE(MID(F22,7,4),MID(F22,4,2),MID(F22,1,2)),"dd/MM/yyyy") -> 01/01/2023 - 31/12/2023
C20: #UNITSCALE# | E20: =StartUp!$E$8 -> MYR'000 | F20: =StartUp!$E$8 -> MYR'000
C21: #STDT# | E21: =StartUp!$D$8 -> 01/01/2024 | F21: =StartUp!$D$10 -> 01/01/2023
C22: #ENDT# | E22: =StartUp!$D$9 -> 31/12/2024 | F22: =StartUp!$D$11 -> 31/12/2023
C23: #TABLE#
A24: ssmt-mfrs-cor_2022-12-31.xsd#ssmt-mfrs_AnalysisOfProfitOrLossAbstract | D24: Analysis of profit or loss
A25: ssmt-mfrs-cor_2022-12-31.xsd#ssmt-mfrs_StatementOfProfitOrLossLineItems | D25: Statement of profit or loss
A26: full_ifrs-cor_2022-03-24.xsd#ifrs-full_RevenueAbstract | D26: Revenue
A27: ssmt-mfrs-cor_2022-12-31.xsd#ssmt-mfrs_RevenueFromSaleOfGoodsAbstract | D27: Revenue from sale of goods
A28: full_ifrs-cor_2022-03-24.xsd#ifrs-full_RevenueFromSaleOfTelecommunicationEquipment@http://xbrl.ssm.com.my/role/ssm/lab_rol_ssmt-fs-mfrs_2022-12-31/ReportingLabel | D28: Revenue from sale of broadband and telecommunication
A29: ssmt-mfrs-cor_2022-12-31.xsd#ssmt-mfrs_RevenueFromSaleOfProperty@http://xbrl.ssm.com.my/role/ssm/lab_rol_ssmt-fs-mfrs_2022-12-31/ReportingLabel | D29: Revenue from property development
A30: ssmt-mfrs-cor_2022-12-31.xsd#ssmt-mfrs_RevenueFromSaleOfConstructionContracts@http://xbrl.ssm.com.my/role/ssm/lab_rol_ssmt-fs-mfrs_2022-12-31/ReportingLabel | D30: Revenue from construction contracts
A31: ssmt-mfrs-cor_2022-12-31.xsd#ssmt-mfrs_RevenueFromSaleOfCleanWaterTreatmentAndDisposalOfWasteWater@http://xbrl.ssm.com.my/role/ssm/lab_rol_ssmt-fs-mfrs_2022-12-31/ReportingLabel | D31: Revenue from clean water, treatment and disposal of waste water
A32: full_ifrs-cor_2022-03-24.xsd#ifrs-full_RevenueFromSaleOfFoodAndBeverage | D32: Revenue from sale of food and beverage
A33: full_ifrs-cor_2022-03-24.xsd#ifrs-full_RevenueFromSaleOfAgriculturalProduce | D33: Revenue from sale of agricultural produce
A34: full_ifrs-cor_2022-03-24.xsd#ifrs-full_RevenueFromSaleOfOilAndGasProducts | D34: Revenue from sale of oil and gas products
A35: ssmt-mfrs-cor_2022-12-31.xsd#ssmt-mfrs_RevenueFromSaleOfOtherGoods | D35: Revenue from sale of other goods
A36: full_ifrs-cor_2022-03-24.xsd#ifrs-full_RevenueFromSaleOfGoods@http://xbrl.ssm.com.my/role/ssm/fs/mfrs/lab_rol_ssmt-fs-mfrs_2022-12-31/ReportingTotalLabel | D36: Total revenue from sale of goods | E36: =1*E28+1*E29+1*E30+1*E31+1*E32+1*E33+1*E34+1*E35 -> 0 | F36: =1*F28+1*F29+1*F30+1*F31+1*F32+1*F33+1*F34+1*F35 -> 0
A37: ssmt-mfrs-cor_2022-12-31.xsd#ssmt-mfrs_RevenueFromRenderingOfServicesAbstract | D37: Revenue from rendering of services
A38: ssmt-mfrs-cor_2022-12-31.xsd#ssmt-mfrs_RevenueFromEntertainmentOperations | D38: Revenue from rendering of entertainment services
A39: full_ifrs-cor_2022-03-24.xsd#ifrs-full_RevenueFromRenderingOfTelecommunicationServices | D39: Revenue from rendering of telecommunication services
A40: full_ifrs-cor_2022-03-24.xsd#ifrs-full_RevenueFromRenderingOfTransportServices | D40: Revenue from rendering of transport services
A41: full_ifrs-cor_2022-03-24.xsd#ifrs-full_RevenueFromRenderingOfInformationTechnologyServices | D41: Revenue from rendering of information technology services
A42: ssmt-mfrs-cor_2022-12-31.xsd#ssmt-mfrs_RevenueFromEducationalServices | D42: Revenue from rendering of educational services
A43: ssmt-mfrs-cor_2022-12-31.xsd#ssmt-mfrs_RevenueFromHealthcareServices | D43: Revenue from rendering of healthcare services
A44: full_ifrs-cor_2022-03-24.xsd#ifrs-full_RevenueFromRenderingOfCargoAndMailTransportServices@http://xbrl.ssm.com.my/role/ssm/lab_rol_ssmt-fs-mfrs_2022-12-31/ReportingLabel | D44: Revenue from rendering of shipping and shipping related services
A45: ssmt-mfrs-cor_2022-12-31.xsd#ssmt-mfrs_RevenueFromRenderingOfOtherServices | D45: Revenue from rendering of other services
A46: full_ifrs-cor_2022-03-24.xsd#ifrs-full_RevenueFromRenderingOfServices@http://xbrl.ssm.com.my/role/ssm/fs/mfrs/lab_rol_ssmt-fs-mfrs_2022-12-31/ReportingTotalLabel | D46: Total revenue from rendering of services | E46: =1*E38+1*E39+1*E40+1*E41+1*E42+1*E43+1*E44+1*E45 -> 0 | F46: =1*F38+1*F39+1*F40+1*F41+1*F42+1*F43+1*F44+1*F45 -> 0
A47: ssmt-mfrs-cor_2022-12-31.xsd#ssmt-mfrs_InterestIncomeAbstract | D47: Interest income
A48: full_ifrs-cor_2022-03-24.xsd#ifrs-full_InterestIncomeOnLoansAndReceivables@http://xbrl.ssm.com.my/role/ssm/lab_rol_ssmt-fs-mfrs_2022-12-31/ReportingLabel | D48: Interest income on loans, advances and financing
A49: full_ifrs-cor_2022-03-24.xsd#ifrs-full_InterestIncomeOnOtherFinancialAssets | D49: Interest income on other financial assets
A50: full_ifrs-cor_2022-03-24.xsd#ifrs-full_RevenueFromInterest@http://xbrl.ssm.com.my/role/ssm/fs/mfrs/lab_rol_ssmt-fs-mfrs_2022-12-31/ReportingTotalLabel | D50: Total interest income | E50: =1*E48+1*E49 -> 0 | F50: =1*F48+1*F49 -> 0
A51: full_ifrs-cor_2022-03-24.xsd#ifrs-full_FeeAndCommissionIncomeAbstract@http://xbrl.ssm.com.my/role/ssm/lab_rol_ssmt-fs-mfrs_2022-12-31/ReportingLabel | D51: Other fee and commission income
A52: full_ifrs-cor_2022-03-24.xsd#ifrs-full_BrokerageFeeIncome@http://xbrl.ssm.com.my/role/ssm/lab_rol_ssmt-fs-mfrs_2022-12-31/ReportingLabel | D52: Gross brokerage and other charges
A53: full_ifrs-cor_2022-03-24.xsd#ifrs-full_PortfolioAndOtherManagementFeeIncome@http://xbrl.ssm.com.my/role/ssm/lab_rol_ssmt-fs-mfrs_2022-12-31/ReportingLabel | D53: Underwriting commissions and fund management income
A54: full_ifrs-cor_2022-03-24.xsd#ifrs-full_OtherFeeAndCommissionIncome | D54: Other fee and commission income
A55: full_ifrs-cor_2022-03-24.xsd#ifrs-full_FeeAndCommissionIncome@http://xbrl.ssm.com.my/role/ssm/fs/mfrs/lab_rol_ssmt-fs-mfrs_2022-12-31/ReportingTotalLabel | D55: Total other fee and commission income | E55: =1*E52+1*E53+1*E54 -> 0 | F55: =1*F52+1*F53+1*F54 -> 0
A56: full_ifrs-cor_2022-03-24.xsd#ifrs-full_RevenueFromDividends | D56: Dividend income
A57: full_ifrs-cor_2022-03-24.xsd#ifrs-full_RentalIncome | D57: Rental income
A58: full_ifrs-cor_2022-03-24.xsd#ifrs-full_RevenueFromRoyalties | D58: Royalty income
A59: full_ifrs-cor_2022-03-24.xsd#ifrs-full_OtherRevenue | D59: Other revenue
A60: full_ifrs-cor_2022-03-24.xsd#ifrs-full_Revenue@http://www.xbrl.org/2003/role/totalLabel | D60: *Total revenue | E60: =1*E36+1*E46+1*E50+1*E55+1*E56+1*E57+1*E58+1*E59 -> 0 | F60: =1*F36+1*F46+1*F50+1*F55+1*F56+1*F57+1*F58+1*F59 -> 0 | G60: See details
A61: ssmt-mfrs-cor_2022-12-31.xsd#ssmt-mfrs_CostOfSalesAbstract | D61: Cost of sales
A62: ssmt-mfrs-cor_2022-12-31.xsd#ssmt-mfrs_CostOfInventories | D62: Cost of inventories
A63: ssmt-mfrs-cor_2022-12-31.xsd#ssmt-mfrs_ConstructionContractCost | D63: Construction contract costs
A64: full_ifrs-cor_2022-03-24.xsd#ifrs-full_EnergyExpense@http://xbrl.ssm.com.my/role/ssm/lab_rol_ssmt-fs-mfrs_2022-12-31/ReportingLabel | D64: Energy costs
A65: full_ifrs-cor_2022-03-24.xsd#ifrs-full_PropertyDevelopmentAndProjectManagementExpense@http://xbrl.ssm.com.my/role/ssm/lab_rol_ssmt-fs-mfrs_2022-12-31/ReportingLabel | D65: Property development costs
A66: ssmt-mfrs-cor_2022-12-31.xsd#ssmt-mfrs_OtherCostOfSales | D66: Other cost of sales
A67: full_ifrs-cor_2022-03-24.xsd#ifrs-full_CostOfSales@http://xbrl.ssm.com.my/role/ssm/fs/mfrs/lab_rol_ssmt-fs-mfrs_2022-12-31/ReportingTotalLabel | D67: *Total cost of sales | E67: =1*E62+1*E63+1*E64+1*E65+1*E66 -> 0 | F67: =1*F62+1*F63+1*F64+1*F65+1*F66 -> 0 | G67: See details
A68: ssmt-mfrs-cor_2022-12-31.xsd#ssmt-mfrs_OtherIncomeAbstract | D68: Other income
A69: ssmt-mfrs-cor_2022-12-31.xsd#ssmt-mfrs_AmortisationOfDeferredIncome | D69: Deferred income
A70: ssmt-mfrs-cor_2022-12-31.xsd#ssmt-mfrs_BadDebtsRecovered | D70: Bad debts recovered
A71: ssmt-mfrs-cor_2022-12-31.xsd#ssmt-mfrs_OtherIncomeDividend@http://xbrl.ssm.com.my/role/ssm/lab_rol_ssmt-fs-mfrs_2022-12-31/ReportingLabel | D71: Dividend income
A72: ssmt-mfrs-cor_2022-12-31.xsd#ssmt-mfrs_OtherIncomeRoyaltyAndFranchise@http://xbrl.ssm.com.my/role/ssm/lab_rol_ssmt-fs-mfrs_2022-12-31/ReportingLabel | D72: Royalty/franchise income
A73: ssmt-mfrs-cor_2022-12-31.xsd#ssmt-mfrs_WriteBackOfFuelCost | D73: Write back of fuel cost
A74: full_ifrs-cor_2022-03-24.xsd#ifrs-full_IncomeFromReimbursementsUnderInsurancePolicies | D74: Income from reimbursements under insurance policies
A75: ssmt-mfrs-cor_2022-12-31.xsd#ssmt-mfrs_GrantsOrIncentivesReceivedByMalaysianGovernmentOrAgencies | D75: Grant or incentives by Malaysian government or it's agencies
A76: ssmt-mfrs-cor_2022-12-31.xsd#ssmt-mfrs_GrantsOrIncentivesReceivedByForeignGovernmentOrAgencies | D76: Grant or incentives by foreign government or it's agencies
A77: ssmt-mfrs-cor_2022-12-31.xsd#ssmt-mfrs_ContributionsReceivedByLocalContributor@http://xbrl.ssm.com.my/role/ssm/lab_rol_ssmt-fs-mfrs_2022-12-31/ReportingLabel | D77: Contributions or donations by local contributor
A78: ssmt-mfrs-cor_2022-12-31.xsd#ssmt-mfrs_ContributionsReceivedByForeignContributor@http://xbrl.ssm.com.my/role/ssm/lab_rol_ssmt-fs-mfrs_2022-12-31/ReportingLabel | D78: Contributions or donations by foreign contributor
A79: ssmt-mfrs-cor_2022-12-31.xsd#ssmt-mfrs_ContributionsReceivedByUnknownContributor@http://xbrl.ssm.com.my/role/ssm/lab_rol_ssmt-fs-mfrs_2022-12-31/ReportingLabel | D79: Contributions or donations by unknown contributor
... A82: ssmt-mfrs-cor_2022-12-31.xsd#ssmt-mfrs_UnrealisedGainOnForeignExchange | D82: Unrealised gain on foreign exchange
A83: ssmt-mfrs-cor_2022-12-31.xsd#ssmt-mfrs_GainsOnForeignExchange@http://xbrl.ssm.com.my/role/ssm/fs/mfrs/lab_rol_ssmt-fs-mfrs_2022-12-31/ReportingTotalLabel | D83: Total foreign exchange gain | E83: =1*E81+1*E82 -> 0 | F83: =1*F81+1*F82 -> 0
A84: ssmt-mfrs-cor_2022-12-31.xsd#ssmt-mfrs_GainsOnDisposalOfSubsidiariesAssociatesAndJointVenturesAbstract | D84: Gain on disposal of subsidiaries, associates and joint ventures
A85: ssmt-mfrs-cor_2022-12-31.xsd#ssmt-mfrs_GainsFromDisposalOfSubsidiaries | D85: Gain on disposal of subsidiaries
A86: ssmt-mfrs-cor_2022-12-31.xsd#ssmt-mfrs_GainsFromDisposalOfAssociates | D86: Gain on disposal of associates
A87: ssmt-mfrs-cor_2022-12-31.xsd#ssmt-mfrs_GainsFromDisposalOfJointVentures | D87: Gain on disposal of joint ventures
A88: ssmt-mfrs-cor_2022-12-31.xsd#ssmt-mfrs_GainsOnDisposalOfSubsidiaryJointVenturesAndAssociates@http://xbrl.ssm.com.my/role/ssm/fs/mfrs/lab_rol_ssmt-fs-mfrs_2022-12-31/ReportingTotalLabel | D88: Total gain on disposal of subsidiaries, associates and joint ventures | E88: =1*E85+1*E86+1*E87 -> 0 | F88: =1*F85+1*F86+1*F87 -> 0
A89: ssmt-mfrs-cor_2022-12-31.xsd#ssmt-mfrs_GainsOnDisposalOfOtherInvestments | D89: Gain on disposal from other investments
A90: full_ifrs-cor_2022-03-24.xsd#ifrs-full_GainsOnDisposalsOfPropertyPlantAndEquipment | D90: Gains on disposals of property, plant and equipment
A91: full_ifrs-cor_2022-03-24.xsd#ifrs-full_GainsOnDisposalsOfNoncurrentAssets@http://xbrl.ssm.com.my/role/ssm/lab_rol_ssmt-fs-mfrs_2022-12-31/ReportingLabel | D91: Gains on disposals of other non-current assets
A92: ssmt-mfrs-cor_2022-12-31.xsd#ssmt-mfrs_OtherGainsRecognisedInProfitOrLossFairValueMeasurementAssets | D92: Other gains recognised in profit or loss, fair value measurement, assets
A93: ssmt-mfrs-cor_2022-12-31.xsd#ssmt-mfrs_ReversalOfImpairmentLossRecognisedInProfirOrLossAbstract | D93: Reversal of impairment loss recognised in profit or loss
A94: full_ifrs-cor_2022-03-24.xsd#ifrs-full_ReversalOfImpairmentLossRecognisedInProfitOrLossLoansAndAdvances@http://xbrl.ssm.com.my/role/ssm/lab_rol_ssmt-fs-mfrs_2022-12-31/ReportingLabel | D94: Reversal of impairment loss on receivables
A95: full_ifrs-cor_2022-03-24.xsd#ifrs-full_ReversalOfImpairmentLossRecognisedInProfitOrLossInvestmentProperty@http://xbrl.ssm.com.my/role/ssm/lab_rol_ssmt-fs-mfrs_2022-12-31/ReportingLabel | D95: Reversal of impairment in development expenditure
A96: ssmt-mfrs-cor_2022-12-31.xsd#ssmt-mfrs_ReversalOfImpairmentLossInLandHeldForDevelopment@http://xbrl.ssm.com.my/role/ssm/lab_rol_ssmt-fs-mfrs_2022-12-31/ReportingLabel | D96: Reversal of impairment in land held for property development
A97: full_ifrs-cor_2022-03-24.xsd#ifrs-full_ReversalOfImpairmentLossRecognisedInProfitOrLossPropertyPlantAndEquipment@http://xbrl.ssm.com.my/role/ssm/lab_rol_ssmt-fs-mfrs_2022-12-31/ReportingLabel | D97: Reversal of impairment in property, plant and equipment
A98: ssmt-mfrs-cor_2022-12-31.xsd#ssmt-mfrs_ReversalOfImpairmentLossForOtherAssets | D98: Reversal of impairment in other assets
A99: full_ifrs-cor_2022-03-24.xsd#ifrs-full_ReversalOfImpairmentLossRecognisedInProfitOrLoss@http://xbrl.ssm.com.my/role/ssm/fs/mfrs/lab_rol_ssmt-fs-mfrs_2022-12-31/ReportingTotalLabel | D99: Total reversal of impairment loss recognised in profit or loss | E99: =1*E94+1*E95+1*E96+1*E97+1*E98 -> 0 | F99: =1*F94+1*F95+1*F96+1*F97+1*F98 -> 0
A100: full_ifrs-cor_2022-03-24.xsd#ifrs-full_ReversalOfInventoryWritedown@http://xbrl.ssm.com.my/role/ssm/lab_rol_ssmt-fs-mfrs_2022-12-31/ReportingLabel | D100: Reversal of inventories written down to net realisable value
A101: ssmt-mfrs-cor_2022-12-31.xsd#ssmt-mfrs_OtherInterestIncome@http://xbrl.ssm.com.my/role/ssm/lab_rol_ssmt-fs-mfrs_2022-12-31/ReportingLabel | D101: Interest income
A102: ssmt-mfrs-cor_2022-12-31.xsd#ssmt-mfrs_IncomeFromManagementFees@http://xbrl.ssm.com.my/role/ssm/lab_rol_ssmt-fs-mfrs_2022-12-31/ReportingLabel | D102: Management fees
A103: ssmt-mfrs-cor_2022-12-31.xsd#ssmt-mfrs_NetDepositsRecognised | D103: Net deposits recognised
A104: full_ifrs-cor_2022-03-24.xsd#ifrs-full_GainsOnChangeInFairValueOfDerivatives@http://xbrl.ssm.com.my/role/ssm/lab_rol_ssmt-fs-mfrs_2022-12-31/ReportingLabel | D104: Net fair value gain on derivatives
A105: ssmt-mfrs-cor_2022-12-31.xsd#ssmt-mfrs_FairValueGainOnRecycleOfForexReserveUponDisposalOfSubsdiaries@http://xbrl.ssm.com.my/role/ssm/lab_rol_ssmt-fs-mfrs_2022-12-31/ReportingLabel | D105: Net fair value gain on recycle of forex reserve upon disposal of subsidiaries
A106: ssmt-mfrs-cor_2022-12-31.xsd#ssmt-mfrs_OtherFeesAndCommissionIncome@http://xbrl.ssm.com.my/role/ssm/lab_rol_ssmt-fs-mfrs_2022-12-31/ReportingLabel | D106: Other fee and commission
A107: ssmt-mfrs-cor_2022-12-31.xsd#ssmt-mfrs_OtherRentalIncome@http://xbrl.ssm.com.my/role/ssm/lab_rol_ssmt-fs-mfrs_2022-12-31/ReportingLabel | D107: Other rental income
A108: ssmt-mfrs-cor_2022-12-31.xsd#ssmt-mfrs_OtherRentalIncomeOnLandAndBuildings@http://xbrl.ssm.com.my/role/ssm/lab_rol_ssmt-fs-mfrs_2022-12-31/ReportingLabel | D108: Rental income on land and buildings
A109: full_ifrs-cor_2022-03-24.xsd#ifrs-full_MiscellaneousOtherOperatingIncome@http://xbrl.ssm.com.my/role/ssm/lab_rol_ssmt-fs-mfrs_2022-12-31/ReportingLabel | D109: Other miscellaneous income
...

Sheet SOCI-BeforeOfTax
A1: 05e58da4-b2cb-4591-bf01-0861836ec42b:~:AtleastOneValueInAnyLayout:~:True:~:<?xml version="1.0" encoding="utf-16"?>_x000D_ <Customization xmlns:xsi="http://www.w3.org/2001/XMLSchema-instance" xmlns:xsd="http://www.w3.org/2001/XMLSchema" ComparitiveDate="False" LayoutByDate="False" LayoutByCompany="False" ShowAllDomains="False" TotalDomain="True" DefaultDates="2" />:~:http://xbrl.ssm.com.my/role/ssm/rol_ssmt-fs-mfrs_2022-12-31/ssmt-fs-mfrs_2022-12-31_role-400100y:~:None
D2: FS-MFRS Statement of Comprehensive Income - Before tax
D3: * denotes mandatory items to be reported
C5: 18ef8105-8057-4eb5-a37a-ad215e96da10:~:SOCI-BeforeOfTax_1_TBLYT:~:NotMandatory:~:False:~:0:~:True:~:<?xml version="1.0" encoding="utf-16"?>_x000D_ <Customization xmlns:xsi="http://www.w3.org/2001/XMLSchema-instance" xmlns:xsd="http://www.w3.org/2001/XMLSchema" ComparitiveDate="False" LayoutByDate="False" LayoutByCompany="False" ShowAllDomains="False" TotalDomain="True" DefaultDates="2" />:~:LytTxb:~::~:False:~:True:~:ssmt-mfrs-cor_2022-12-31.xsd#ssmt-mfrs_DisclosureOnStatementOfComprehensiveIncomeBeforeTax@http://www.xbrl.org/2003/role/label:~:
C8: #LAYOUTSCSR# | D8: #PRIM# | F8: #TABLE# | G8: #LAYOUTECSR#
C9: #TABLE#
A10: ssmt-mfrs-cor_2022-12-31.xsd#ssmt-mfrs_DisclosureOnStatementOfComprehensiveIncomeBeforeTax | D10: Disclosure on statement of comprehensive income before tax
C11: #TABLE#
C12: #LAYOUTSCER# | G12: #LAYOUTECER#
C15: da0d7a1d-4bd5-43cd-89a2-c3f3133344fa:~:SOCI-BeforeOfTax_2:~:NotMandatory:~:True:~:1:~:True:~:<?xml version="1.0" encoding="utf-16"?>_x000D_ <Customization xmlns:xsi="http://www.w3.org/2001/XMLSchema-instance" xmlns:xsd="http://www.w3.org/2001/XMLSchema" ComparitiveDate="False" LayoutByDate="False" LayoutByCompany="False" ShowAllDomains="False" TotalDomain="True" DefaultDates="2" />:~:LytHyc:~:ssmt-mfrs-cor_2022-12-31.xsd#ssmt-mfrs_StatementOfComprehensiveIncomeBeforeTaxTable:~:False:~:True:~:ssmt-mfrs-cor_2022-12-31.xsd#ssmt-mfrs_DisclosureOnStatementOfComprehensiveIncomeBeforeTax@http://www.xbrl.org/2003/role/label::ssmt-mfrs-cor_2022-12-31.xsd#ssmt-mfrs_ComprehensiveIncomeBeforeTaxAbstract@http://www.xbrl.org/2003/role/label::ssmt-mfrs-cor_2022-12-31.xsd#ssmt-mfrs_StatementOfComprehensiveIncomeBeforeTaxLineItems@http://www.xbrl.org/2003/role/label:~:ssmt-mfrs-cor_2022-12-31.xsd#ssmt-mfrs_StatementOfComprehensiveIncomeBeforeTaxTable
C18: #LAYOUTSCSR# | D18: #PRIM# | G18: #TABLE# | H18: #LAYOUTECSR#
C19: #STDTENDTDATE# | E19: =TEXT(DATE(MID(E21,7,4),MID(E21,4,2),MID(E21,1,2)),"dd/MM/yyyy")&" - "&TEXT(DATE(MID(E22,7,4),MID(E22,4,2),MID(E22,1,2)),"dd/MM/yyyy") -> 01/01/2024 - 31/12/2024 | F19: =TEXT(DATE(MID(F21,7,4),MID(F21,4,2),MID(F21,1,2)),"dd/MM/yyyy")&" - "&TEXT(DATE(MID(F22,7,4),MID(F22,4,2),MID(F22,1,2)),"dd/MM/yyyy") -> 01/01/2023 - 31/12/2023
C20: #UNITSCALE# | E20: =StartUp!$E$8 -> MYR'000 | F20: =StartUp!$E$8 -> MYR'000
C21: #STDT# | E21: =StartUp!$D$8 -> 01/01/2024 | F21: =StartUp!$D$10 -> 01/01/2023
C22: #ENDT# | E22: =StartUp!$D$9 -> 31/12/2024 | F22: =StartUp!$D$11 -> 31/12/2023
C23: #TABLE#
A24: ssmt-mfrs-cor_2022-12-31.xsd#ssmt-mfrs_ComprehensiveIncomeBeforeTaxAbstract | D24: Comprehensive income before tax
A25: ssmt-mfrs-cor_2022-12-31.xsd#ssmt-mfrs_StatementOfComprehensiveIncomeBeforeTaxLineItems | D25: Statement of comprehensive income before tax
A26: full_ifrs-cor_2022-03-24.xsd#ifrs-full_StatementOfComprehensiveIncomeAbstract | D26: Statement of comprehensive income
A27: full_ifrs-cor_2022-03-24.xsd#ifrs-full_ProfitLoss | D27: *Profit (loss) | E27: ='SOPL-Function'!E46 -> 0 | F27: ='SOPL-Function'!F46 -> 0 | G27: See details
A28: full_ifrs-cor_2022-03-24.xsd#ifrs-full_OtherComprehensiveIncomeAbstract@http://www.xbrl.org/2003/role/terseLabel | D28: Other comprehensive income/(loss), before tax
A29: full_ifrs-cor_2022-03-24.xsd#ifrs-full_ComponentsOfOtherComprehensiveIncomeThatWillNotBeReclassifiedToProfitOrLossBeforeTaxAbstract | D29: Components of other comprehensive income that will not be reclassified to profit or loss, before tax
A30: full_ifrs-cor_2022-03-24.xsd#ifrs-full_OtherComprehensiveIncomeBeforeTaxGainsLossesOnRevaluation@http://xbrl.ssm.com.my/role/ssm/lab_rol_ssmt-fs-mfrs_2022-12-31/ReportingLabel | D30: Other comprehensive income, before tax, gains (losses) on revaluation of property, plant and equipment, right-of-use assets and intangible assets
A31: full_ifrs-cor_2022-03-24.xsd#ifrs-full_OtherComprehensiveIncomeBeforeTaxGainsLossesOnRemeasurementsOfDefinedBenefitPlans@http://xbrl.ssm.com.my/role/ssm/lab_rol_ssmt-fs-mfrs_2022-12-31/ReportingLabel | D31: Remeasurement of defined benefit liability
A32: ssmt-mfrs-cor_2022-12-31.xsd#ssmt-mfrs_OtherComprehensiveIncomeBeforeTaxGainsLossesOnOtherItems | D32: Other comprehensive income, before tax, gains (losses) on other items | E32: =1*E30+1*E31 -> 0 | F32: =1*F30+1*F31 -> 0
A33: full_ifrs-cor_2022-03-24.xsd#ifrs-full_ShareOfOtherComprehensiveIncomeOfAssociatesAndJointVenturesAccountedForUsingEquityMethodThatWillNotBeReclassifiedToProfitOrLossBeforeTax | D33: Share of other comprehensive income of associates and joint ventures accounted for using equity method that will not be reclassified to profit or loss, before tax
A34: full_ifrs-cor_2022-03-24.xsd#ifrs-full_OtherComprehensiveIncomeThatWillNotBeReclassifiedToProfitOrLossBeforeTax@http://www.xbrl.org/2003/role/totalLabel | D34: Total other comprehensive income that will not be reclassified to profit or loss, before tax | E34: =1*E32+1*E33 -> 0 | F34: =1*F32+1*F33 -> 0
A35: full_ifrs-cor_2022-03-24.xsd#ifrs-full_ComponentsOfOtherComprehensiveIncomeThatWillBeReclassifiedToProfitOrLossBeforeTaxAbstract | D35: Components of other comprehensive income that will be reclassified to profit or loss, before tax
A36: full_ifrs-cor_2022-03-24.xsd#ifrs-full_ExchangeDifferencesOnTranslationAbstract | D36: Exchange differences on translation
A37: full_ifrs-cor_2022-03-24.xsd#ifrs-full_GainsLossesOnExchangeDifferencesOnTranslationBeforeTax@http://xbrl.ssm.com.my/role/ssm/lab_rol_ssmt-fs-mfrs_2022-12-31/ReportingLabel | D37: Gains (losses) on exchange differences on translation, before tax
A38: full_ifrs-cor_2022-03-24.xsd#ifrs-full_ReclassificationAdjustmentsOnExchangeDifferencesOnTranslationBeforeTax@http://xbrl.ssm.com.my/role/ssm/lab_rol_ssmt-fs-mfrs_2022-12-31/ReportingNegatedLabel | D38: Reclassification adjustments on exchange differences on translation, before tax
A39: full_ifrs-cor_2022-03-24.xsd#ifrs-full_OtherComprehensiveIncomeBeforeTaxExchangeDifferencesOnTranslation@http://xbrl.ssm.com.my/role/ssm/fs/mfrs/lab_rol_ssmt-fs-mfrs_2022-12-31/ReportingTotalLabel | D39: Other comprehensive income, before tax, exchange differences on translation | E39: =1*E37+-1*E38 -> 0 | F39: =1*F37+-1*F38 -> 0
A40: full_ifrs-cor_2022-03-24.xsd#ifrs-full_CashFlowHedgesAbstract | D40: Cash flow hedges
A41: full_ifrs-cor_2022-03-24.xsd#ifrs-full_GainsLossesOnCashFlowHedgesBeforeTax | D41: Gains (losses) on cash flow hedges, before tax
A42: full_ifrs-cor_2022-03-24.xsd#ifrs-full_ReclassificationAdjustmentsOnCashFlowHedgesBeforeTax@http://www.xbrl.org/2009/role/negatedLabel | D42: Reclassification adjustments on cash flow hedges, before tax
A43: full_ifrs-cor_2022-03-24.xsd#ifrs-full_OtherComprehensiveIncomeBeforeTaxCashFlowHedges@http://www.xbrl.org/2003/role/totalLabel | D43: Other comprehensive income, before tax, cash flow hedges | E43: =1*E41+-1*E42 -> 0 | F43: =1*F41+-1*F42 -> 0
A44: full_ifrs-cor_2022-03-24.xsd#ifrs-full_HedgesOfNetInvestmentsInForeignOperationsAbstract | D44: Hedges of net investment in foreign operations
A45: full_ifrs-cor_2022-03-24.xsd#ifrs-full_GainsLossesOnHedgesOfNetInvestmentsInForeignOperationsBeforeTax | D45: Gains (losses) on hedges of net investments in foreign operations, before tax
A46: full_ifrs-cor_2022-03-24.xsd#ifrs-full_ReclassificationAdjustmentsOnHedgesOfNetInvestmentsInForeignOperationsBeforeTax@http://www.xbrl.org/2009/role/negatedLabel | D46: Reclassification adjustments on hedges of net investments in foreign operations, before tax
A47: full_ifrs-cor_2022-03-24.xsd#ifrs-full_OtherComprehensiveIncomeBeforeTaxHedgesOfNetInvestmentsInForeignOperations@http://www.xbrl.org/2003/role/totalLabel | D47: Other comprehensive income, before tax, hedges of net investments in foreign operations | E47: =1*E45+-1*E46 -> 0 | F47: =1*F45+-1*F46 -> 0
A48: full_ifrs-cor_2022-03-24.xsd#ifrs-full_FinancialAssetsMeasuredAtFairValueThroughOtherComprehensiveIncomeAbstract | D48: Financial assets measured at fair value through other comprehensive income
A49: full_ifrs-cor_2022-03-24.xsd#ifrs-full_GainsLossesOnFinancialAssetsMeasuredAtFairValueThroughOtherComprehensiveIncomeBeforeTax | D49: Gains (losses) on financial assets measured at fair value through other comprehensive income, before tax
A50: full_ifrs-cor_2022-03-24.xsd#ifrs-full_ReclassificationAdjustmentsOnFinancialAssetsMeasuredAtFairValueThroughOtherComprehensiveIncomeBeforeTax@http://www.xbrl.org/2009/role/negatedLabel | D50: Reclassification adjustments on financial assets measured at fair value through other comprehensive income, before tax
A51: full_ifrs-cor_2022-03-24.xsd#ifrs-full_AmountsRemovedFromEquityAndAdjustedAgainstFairValueOfFinancialAssetsOnReclassificationOutOfFairValueThroughOtherComprehensiveIncomeMeasurementCategoryBeforeTax@http://www.xbrl.org/2009/role/negatedLabel | D51: Amounts removed from equity and adjusted against fair value of financial assets on reclassification out of fair value through other comprehensive income measurement category, before tax
A52: full_ifrs-cor_2022-03-24.xsd#ifrs-full_OtherComprehensiveIncomeBeforeTaxFinancialAssetsMeasuredAtFairValueThroughOtherComprehensiveIncome@http://www.xbrl.org/2003/role/totalLabel | D52: Other comprehensive income, before tax, financial assets measured at fair value through other comprehensive income | E52: =1*E49+-1*E50+-1*E51 -> 0 | F52: =1*F49+-1*F50+-1*F51 -> 0
A53: full_ifrs-cor_2022-03-24.xsd#ifrs-full_ShareOfOtherComprehensiveIncomeOfAssociatesAndJointVenturesAccountedForUsingEquityMethodThatWillBeReclassifiedToProfitOrLossBeforeTax | D53: Share of other comprehensive income of associates and joint ventures accounted for using equity method that will be reclassified to profit or loss, before tax
A54: ssmt-mfrs-cor_2022-12-31.xsd#ssmt-mfrs_OtherComprehensiveIncomeBeforeTaxGainsLossesOnOtherItemsThatWillBeReclassifiedToProfitOrLoss | D54: Other comprehensive income, before tax, gains (losses) on other items
A55: full_ifrs-cor_2022-03-24.xsd#ifrs-full_OtherComprehensiveIncomeThatWillBeReclassifiedToProfitOrLossBeforeTax@http://www.xbrl.org/2003/role/totalLabel | D55: Total other comprehensive income that will be reclassified to profit or loss, before tax | E55: =1*E39+1*E43+1*E47+1*E52+1*E53+1*E54 -> 0 | F55: =1*F39+1*F43+1*F47+1*F52+1*F53+1*F54 -> 0
A56: full_ifrs-cor_2022-03-24.xsd#ifrs-full_OtherComprehensiveIncomeBeforeTax@http://www.xbrl.org/2003/role/totalLabel | D56: Total other comprehensive income, before tax | E56: =1*E34+1*E55 -> 0 | F56: =1*F34+1*F55 -> 0
A57: full_ifrs-cor_2022-03-24.xsd#ifrs-full_IncomeTaxRelatingToComponentsOfOtherComprehensiveIncomeThatWillNotBeReclassifiedToProfitOrLossAbstract | D57: Income tax relating to components of other comprehensive income that will not be reclassified to profit or loss
A58: full_ifrs-cor_2022-03-24.xsd#ifrs-full_IncomeTaxRelatingToRemeasurementsOfDefinedBenefitPlansOfOtherComprehensiveIncome@http://xbrl.ssm.com.my/role/ssm/lab_rol_ssmt-fs-mfrs_2022-12-31/ReportingNegatedLabel | D58: Income tax relating to remeasurements of defined benefit plans of other comprehensive income
A59: full_ifrs-cor_2022-03-24.xsd#ifrs-full_IncomeTaxRelatingToComponentsOfOtherComprehensiveIncomeThatWillNotBeReclassifiedToProfitOrLoss@http://www.xbrl.org/2009/role/negatedTotalLabel | D59: Aggregated income tax relating to components of other comprehensive income that will not be reclassified to profit or loss | E59: =1*E58 -> 0 | F59: =1*F58 -> 0
A60: full_ifrs-cor_2022-03-24.xsd#ifrs-full_IncomeTaxRelatingToComponentsOfOtherComprehensiveIncomeThatWillBeReclassifiedToProfitOrLossAbstract | D60: Income tax relating to components of other comprehensive income that will be reclassified to profit or loss
A61: full_ifrs-cor_2022-03-24.xsd#ifrs-full_IncomeTaxRelatingToComponentsOfOtherComprehensiveIncomeThatWillBeReclassifiedToProfitOrLoss@http://www.xbrl.org/2009/role/negatedTotalLabel | D61: Aggregated income tax relating to components of other comprehensive income that will be reclassified to profit or loss
A62: full_ifrs-cor_2022-03-24.xsd#ifrs-full_OtherComprehensiveIncome@http://www.xbrl.org/2003/role/totalLabel | D62: *Total other comprehensive income | E62: =1*E56+-1*E59+-1*E61 -> 0 | F62: =1*F56+-1*F59+-1*F61 -> 0
A63: full_ifrs-cor_2022-03-24.xsd#ifrs-full_ComprehensiveIncome@http://www.xbrl.org/2003/role/totalLabel | D63: *Total comprehensive income | E63: =1*E27+1*E62 -> 0 | F63: =1*F27+1*F62 -> 0
A64: full_ifrs-cor_2022-03-24.xsd#ifrs-full_ComprehensiveIncomeAttributableToAbstract | D64: Comprehensive income attributable to
A65: full_ifrs-cor_2022-03-24.xsd#ifrs-full_ComprehensiveIncomeAttributableToOwnersOfParent | D65: Comprehensive income, attributable to owners of parent
A66: full_ifrs-cor_2022-03-24.xsd#ifrs-full_ComprehensiveIncomeAttributableToNoncontrollingInterests | D66: Comprehensive income, attributable to non-controlling interests
A67: full_ifrs-cor_2022-03-24.xsd#ifrs-full_ComprehensiveIncome@http://www.xbrl.org/2003/role/totalLabel | D67: *Total comprehensive income | E67: =1*E65+1*E66 -> 0 | F67: =1*F65+1*F66 -> 0
C68: #TABLE#
C69: #LAYOUTSCER# | H69: #LAYOUTECER#

Sheet SOCF-Indirect
A1: 503e3356-225d-43e6-92c9-f28e35509980:~:AtleastOneValueInAnyLayout:~:True:~:<?xml version="1.0" encoding="utf-16"?>_x000D_ <Customization xmlns:xsi="http://www.w3.org/2001/XMLSchema-instance" xmlns:xsd="http://www.w3.org/2001/XMLSchema" ComparitiveDate="False" LayoutByDate="False" LayoutByCompany="False" ShowAllDomains="False" TotalDomain="True" DefaultDates="2" />:~:http://xbrl.ssm.com.my/role/ssm/rol_ssmt-fs-mfrs_2022-12-31/ssmt-fs-mfrs_2022-12-31_role-500100y:~:None
D2: FS-MFRS Statement of cash flows, indirect method
D3: * denotes mandatory items to be reported
C5: e7c7c1ba-63eb-4a98-8169-a1143a6d3bfd:~:SOCF-Indirect_1_TBLYT:~:NotMandatory:~:False:~:0:~:True:~:<?xml version="1.0" encoding="utf-16"?>_x000D_ <Customization xmlns:xsi="http://www.w3.org/2001/XMLSchema-instance" xmlns:xsd="http://www.w3.org/2001/XMLSchema" ComparitiveDate="False" LayoutByDate="False" LayoutByCompany="False" ShowAllDomains="False" TotalDomain="True" DefaultDates="2" />:~:LytTxb:~::~:False:~:True:~:ssmt-cor_2022-12-31.xsd#ssmt_DisclosureOnStatementOfCashFlowsAbstract@http://www.xbrl.org/2003/role/label:~:
C8: #LAYOUTSCSR# | D8: #PRIM# | F8: #TABLE# | G8: #LAYOUTECSR#
C9: #TABLE#
A10: ssmt-cor_2022-12-31.xsd#ssmt_DisclosureOnStatementOfCashFlowsAbstract | D10: Disclosure on statement of cash flows
C11: #TABLE#
C12: #LAYOUTSCER# | G12: #LAYOUTECER#
C15: 584d4821-1dc9-4561-a354-286c7cf4df43:~:SOCF-Indirect_2:~:NotMandatory:~:True:~:1:~:True:~:<?xml version="1.0" encoding="utf-16"?>_x000D_ <Customization xmlns:xsi="http://www.w3.org/2001/XMLSchema-instance" xmlns:xsd="http://www.w3.org/2001/XMLSchema" ComparitiveDate="False" LayoutByDate="False" LayoutByCompany="False" ShowAllDomains="False" TotalDomain="True" DefaultDates="2" />:~:LytHyc:~:ssmt-cor_2022-12-31.xsd#ssmt_StatementOfCashFlowsTable:~:False:~:True:~:ssmt-cor_2022-12-31.xsd#ssmt_DisclosureOnStatementOfCashFlowsAbstract@http://www.xbrl.org/2003/role/label::full_ifrs-cor_2022-03-24.xsd#ifrs-full_StatementOfCashFlowsAbstract@http://www.xbrl.org/2003/role/label::ssmt-cor_2022-12-31.xsd#ssmt_StatementOfCashFlowsLineItems@http://www.xbrl.org/2003/role/label:~:ssmt-cor_2022-12-31.xsd#ssmt_StatementOfCashFlowsTable
C18: #LAYOUTSCSR# | D18: #PRIM# | G18: #TABLE# | H18: #LAYOUTECSR#
C19: #STDTENDTDATE# | E19: =TEXT(DATE(MID(E21,7,4),MID(E21,4,2),MID(E21,1,2)),"dd/MM/yyyy")&" - "&TEXT(DATE(MID(E22,7,4),MID(E22,4,2),MID(E22,1,2)),"dd/MM/yyyy") -> 01/01/2024 - 31/12/2024 | F19: =TEXT(DATE(MID(F21,7,4),MID(F21,4,2),MID(F21,1,2)),"dd/MM/yyyy")&" - "&TEXT(DATE(MID(F22,7,4),MID(F22,4,2),MID(F22,1,2)),"dd/MM/yyyy") -> 01/01/2023 - 31/12/2023
C20: #UNITSCALE# | E20: =StartUp!$E$8 -> MYR'000 | F20: =StartUp!$E$8 -> MYR'000
C21: #STDT# | E21: =StartUp!$D$8 -> 01/01/2024 | F21: =StartUp!$D$10 -> 01/01/2023
C22: #ENDT# | E22: =StartUp!$D$9 -> 31/12/2024 | F22: =StartUp!$D$11 -> 31/12/2023
C23: #TABLE#
A24: full_ifrs-cor_2022-03-24.xsd#ifrs-full_StatementOfCashFlowsAbstract | D24: Statement of cash flows
A25: ssmt-cor_2022-12-31.xsd#ssmt_StatementOfCashFlowsLineItems | D25: Statement of cash flows
A26: ssmt-cor_2022-12-31.xsd#ssmt_StatementOfCashFlowsAbstract | D26: Statement of cash flows
A27: full_ifrs-cor_2022-03-24.xsd#ifrs-full_CashFlowsFromUsedInOperatingActivitiesAbstract | D27: Cash flows from (used in) operating activities
A28: full_ifrs-cor_2022-03-24.xsd#ifrs-full_ProfitLossBeforeTax | D28: *Profit (loss) before tax
A29: ssmt-mfrs-cor_2022-12-31.xsd#ssmt-mfrs_AggregateProfitLossBeforeTax@http://xbrl.ssm.com.my/role/ssm/fs/mfrs/lab_rol_ssmt-fs-mfrs_2022-12-31/ReportingTotalLabel | D29: *Total profit(loss) before tax | E29: =1*E28 -> 0 | F29: =1*F28 -> 0
A30: full_ifrs-cor_2022-03-24.xsd#ifrs-full_AdjustmentsForReconcileProfitLossAbstract | D30: Adjustments to reconcile profit (loss)
A31: full_ifrs-cor_2022-03-24.xsd#ifrs-full_AdjustmentsForDepreciationExpense@http://xbrl.ssm.com.my/role/ssm/lab_rol_ssmt-fs-mfrs_2022-12-31/ReportingLabel | D31: Adjustments for depreciation
A32: full_ifrs-cor_2022-03-24.xsd#ifrs-full_AdjustmentsForAmortisationExpense | D32: Adjustments for amortisation expense
A33: full_ifrs-cor_2022-03-24.xsd#ifrs-full_AdjustmentsForDividendIncome | D33: Adjustments for dividend income
A34: full_ifrs-cor_2022-03-24.xsd#ifrs-full_AdjustmentsForSharebasedPayments@http://xbrl.ssm.com.my/role/ssm/lab_rol_ssmt-fs-mfrs_2022-12-31/ReportingLabel | D34: Adjustments for equity settled share-based payment transactions
A35: full_ifrs-cor_2022-03-24.xsd#ifrs-full_AdjustmentsForGainsLossesOnFairValueAdjustmentInvestmentProperty@http://xbrl.ssm.com.my/role/ssm/lab_rol_ssmt-fs-mfrs_2022-12-31/ReportingLabel | D35: Adjustments for changes in fair value of investment properties
A36: ssmt-mfrs-cor_2022-12-31.xsd#ssmt-mfrs_AdjustmentsForUnrealisedForeignExchangeGainLoss@http://xbrl.ssm.com.my/role/ssm/lab_rol_ssmt-fs-mfrs_2022-12-31/ReportingLabel | D36: Adjustments for unrealised foreign exchange losses (gains)
A37: full_ifrs-cor_2022-03-24.xsd#ifrs-full_AdjustmentsForInterestIncome | D37: Adjustments for interest income
A38: ssmt-mfrs-cor_2022-12-31.xsd#ssmt-mfrs_AdjustmentsForPerformanceBasedEmployeeShareSchemeAndOtherExpenses | D38: Adjustments for performance-based employee share scheme and other expenses
A39: ssmt-mfrs-cor_2022-12-31.xsd#ssmt-mfrs_AdjustmentsForShareOfProfitsOfJointVentures@http://xbrl.ssm.com.my/role/ssm/lab_rol_ssmt-fs-mfrs_2022-12-31/ReportingLabel | D39: Adjustments for share of profits of joint ventures (net of tax)
A40: ssmt-mfrs-cor_2022-12-31.xsd#ssmt-mfrs_AdjustmentsForShareOptionExpenses | D40: Adjustments for share option expenses
A41: full_ifrs-cor_2022-03-24.xsd#ifrs-full_AdjustmentsForUndistributedProfitsOfAssociates | D41: Adjustments for undistributed profits of associates
... A55: ssmt-mfrs-cor_2022-12-31.xsd#ssmt-mfrs_ImpairmentLossRecognisedInProfitOrLossOnOtherFinancialAssetsOrReceivables@http://xbrl.ssm.com.my/role/ssm/lab_rol_ssmt-fs-mfrs_2022-12-31/ReportingLabel | D55: Impairment (reversal of impairment) of other financial assets or receivables
A56: full_ifrs-cor_2022-03-24.xsd#ifrs-full_ImpairmentLossRecognisedInProfitOrLoss@http://xbrl.ssm.com.my/role/ssm/fs/mfrs/lab_rol_ssmt-fs-mfrs_2022-12-31/ReportingTotalLabel | D56: Total adjustment for impairment (reversal of impairment) | E56: =1*E47+1*E48+1*E49+1*E50+1*E51+1*E52+1*E53+1*E54+1*E55 -> 0 | F56: =1*F47+1*F48+1*F49+1*F50+1*F51+1*F52+1*F53+1*F54+1*F55 -> 0
A57: full_ifrs-cor_2022-03-24.xsd#ifrs-full_GainsLossesOnDisposalsOfNoncurrentAssetsAbstract@http://xbrl.ssm.com.my/role/ssm/lab_rol_ssmt-fs-mfrs_2022-12-31/ReportingLabel | D57: Adjustments for losses (gains) on disposal of non-current assets
A58: full_ifrs-cor_2022-03-24.xsd#ifrs-full_GainsLossesOnDisposalsOfPropertyPlantAndEquipment@http://xbrl.ssm.com.my/role/ssm/lab_rol_ssmt-fs-mfrs_2022-12-31/ReportingLabel | D58: (Gain) loss on disposal of property, plant and equipment
A59: full_ifrs-cor_2022-03-24.xsd#ifrs-full_GainsLossesOnDisposalsOfInvestmentProperties@http://xbrl.ssm.com.my/role/ssm/lab_rol_ssmt-fs-mfrs_2022-12-31/ReportingLabel | D59: (Gain) loss on disposal of investment properties
A60: full_ifrs-cor_2022-03-24.xsd#ifrs-full_GainsLossesOnDisposalsOfNoncurrentAssets@http://xbrl.ssm.com.my/role/ssm/fs/mfrs/lab_rol_ssmt-fs-mfrs_2022-12-31/ReportingTotalLabel | D60: Total gain (loss) on disposal of non-current assets | E60: =1*E58+1*E59 -> 0 | F60: =1*F58+1*F59 -> 0
A61: ssmt-mfrs-cor_2022-12-31.xsd#ssmt-mfrs_GainsLossesOnDisposalOfSubsidiaries@http://xbrl.ssm.com.my/role/ssm/lab_rol_ssmt-fs-mfrs_2022-12-31/ReportingLabel | D61: (Gain) loss on disposal of subsidiaries
A62: ssmt-mfrs-cor_2022-12-31.xsd#ssmt-mfrs_GainsLossesOnDisposalOfAssociates@http://xbrl.ssm.com.my/role/ssm/lab_rol_ssmt-fs-mfrs_2022-12-31/ReportingLabel | D62: (Gain) loss on disposal of associates
A63: ssmt-mfrs-cor_2022-12-31.xsd#ssmt-mfrs_GainsLossesOnDisposalOfJointVentures@http://xbrl.ssm.com.my/role/ssm/lab_rol_ssmt-fs-mfrs_2022-12-31/ReportingLabel | D63: (Gain) loss on disposal of joint ventures
A64: ssmt-mfrs-cor_2022-12-31.xsd#ssmt-mfrs_GainsLossesOnDisposalOfOtherInvestments@http://xbrl.ssm.com.my/role/ssm/lab_rol_ssmt-fs-mfrs_2022-12-31/ReportingLabel | D64: Gain on disposal of other investments
A65: ssmt-mfrs-cor_2022-12-31.xsd#ssmt-mfrs_RealisedGainTransferredFromEquityOnForeignCurrencyExchange@http://xbrl.ssm.com.my/role/ssm/lab_rol_ssmt-fs-mfrs_2022-12-31/ReportingLabel | D65: Realised foreign currencies exchange gain transferred from equity
A66: full_ifrs-cor_2022-03-24.xsd#ifrs-full_OtherAdjustmentsForNoncashItems | D66: Other adjustments for non-cash items
A67: ssmt-mfrs-cor_2022-12-31.xsd#ssmt-mfrs_WriteOffOfAssetsAbstract@http://xbrl.ssm.com.my/role/ssm/lab_rol_ssmt-fs-mfrs_2022-12-31/ReportingLabel | D67: Write–off:
A68: full_ifrs-cor_2022-03-24.xsd#ifrs-full_WritedownsReversalsOfPropertyPlantAndEquipment@http://www.xbrl.org/2003/role/terseLabel | D68: Write offs of property, plant and equipment
A69: ssmt-mfrs-cor_2022-12-31.xsd#ssmt-mfrs_WritedownsReversalsOfIntangibleAssets@http://xbrl.ssm.com.my/role/ssm/lab_rol_ssmt-fs-mfrs_2022-12-31/ReportingLabel | D69: Write offs of intangible assets
A70: ssmt-mfrs-cor_2022-12-31.xsd#ssmt-mfrs_WritedownsReversalsOfInvestments@http://xbrl.ssm.com.my/role/ssm/lab_rol_ssmt-fs-mfrs_2022-12-31/ReportingLabel | D70: Write offs of investments
A71: full_ifrs-cor_2022-03-24.xsd#ifrs-full_WritedownsReversalsOfInventories@http://xbrl.ssm.com.my/role/ssm/lab_rol_ssmt-fs-mfrs_2022-12-31/ReportingLabel | D71: Write offs of inventories
A72: ssmt-mfrs-cor_2022-12-31.xsd#ssmt-mfrs_WritedownsOfTradeAndOtherReceivables@http://xbrl.ssm.com.my/role/ssm/lab_rol_ssmt-fs-mfrs_2022-12-31/ReportingLabel | D72: Write off of trade and other receivables
A73: ssmt-mfrs-cor_2022-12-31.xsd#ssmt-mfrs_WritedownsReversalsOfOtherFinancialAssets@http://xbrl.ssm.com.my/role/ssm/lab_rol_ssmt-fs-mfrs_2022-12-31/ReportingLabel | D73: Write offs of other financial assets
A74: ssmt-mfrs-cor_2022-12-31.xsd#ssmt-mfrs_WritedownsReversalsOfAssets@http://xbrl.ssm.com.my/role/ssm/fs/mfrs/lab_rol_ssmt-fs-mfrs_2022-12-31/ReportingTotalLabel | D74: Total write-off | E74: =1*E68+1*E69+1*E70+1*E71+1*E72+1*E73 -> 0 | F74: =1*F68+1*F69+1*F70+1*F71+1*F72+1*F73 -> 0
A75: ssmt-mfrs-cor_2022-12-31.xsd#ssmt-mfrs_WriteBackOfExpenses | D75: Write back of expenses
A76: full_ifrs-cor_2022-03-24.xsd#ifrs-full_OtherAdjustmentsToReconcileProfitLoss | D76: Other adjustments to reconcile profit (loss)
A77: full_ifrs-cor_2022-03-24.xsd#ifrs-full_AdjustmentsForReconcileProfitLoss@http://www.xbrl.org/2003/role/totalLabel | D77: *Total adjustments to reconcile profit (loss) | E77: =1*E31+1*E32+-1*E33+1*E34+-1*E35+1*E36+-1*E37+1*E38+1*E39+1*E40+-1*E41+1*E42+-1*E43+-1*E44+1*E45+1*E56+-1*E60+-1*E61+-1*E62+-1*E63+-1*E64+-1*E65+1*E66+1*E74+1*E75+1*E76 -> 0 | F77: =1*F31+1*F32+-1*F33+1*F34+-1*F35+1*F36+-1*F37+1*F38+1*F39+1*F40+-1*F41+1*F42+-1*F43+-1*F44+1*F45+1*F56+-1*F60+-1*F61+-1*F62+-1*F63+-1*F64+-1*F65+1*F66+1*F74+1*F75+1*F76 -> 0
A78: full_ifrs-cor_2022-03-24.xsd#ifrs-full_CashFlowsFromUsedInOperationsBeforeChangesInWorkingCapital@http://xbrl.ssm.com.my/role/ssm/lab_rol_ssmt-fs-mfrs_2022-12-31/ReportingLabel | D78: *Operating surplus (deficit) before working capital changes | E78: =1*E29+1*E77 -> 0 | F78: =1*F29+1*F77 -> 0
A79: ssmt-mfrs-cor_2022-12-31.xsd#ssmt-mfrs_ChangesInWorkingCapitalAbstract | D79: Changes in working capital
A80: full_ifrs-cor_2022-03-24.xsd#ifrs-full_AdjustmentsForDecreaseIncreaseInInventories | D80: Adjustments for decrease (increase) in inventories
A81: full_ifrs-cor_2022-03-24.xsd#ifrs-full_AdjustmentsForDecreaseIncreaseInTradeAndOtherReceivables | D81: Adjustments for decrease (increase) in trade and other receivables
A82: full_ifrs-cor_2022-03-24.xsd#ifrs-full_AdjustmentsForIncreaseDecreaseInTradeAndOtherPayables | D82: Adjustments for increase (decrease) in trade and other payables
A83: ssmt-mfrs-cor_2022-12-31.xsd#ssmt-mfrs_AdjustmentsForDecreaseIncreaseInPropertyDevelopmentCosts | D83: Adjustments for decrease (increase) in property development costs
A84: full_ifrs-cor_2022-03-24.xsd#ifrs-full_AdjustmentsForDecreaseIncreaseInContractAssets | D84: Adjustments for decrease (increase) in contract assets
A85: ssmt-cor_2022-12-31.xsd#ssmt_AdjustmentsForDecreaseIncreaseInContractLiabilities | D85: Adjustments for decrease (increase) in contract liabilities
A86: full_ifrs-cor_2022-03-24.xsd#ifrs-full_IncreaseDecreaseInWorkingCapital@http://xbrl.ssm.com.my/role/ssm/fs/mfrs/lab_rol_ssmt-fs-mfrs_2022-12-31/ReportingTotalLabel | D86: *Total changes in working capital | E86: =-1*E80+-1*E81+-1*E82+-1*E83+-1*E84+-1*E85 -> 0 | F86: =-1*F80+-1*F81+-1*F82+-1*F83+-1*F84+-1*F85 -> 0
A87: full_ifrs-cor_2022-03-24.xsd#ifrs-full_CashFlowsFromUsedInOperations@http://xbrl.ssm.com.my/role/ssm/fs/mfrs/lab_rol_ssmt-fs-mfrs_2022-12-31/ReportingTotalLabel | D87: *Cash generated from (used in) operations | E87: =1*E78+1*E86 -> 0 | F87: =1*F78+1*F86 -> 0
A88: full_ifrs-cor_2022-03-24.xsd#ifrs-full_DividendsReceivedClassifiedAsOperatingActivities@http://www.xbrl.org/2003/role/terseLabel | D88: Dividends received
A89: full_ifrs-cor_2022-03-24.xsd#ifrs-full_DividendsPaidClassifiedAsOperatingActivities@http://www.xbrl.org/2009/role/negatedTerseLabel | D89: Dividends paid
A90: full_ifrs-cor_2022-03-24.xsd#ifrs-full_InterestReceivedClassifiedAsOperatingActivities@http://www.xbrl.org/2003/role/terseLabel | D90: Interest received
A91: full_ifrs-cor_2022-03-24.xsd#ifrs-full_InterestPaidClassifiedAsOperatingActivities@http://www.xbrl.org/2009/role/negatedTerseLabel | D91: Interest paid
A92: ssmt-mfrs-cor_2022-12-31.xsd#ssmt-mfrs_PaymentsForRetirementBenefitsScheme | D92: Payment to a retirement benefits scheme
A93: full_ifrs-cor_2022-03-24.xsd#ifrs-full_IncomeTaxesPaidRefundClassifiedAsOperatingActivities@http://www.xbrl.org/2009/role/negatedTerseLabel | D93: Income taxes refund (paid)
A94: full_ifrs-cor_2022-03-24.xsd#ifrs-full_OtherInflowsOutflowsOfCashClassifiedAsOperatingActivities@http://xbrl.ssm.com.my/role/ssm/lab_rol_ssmt-fs-mfrs_2022-12-31/ReportingLabel | D94: Other cash inflows (outflows) from operating activities
A95: full_ifrs-cor_2022-03-24.xsd#ifrs-full_CashFlowsFromUsedInOperatingActivities@http://www.xbrl.org/2009/role/netLabel | D95: *Net cash flows from (used in) operating activities | E95: =1*E44+1*E88+1*E89+1*E90+1*E91+1*E92+1*E93+1*E94+1*E87 -> 0 | F95: =1*F44+1*F88+1*F89+1*F90+1*F91+1*F92+1*F93+1*F94+1*F87 -> 0
A96: full_ifrs-cor_2022-03-24.xsd#ifrs-full_CashFlowsFromUsedInInvestingActivitiesAbstract | D96: Cash flows from (used in) investing activities
A97: full_ifrs-cor_2022-03-24.xsd#ifrs-full_CashFlowsFromLosingControlOfSubsidiariesOrOtherBusinessesClassifiedAsInvestingActivities@http://xbrl.ssm.com.my/role/ssm/lab_rol_ssmt-fs-mfrs_2022-12-31/ReportingLabel | D97: Proceeds from disposal of subsidiaries
A98: full_ifrs-cor_2022-03-24.xsd#ifrs-full_CashFlowsUsedInObtainingControlOfSubsidiariesOrOtherBusinessesClassifiedAsInvestingActivities@http://www.xbrl.org/2009/role/negatedLabel | D98: Acquisition and subscription of shares in subsidiaries
A99: full_ifrs-cor_2022-03-24.xsd#ifrs-full_ProceedsFromSalesOfInterestsInAssociates@http://xbrl.ssm.com.my/role/ssm/lab_rol_ssmt-fs-mfrs_2022-12-31/ReportingLabel | D99: Proceeds from disposal of associates
A100: ssmt-mfrs-cor_2022-12-31.xsd#ssmt-mfrs_OtherCashPaymentsToAcquireInterestsInAssociates@http://www.xbrl.org/2009/role/negatedTerseLabel | D100: Acquisition and subscription of shares in associates
A101: full_ifrs-cor_2022-03-24.xsd#ifrs-full_OtherCashReceiptsFromSalesOfInterestsInJointVenturesClassifiedAsInvestingActivities@http://xbrl.ssm.com.my/role/ssm/lab_rol_ssmt-fs-mfrs_2022-12-31/ReportingLabel | D101: Proceeds from disposal of joint ventures
A102: full_ifrs-cor_2022-03-24.xsd#ifrs-full_OtherCashPaymentsToAcquireInterestsInJointVenturesClassifiedAsInvestingActivities@http://www.xbrl.org/2009/role/negatedLabel | D102: Acquisition and subscription of shares in joint ventures
A103: full_ifrs-cor_2022-03-24.xsd#ifrs-full_CashReceiptsFromRepaymentOfAdvancesAndLoansMadeToOtherPartiesClassifiedAsInvestingActivities | D103: Cash receipts from repayment of advances and loans made to other parties, classified as investing activities
A104: full_ifrs-cor_2022-03-24.xsd#ifrs-full_CashAdvancesAndLoansMadeToOtherPartiesClassifiedAsInvestingActivities@http://www.xbrl.org/2009/role/negatedTerseLabel | D104: Cash advances and loans made to other parties
A105: ssmt-mfrs-cor_2022-12-31.xsd#ssmt-mfrs_DepositPlacedWithInvestmentBrokers | D105: Deposit placed with investment brokers
A106: full_ifrs-cor_2022-03-24.xsd#ifrs-full_OtherCashPaymentsToAcquireEquityOrDebtInstrumentsOfOtherEntitiesClassifiedAsInvestingActivities@http://www.xbrl.org/2009/role/negatedTerseLabel | D106: Other cash payments to acquire equity or debt instruments of other entities
A107: full_ifrs-cor_2022-03-24.xsd#ifrs-full_OtherCashReceiptsFromSalesOfEquityOrDebtInstrumentsOfOtherEntitiesClassifiedAsInvestingActivities@http://xbrl.ssm.com.my/role/ssm/lab_rol_ssmt-fs-mfrs_2022-12-31/ReportingLabel | D107: Other cash receipts from sales of equity or debt instruments of other entities
... A126: full_ifrs-cor_2022-03-24.xsd#ifrs-full_OtherInflowsOutflowsOfCashClassifiedAsInvestingActivities@http://xbrl.ssm.com.my/role/ssm/lab_rol_ssmt-fs-mfrs_2022-12-31/ReportingLabel | D126: Other cash inflows (outflows) from investing activities
A127: full_ifrs-cor_2022-03-24.xsd#ifrs-full_CashFlowsFromUsedInInvestingActivities@http://www.xbrl.org/2009/role/netLabel | D127: *Net cash flows from (used in) investing activities | E127: =1*E97+-1*E98+1*E99+1*E101+-1*E102+1*E103+-1*E104+1*E105+-1*E106+1*E107+-1*E108+1*E109+1*E110+1*E111+1*E112+1*E113+-1*E115+-1*E116+-1*E117+1*E118+1*E119+1*E120+-1*E121+1*E126+1*E100+-1*E122+1*E114+-1*E123+-1*E124+1*E125 -> 0 | F127: =1*F97+-1*F98+1*F99+1*F101+-1*F102+1*F103+-1*F104+1*F105+-1*F106+1*F107+-1*F108+1*F109+1*F110+1*F111+1*F112+1*F113+-1*F115+-1*F116+-1*F117+1*F118+1*F119+1*F120+-1*F121+1*F126+1*F100+-1*F122+1*F114+-1*F123+-1*F124+1*F125 -> 0
A128: full_ifrs-cor_2022-03-24.xsd#ifrs-full_CashFlowsFromUsedInFinancingActivitiesAbstract | D128: Cash flows from (used in) financing activities
A129: ssmt-mfrs-cor_2022-12-31.xsd#ssmt-mfrs_PaymentsForPrincipalPortionOfLeaseLiability@http://xbrl.ssm.com.my/role/ssm/lab_rol_ssmt-fs-mfrs_2022-12-31/ReportingLabel | D129: Cash payments for the principal portion of the lease liability
A130: ssmt-mfrs-cor_2022-12-31.xsd#ssmt-mfrs_PaymentsForInterestPortionOfLeaseLiability@http://xbrl.ssm.com.my/role/ssm/lab_rol_ssmt-fs-mfrs_2022-12-31/ReportingLabel | D130: Cash payments for the interest portion of the lease liability
A131: full_ifrs-cor_2022-03-24.xsd#ifrs-full_ProceedsFromIssuingShares | D131: Proceeds from issuing shares
A132: ssmt-mfrs-cor_2022-12-31.xsd#ssmt-mfrs_ProceedsFromIssueOfSharesInSubsidiaryToNoncontrollingInterests | D132: Proceeds from issue of shares in subsidiary to non-controlling interests
A133: full_ifrs-cor_2022-03-24.xsd#ifrs-full_ProceedsFromIssuingOtherEquityInstruments | D133: Proceeds from issuing other equity instruments
A134: full_ifrs-cor_2022-03-24.xsd#ifrs-full_ProceedsFromExerciseOfOptions@http://xbrl.ssm.com.my/role/ssm/lab_rol_ssmt-fs-mfrs_2022-12-31/ReportingLabel | D134: Proceeds from share-based compensation transactions
A135: full_ifrs-cor_2022-03-24.xsd#ifrs-full_PaymentsToAcquireOrRedeemEntitysShares | D135: Payments to acquire or redeem entity's shares
A136: ssmt-mfrs-cor_2022-12-31.xsd#ssmt-mfrs_PaymentsMadeToAcquireNoncontrollingInterest@http://xbrl.ssm.com.my/role/ssm/lab_rol_ssmt-fs-mfrs_2022-12-31/ReportingLabel | D136: Acquisition of non-controlling interests
A137: full_ifrs-cor_2022-03-24.xsd#ifrs-full_PaymentsOfOtherEquityInstruments | D137: Payments of other equity instruments
A138: ssmt-mfrs-cor_2022-12-31.xsd#ssmt-mfrs_CashPaymentsForIssuanceOfPerpetualSukuk@http://xbrl.ssm.com.my/role/ssm/lab_rol_ssmt-fs-mfrs_2022-12-31/ReportingLabel | D138: Perpetual sukuk issuance expenses
...

Sheet SOCIE
A1: d3e49dce-3dbf-475f-a3ed-fe19378bfac3:~:AtleastOneValueInAnyLayout:~:True:~:<?xml version="1.0" encoding="utf-16"?>_x000D_ <Customization xmlns:xsi="http://www.w3.org/2001/XMLSchema-instance" xmlns:xsd="http://www.w3.org/2001/XMLSchema" ComparitiveDate="False" LayoutByDate="True" LayoutByCompany="True" ShowAllDomains="True" TotalDomain="True" DefaultDates="2" />:~:http://xbrl.ssm.com.my/role/ssm/rol_ssmt-fs-mfrs_2022-12-31/ssmt-fs-mfrs_2022-12-31_role-610000:~:None
D2: FS-MFRS Statement of Changes in Equity
D3: * denotes mandatory items to be reported
C5: 02e045b9-3494-4f53-9efe-596d03fae191:~:SOCIE_1_TBLYT:~:NotMandatory:~:False:~:0:~:True:~:<?xml version="1.0" encoding="utf-16"?>_x000D_ <Customization xmlns:xsi="http://www.w3.org/2001/XMLSchema-instance" xmlns:xsd="http://www.w3.org/2001/XMLSchema" ComparitiveDate="False" LayoutByDate="True" LayoutByCompany="True" ShowAllDomains="True" TotalDomain="True" DefaultDates="2" />:~:LytTxb:~::~:False:~:True:~:ssmt-mfrs-cor_2022-12-31.xsd#ssmt-mfrs_DisclosureOfChangesInEquityAbstract@http://www.xbrl.org/2003/role/label:~:
C8: #LAYOUTSCSR# | D8: #PRIM# | F8: #TABLE# | G8: #LAYOUTECSR#
C9: #TABLE#
A10: ssmt-mfrs-cor_2022-12-31.xsd#ssmt-mfrs_DisclosureOfChangesInEquityAbstract | D10: Disclosure of changes in equity
C11: #TABLE#
C12: #LAYOUTSCER# | G12: #LAYOUTECER#
C15: 65fc94ef-75be-44d7-8500-4770799cdca0:~:SOCIE_2:~:NotMandatory:~:False:~:1:~:True:~:<?xml version="1.0" encoding="utf-16"?>_x000D_ <Customization xmlns:xsi="http://www.w3.org/2001/XMLSchema-instance" xmlns:xsd="http://www.w3.org/2001/XMLSchema" ComparitiveDate="False" LayoutByDate="True" LayoutByCompany="True" ShowAllDomains="True" TotalDomain="True" DefaultDates="2" />:~:LytHyc:~:full_ifrs-cor_2022-03-24.xsd#ifrs-full_StatementOfChangesInEquityTable:~:False:~:True:~:ssmt-mfrs-cor_2022-12-31.xsd#ssmt-mfrs_DisclosureOfChangesInEquityAbstract@http://www.xbrl.org/2003/role/label::full_ifrs-cor_2022-03-24.xsd#ifrs-full_StatementOfChangesInEquityAbstract@http://www.xbrl.org/2003/role/label::full_ifrs-cor_2022-03-24.xsd#ifrs-full_StatementOfChangesInEquityLineItems@http://www.xbrl.org/2003/role/label:~:full_ifrs-cor_2022-03-24.xsd#ifrs-full_StatementOfChangesInEquityTable
E17: full_ifrs-cor_2022-03-24.xsd#ifrs-full_StatementOfChangesInEquityTable::full_ifrs-cor_2022-03-24.xsd#ifrs-full_ComponentsOfEquityAxis::full_ifrs-cor_2022-03-24.xsd#ifrs-full_IssuedCapitalMember | F17: full_ifrs-cor_2022-03-24.xsd#ifrs-full_StatementOfChangesInEquityTable::full_ifrs-cor_2022-03-24.xsd#ifrs-full_ComponentsOfEquityAxis::full_ifrs-cor_2022-03-24.xsd#ifrs-full_RetainedEarningsMember | G17: full_ifrs-cor_2022-03-24.xsd#ifrs-full_StatementOfChangesInEquityTable::full_ifrs-cor_2022-03-24.xsd#ifrs-full_ComponentsOfEquityAxis::full_ifrs-cor_2022-03-24.xsd#ifrs-full_TreasurySharesMember | H17: full_ifrs-cor_2022-03-24.xsd#ifrs-full_StatementOfChangesInEquityTable::full_ifrs-cor_2022-03-24.xsd#ifrs-full_ComponentsOfEquityAxis::full_ifrs-cor_2022-03-24.xsd#ifrs-full_CapitalReserveMember | I17: full_ifrs-cor_2022-03-24.xsd#ifrs-full_StatementOfChangesInEquityTable::full_ifrs-cor_2022-03-24.xsd#ifrs-full_ComponentsOfEquityAxis::full_ifrs-cor_2022-03-24.xsd#ifrs-full_ReserveOfGainsAndLossesOnHedgingInstrumentsThatHedgeInvestmentsInEquityInstrumentsMember | J17: full_ifrs-cor_2022-03-24.xsd#ifrs-full_StatementOfChangesInEquityTable::full_ifrs-cor_2022-03-24.xsd#ifrs-full_ComponentsOfEquityAxis::ssmt-mfrs-cor_2022-12-31.xsd#ssmt-mfrs_ForeignCurrencyTranslationReserveMember | K17: full_ifrs-cor_2022-03-24.xsd#ifrs-full_StatementOfChangesInEquityTable::full_ifrs-cor_2022-03-24.xsd#ifrs-full_ComponentsOfEquityAxis::full_ifrs-cor_2022-03-24.xsd#ifrs-full_ReserveOfSharebasedPaymentsMember | L17: full_ifrs-cor_2022-03-24.xsd#ifrs-full_StatementOfChangesInEquityTable::full_ifrs-cor_2022-03-24.xsd#ifrs-full_ComponentsOfEquityAxis::full_ifrs-cor_2022-03-24.xsd#ifrs-full_RevaluationSurplusMember | M17: full_ifrs-cor_2022-03-24.xsd#ifrs-full_StatementOfChangesInEquityTable::full_ifrs-cor_2022-03-24.xsd#ifrs-full_ComponentsOfEquityAxis::full_ifrs-cor_2022-03-24.xsd#ifrs-full_StatutoryReserveMember | N17: full_ifrs-cor_2022-03-24.xsd#ifrs-full_StatementOfChangesInEquityTable::full_ifrs-cor_2022-03-24.xsd#ifrs-full_ComponentsOfEquityAxis::full_ifrs-cor_2022-03-24.xsd#ifrs-full_WarrantReserveMember | O17: full_ifrs-cor_2022-03-24.xsd#ifrs-full_StatementOfChangesInEquityTable::full_ifrs-cor_2022-03-24.xsd#ifrs-full_ComponentsOfEquityAxis::ssmt-mfrs-cor_2022-12-31.xsd#ssmt-mfrs_OtherNondistributableReserveMember | P17: full_ifrs-cor_2022-03-24.xsd#ifrs-full_StatementOfChangesInEquityTable::full_ifrs-cor_2022-03-24.xsd#ifrs-full_ComponentsOfEquityAxis::ssmt-cor_2022-12-31.xsd#ssmt_NonDistributableReservesMember | Q17: full_ifrs-cor_2022-03-24.xsd#ifrs-full_StatementOfChangesInEquityTable::full_ifrs-cor_2022-03-24.xsd#ifrs-full_ComponentsOfEquityAxis::ssmt-mfrs-cor_2022-12-31.xsd#ssmt-mfrs_FairValueAdjustmentReserveMember | R17: full_ifrs-cor_2022-03-24.xsd#ifrs-full_StatementOfChangesInEquityTable::full_ifrs-cor_2022-03-24.xsd#ifrs-full_ComponentsOfEquityAxis::ssmt-cor_2022-12-31.xsd#ssmt_ReserveOfNoncurrentAssetsClassifiedAsHeldForSaleMember | S17: full_ifrs-cor_2022-03-24.xsd#ifrs-full_StatementOfChangesInEquityTable::full_ifrs-cor_2022-03-24.xsd#ifrs-full_ComponentsOfEquityAxis::ssmt-mfrs-cor_2022-12-31.xsd#ssmt-mfrs_ConsolidatedReserveMember | T17: full_ifrs-cor_2022-03-24.xsd#ifrs-full_StatementOfChangesInEquityTable::full_ifrs-cor_2022-03-24.xsd#ifrs-full_ComponentsOfEquityAxis::ssmt-mfrs-cor_2022-12-31.xsd#ssmt-mfrs_WarrantyReserveMember | U17: full_ifrs-cor_2022-03-24.xsd#ifrs-full_StatementOfChangesInEquityTable::full_ifrs-cor_2022-03-24.xsd#ifrs-full_ComponentsOfEquityAxis::ssmt-mfrs-cor_2022-12-31.xsd#ssmt-mfrs_OtherDistributableReserveMember | V17: full_ifrs-cor_2022-03-24.xsd#ifrs-full_StatementOfChangesInEquityTable::full_ifrs-cor_2022-03-24.xsd#ifrs-full_ComponentsOfEquityAxis::ssmt-cor_2022-12-31.xsd#ssmt_DistributableReservesMember | W17: full_ifrs-cor_2022-03-24.xsd#ifrs-full_StatementOfChangesInEquityTable::full_ifrs-cor_2022-03-24.xsd#ifrs-full_ComponentsOfEquityAxis::full_ifrs-cor_2022-03-24.xsd#ifrs-full_OtherReservesMember | X17: full_ifrs-cor_2022-03-24.xsd#ifrs-full_StatementOfChangesInEquityTable::full_ifrs-cor_2022-03-24.xsd#ifrs-full_ComponentsOfEquityAxis::full_ifrs-cor_2022-03-24.xsd#ifrs-full_EquityAttributableToOwnersOfParentMember | Y17: full_ifrs-cor_2022-03-24.xsd#ifrs-full_StatementOfChangesInEquityTable::full_ifrs-cor_2022-03-24.xsd#ifrs-full_ComponentsOfEquityAxis::ssmt-mfrs-cor_2022-12-31.xsd#ssmt-mfrs_OtherComponentsOfEquityMember | Z17: full_ifrs-cor_2022-03-24.xsd#ifrs-full_StatementOfChangesInEquityTable::full_ifrs-cor_2022-03-24.xsd#ifrs-full_ComponentsOfEquityAxis::full_ifrs-cor_2022-03-24.xsd#ifrs-full_NoncontrollingInterestsMember | AA17: 0
C18: #LAYOUTSCSR# | D18: #PRIM# | AB18: #TABLE# | AC18: #LAYOUTECSR#
B19: full_ifrs-cor_2022-03-24.xsd#ifrs-full_StatementOfChangesInEquityTable::full_ifrs-cor_2022-03-24.xsd#ifrs-full_ComponentsOfEquityAxis | C19: #DOM# | D19: Edit Components of equity | E19: Issued capital | F19: Retained earnings | G19: Treasury shares | H19: Capital reserve | I19: Hedging reserve | J19: Foreign currency translation reserve | K19: Reserve of share-based payments | L19: Revaluation surplus | M19: Statutory reserve | N19: Warrant reserve | O19: Other non-distributable reserves | P19: Sub-total of non-distributable reserves | Q19: Fair value reserve | R19: Reserve of non-current assets classified as held for sale | S19: Consolidation reserve | T19: Warranty reserve | U19: Other distributable reserves | V19: Sub-Total of distributable reserves | W19: Reserves | X19: Equity attributable to owners | Y19: Equity, others components | Z19: Non-controlling interests | AA19: Total
C20: #STDTENDTDATE# | E20: =TEXT(DATE(MID(E22,7,4),MID(E22,4,2),MID(E22,1,2)),"dd/MM/yyyy")&" - "&TEXT(DATE(MID(E23,7,4),MID(E23,4,2),MID(E23,1,2)),"dd/MM/yyyy") -> 01/01/2024 - 31/12/2024 | F20: =TEXT(DATE(MID(F22,7,4),MID(F22,4,2),MID(F22,1,2)),"dd/MM/yyyy")&" - "&TEXT(DATE(MID(F23,7,4),MID(F23,4,2),MID(F23,1,2)),"dd/MM/yyyy") -> 01/01/2024 - 31/12/2024 | G20: =TEXT(DATE(MID(G22,7,4),MID(G22,4,2),MID(G22,1,2)),"dd/MM/yyyy")&" - "&TEXT(DATE(MID(G23,7,4),MID(G23,4,2),MID(G23,1,2)),"dd/MM/yyyy") -> 01/01/2024 - 31/12/2024 | H20: =TEXT(DATE(MID(H22,7,4),MID(H22,4,2),MID(H22,1,2)),"dd/MM/yyyy")&" - "&TEXT(DATE(MID(H23,7,4),MID(H23,4,2),MID(H23,1,2)),"dd/MM/yyyy") -> 01/01/2024 - 31/12/2024 | I20: =TEXT(DATE(MID(I22,7,4),MID(I22,4,2),MID(I22,1,2)),"dd/MM/yyyy")&" - "&TEXT(DATE(MID(I23,7,4),MID(I23,4,2),MID(I23,1,2)),"dd/MM/yyyy") -> 01/01/2024 - 31/12/2024 | J20: =TEXT(DATE(MID(J22,7,4),MID(J22,4,2),MID(J22,1,2)),"dd/MM/yyyy")&" - "&TEXT(DATE(MID(J23,7,4),MID(J23,4,2),MID(J23,1,2)),"dd/MM/yyyy") -> 01/01/2024 - 31/12/2024 | K20: =TEXT(DATE(MID(K22,7,4),MID(K22,4,2),MID(K22,1,2)),"dd/MM/yyyy")&" - "&TEXT(DATE(MID(K23,7,4),MID(K23,4,2),MID(K23,1,2)),"dd/MM/yyyy") -> 01/01/2024 - 31/12/2024 | L20: =TEXT(DATE(MID(L22,7,4),MID(L22,4,2),MID(L22,1,2)),"dd/MM/yyyy")&" - "&TEXT(DATE(MID(L23,7,4),MID(L23,4,2),MID(L23,1,2)),"dd/MM/yyyy") -> 01/01/2024 - 31/12/2024 | ... AA20: =TEXT(DATE(MID(AA22,7,4),MID(AA22,4,2),MID(AA22,1,2)),"dd/MM/yyyy")&" - "&TEXT(DATE(MID(AA23,7,4),MID(AA23,4,2),MID(AA23,1,2)),"dd/MM/yyyy") -> 01/01/2024 - 31/12/2024
C21: #UNITSCALE# | E21: =StartUp!$E$8 -> MYR'000 | F21: =StartUp!$E$8 -> MYR'000 | G21: =StartUp!$E$8 -> MYR'000 | H21: =StartUp!$E$8 -> MYR'000 | I21: =StartUp!$E$8 -> MYR'000 | J21: =StartUp!$E$8 -> MYR'000 | K21: =StartUp!$E$8 -> MYR'000 | L21: =StartUp!$E$8 -> MYR'000 | ... AA21: =StartUp!$E$8 -> MYR'000
C22: #STDT# | E22: =StartUp!$D$8 -> 01/01/2024 | F22: =StartUp!$D$8 -> 01/01/2024 | G22: =StartUp!$D$8 -> 01/01/2024 | H22: =StartUp!$D$8 -> 01/01/2024 | I22: =StartUp!$D$8 -> 01/01/2024 | J22: =StartUp!$D$8 -> 01/01/2024 | K22: =StartUp!$D$8 -> 01/01/2024 | L22: =StartUp!$D$8 -> 01/01/2024 | ... AA22: =StartUp!$D$8 -> 01/01/2024
C23: #ENDT# | E23: =StartUp!$D$9 -> 31/12/2024 | F23: =StartUp!$D$9 -> 31/12/2024 | G23: =StartUp!$D$9 -> 31/12/2024 | H23: =StartUp!$D$9 -> 31/12/2024 | I23: =StartUp!$D$9 -> 31/12/2024 | J23: =StartUp!$D$9 -> 31/12/2024 | K23: =StartUp!$D$9 -> 31/12/2024 | L23: =StartUp!$D$9 -> 31/12/2024 | ... AA23: =StartUp!$D$9 -> 31/12/2024
C24: #TABLE#
A25: full_ifrs-cor_2022-03-24.xsd#ifrs-full_StatementOfChangesInEquityAbstract | D25: Statement of changes in equity
A26: full_ifrs-cor_2022-03-24.xsd#ifrs-full_StatementOfChangesInEquityLineItems | D26: Statement of changes in equity
A27: full_ifrs-cor_2022-03-24.xsd#ifrs-full_Equity@http://www.xbrl.org/2003/role/periodStartLabel | D27: *Equity at beginning of period
A28: ssmt-mfrs-cor_2022-12-31.xsd#ssmt-mfrs_ImpactOfChangeInAccountingStandards | D28: *Impact of changes in accounting policies
A29: ssmt-mfrs-cor_2022-12-31.xsd#ssmt-mfrs_EquityBalanceRestated@http://xbrl.ssm.com.my/role/ssm/fs/mfrs/lab_rol_ssmt-fs-mfrs_2022-12-31/ReportingPeriodStartLabel | D29: *Equity at beginning of period, restated | E29: =SOCIE!E27+SOCIE!E28 -> 0 | F29: =SOCIE!F27+SOCIE!F28 -> 0 | G29: =SOCIE!G27+SOCIE!G28 -> 0 | H29: =SOCIE!H27+SOCIE!H28 -> 0 | I29: =SOCIE!I27+SOCIE!I28 -> 0 | J29: =SOCIE!J27+SOCIE!J28 -> 0 | K29: =SOCIE!K27+SOCIE!K28 -> 0 | L29: =SOCIE!L27+SOCIE!L28 -> 0 | ... AA29: =SOCIE!AA27+SOCIE!AA28 -> 0
A30: full_ifrs-cor_2022-03-24.xsd#ifrs-full_ChangesInEquityAbstract | D30: Changes in equity
A31: full_ifrs-cor_2022-03-24.xsd#ifrs-full_ComprehensiveIncomeAbstract | D31: Comprehensive income
A32: full_ifrs-cor_2022-03-24.xsd#ifrs-full_ProfitLoss | D32: *Profit (loss)
A33: full_ifrs-cor_2022-03-24.xsd#ifrs-full_OtherComprehensiveIncome@http://www.xbrl.org/2003/role/totalLabel | D33: *Total other comprehensive income
A34: full_ifrs-cor_2022-03-24.xsd#ifrs-full_ComprehensiveIncome@http://www.xbrl.org/2003/role/totalLabel | D34: *Total comprehensive income | E34: =1*E32+1*E33 -> 0 | F34: =1*F32+1*F33 -> 0 | G34: =1*G32+1*G33 -> 0 | H34: =1*H32+1*H33 -> 0 | I34: =1*I32+1*I33 -> 0 | J34: =1*J32+1*J33 -> 0 | K34: =1*K32+1*K33 -> 0 | L34: =1*L32+1*L33 -> 0 | ... AA34: =1*AA32+1*AA33 -> 0
A35: ssmt-mfrs-cor_2022-12-31.xsd#ssmt-mfrs_ContributionsByAndDistributionsToOwnersAbstract | D35: Contributions by and distributions to owners
A36: full_ifrs-cor_2022-03-24.xsd#ifrs-full_IncreaseDecreaseThroughAcquisitionOfSubsidiary@http://xbrl.ssm.com.my/role/ssm/lab_rol_ssmt-fs-mfrs_2022-12-31/ReportingLabel | D36: Acquisition (dilution) of equity interest in subsidiaries
A37: full_ifrs-cor_2022-03-24.xsd#ifrs-full_IncreaseDecreaseThroughConversionOfConvertibleInstruments@http://xbrl.ssm.com.my/role/ssm/lab_rol_ssmt-fs-mfrs_2022-12-31/ReportingLabel | D37: Arising from conversion of Irredeemable Convertible Unsecured Loan Stock (ICULS)
A38: full_ifrs-cor_2022-03-24.xsd#ifrs-full_DividendsPaid@http://xbrl.ssm.com.my/role/ssm/lab_rol_ssmt-fs-mfrs_2022-12-31/ReportingLabel | D38: Dividends paid
A39: full_ifrs-cor_2022-03-24.xsd#ifrs-full_IssueOfEquity@http://xbrl.ssm.com.my/role/ssm/lab_rol_ssmt-fs-mfrs_2022-12-31/ReportingLabel | D39: Issuance of shares
A40: full_ifrs-cor_2022-03-24.xsd#ifrs-full_IssueOfConvertibleInstruments@http://xbrl.ssm.com.my/role/ssm/lab_rol_ssmt-fs-mfrs_2022-12-31/ReportingLabel | D40: Issue of convertible notes, net of tax
A41: full_ifrs-cor_2022-03-24.xsd#ifrs-full_IncreaseDecreaseThroughSharebasedPaymentTransactions | D41: Increase (decrease) through share-based payment transactions, equity
A42: full_ifrs-cor_2022-03-24.xsd#ifrs-full_IncreaseDecreaseThroughTreasuryShareTransactions@http://xbrl.ssm.com.my/role/ssm/lab_rol_ssmt-fs-mfrs_2022-12-31/ReportingLabel | D42: Treasury shares transactions
A43: full_ifrs-cor_2022-03-24.xsd#ifrs-full_IncreaseDecreaseThroughTransactionsWithOwners@http://xbrl.ssm.com.my/role/ssm/lab_rol_ssmt-fs-mfrs_2022-12-31/ReportingLabel | D43: Other transactions with owners
A44: full_ifrs-cor_2022-03-24.xsd#ifrs-full_IncreaseDecreaseThroughTransfersAndOtherChangesEquity | D44: Increase (decrease) through other changes, equity
A45: full_ifrs-cor_2022-03-24.xsd#ifrs-full_ChangesInEquity@http://www.xbrl.org/2003/role/totalLabel | D45: *Total increase (decrease) in equity | E45: =1*E34+1*E36+1*E37+-1*E38+1*E39+1*E40+1*E41+1*E42+1*E43+1*E44 -> 0 | F45: =1*F34+1*F36+1*F37+-1*F38+1*F39+1*F40+1*F41+1*F42+1*F43+1*F44 -> 0 | G45: =1*G34+1*G36+1*G37+-1*G38+1*G39+1*G40+1*G41+1*G42+1*G43+1*G44 -> 0 | H45: =1*H34+1*H36+1*H37+-1*H38+1*H39+1*H40+1*H41+1*H42+1*H43+1*H44 -> 0 | I45: =1*I34+1*I36+1*I37+-1*I38+1*I39+1*I40+1*I41+1*I42+1*I43+1*I44 -> 0 | J45: =1*J34+1*J36+1*J37+-1*J38+1*J39+1*J40+1*J41+1*J42+1*J43+1*J44 -> 0 | K45: =1*K34+1*K36+1*K37+-1*K38+1*K39+1*K40+1*K41+1*K42+1*K43+1*K44 -> 0 | L45: =1*L34+1*L36+1*L37+-1*L38+1*L39+1*L40+1*L41+1*L42+1*L43+1*L44 -> 0 | ... AA45: =1*AA34+1*AA36+1*AA37+-1*AA38+1*AA39+1*AA40+1*AA41+1*AA42+1*AA43+1*AA44 -> 0
A46: full_ifrs-cor_2022-03-24.xsd#ifrs-full_Equity@http://www.xbrl.org/2003/role/periodEndLabel | D46: *Equity at end of period | E46: =SOCIE!E29+SOCIE!E45 -> 0 | F46: =SOCIE!F29+SOCIE!F45 -> 0 | G46: =SOCIE!G29+SOCIE!G45 -> 0 | H46: =SOCIE!H29+SOCIE!H45 -> 0 | I46: =SOCIE!I29+SOCIE!I45 -> 0 | J46: =SOCIE!J29+SOCIE!J45 -> 0 | K46: =SOCIE!K29+SOCIE!K45 -> 0 | L46: =SOCIE!L29+SOCIE!L45 -> 0 | ... AA46: =SOCIE!AA29+SOCIE!AA45 -> 0
C47: #TABLE#
C48: #LAYOUTSCER# | AC48: #LAYOUTECER#
C51: fb9d9c63-bb90-4d43-8d3b-62334f905062:~:SOCIE_2:~:NotMandatory:~:True:~:1:~:True:~:<?xml version="1.0" encoding="utf-16"?>_x000D_ <Customization xmlns:xsi="http://www.w3.org/2001/XMLSchema-instance" xmlns:xsd="http://www.w3.org/2001/XMLSchema" ComparitiveDate="False" LayoutByDate="True" LayoutByCompany="True" ShowAllDomains="True" TotalDomain="True" DefaultDates="2" />:~:LytHyc:~:full_ifrs-cor_2022-03-24.xsd#ifrs-full_StatementOfChangesInEquityTable:~:False:~:False:~:ssmt-mfrs-cor_2022-12-31.xsd#ssmt-mfrs_DisclosureOfChangesInEquityAbstract@http://www.xbrl.org/2003/role/label::full_ifrs-cor_2022-03-24.xsd#ifrs-full_StatementOfChangesInEquityAbstract@http://www.xbrl.org/2003/role/label::full_ifrs-cor_2022-03-24.xsd#ifrs-full_StatementOfChangesInEquityLineItems@http://www.xbrl.org/2003/role/label:~:full_ifrs-cor_2022-03-24.xsd#ifrs-full_StatementOfChangesInEquityTable
E53: full_ifrs-cor_2022-03-24.xsd#ifrs-full_StatementOfChangesInEquityTable::full_ifrs-cor_2022-03-24.xsd#ifrs-full_ComponentsOfEquityAxis::full_ifrs-cor_2022-03-24.xsd#ifrs-full_IssuedCapitalMember | F53: full_ifrs-cor_2022-03-24.xsd#ifrs-full_StatementOfChangesInEquityTable::full_ifrs-cor_2022-03-24.xsd#ifrs-full_ComponentsOfEquityAxis::full_ifrs-cor_2022-03-24.xsd#ifrs-full_RetainedEarningsMember | G53: full_ifrs-cor_2022-03-24.xsd#ifrs-full_StatementOfChangesInEquityTable::full_ifrs-cor_2022-03-24.xsd#ifrs-full_ComponentsOfEquityAxis::full_ifrs-cor_2022-03-24.xsd#ifrs-full_TreasurySharesMember | H53: full_ifrs-cor_2022-03-24.xsd#ifrs-full_StatementOfChangesInEquityTable::full_ifrs-cor_2022-03-24.xsd#ifrs-full_ComponentsOfEquityAxis::full_ifrs-cor_2022-03-24.xsd#ifrs-full_CapitalReserveMember | I53: full_ifrs-cor_2022-03-24.xsd#ifrs-full_StatementOfChangesInEquityTable::full_ifrs-cor_2022-03-24.xsd#ifrs-full_ComponentsOfEquityAxis::full_ifrs-cor_2022-03-24.xsd#ifrs-full_ReserveOfGainsAndLossesOnHedgingInstrumentsThatHedgeInvestmentsInEquityInstrumentsMember | J53: full_ifrs-cor_2022-03-24.xsd#ifrs-full_StatementOfChangesInEquityTable::full_ifrs-cor_2022-03-24.xsd#ifrs-full_ComponentsOfEquityAxis::ssmt-mfrs-cor_2022-12-31.xsd#ssmt-mfrs_ForeignCurrencyTranslationReserveMember | K53: full_ifrs-cor_2022-03-24.xsd#ifrs-full_StatementOfChangesInEquityTable::full_ifrs-cor_2022-03-24.xsd#ifrs-full_ComponentsOfEquityAxis::full_ifrs-cor_2022-03-24.xsd#ifrs-full_ReserveOfSharebasedPaymentsMember | L53: full_ifrs-cor_2022-03-24.xsd#ifrs-full_StatementOfChangesInEquityTable::full_ifrs-cor_2022-03-24.xsd#ifrs-full_ComponentsOfEquityAxis::full_ifrs-cor_2022-03-24.xsd#ifrs-full_RevaluationSurplusMember | M53: full_ifrs-cor_2022-03-24.xsd#ifrs-full_StatementOfChangesInEquityTable::full_ifrs-cor_2022-03-24.xsd#ifrs-full_ComponentsOfEquityAxis::full_ifrs-cor_2022-03-24.xsd#ifrs-full_StatutoryReserveMember | N53: full_ifrs-cor_2022-03-24.xsd#ifrs-full_StatementOfChangesInEquityTable::full_ifrs-cor_2022-03-24.xsd#ifrs-full_ComponentsOfEquityAxis::full_ifrs-cor_2022-03-24.xsd#ifrs-full_WarrantReserveMember | O53: full_ifrs-cor_2022-03-24.xsd#ifrs-full_StatementOfChangesInEquityTable::full_ifrs-cor_2022-03-24.xsd#ifrs-full_ComponentsOfEquityAxis::ssmt-mfrs-cor_2022-12-31.xsd#ssmt-mfrs_OtherNondistributableReserveMember | P53: full_ifrs-cor_2022-03-24.xsd#ifrs-full_StatementOfChangesInEquityTable::full_ifrs-cor_2022-03-24.xsd#ifrs-full_ComponentsOfEquityAxis::ssmt-cor_2022-12-31.xsd#ssmt_NonDistributableReservesMember | Q53: full_ifrs-cor_2022-03-24.xsd#ifrs-full_StatementOfChangesInEquityTable::full_ifrs-cor_2022-03-24.xsd#ifrs-full_ComponentsOfEquityAxis::ssmt-mfrs-cor_2022-12-31.xsd#ssmt-mfrs_FairValueAdjustmentReserveMember | R53: full_ifrs-cor_2022-03-24.xsd#ifrs-full_StatementOfChangesInEquityTable::full_ifrs-cor_2022-03-24.xsd#ifrs-full_ComponentsOfEquityAxis::ssmt-cor_2022-12-31.xsd#ssmt_ReserveOfNoncurrentAssetsClassifiedAsHeldForSaleMember | S53: full_ifrs-cor_2022-03-24.xsd#ifrs-full_StatementOfChangesInEquityTable::full_ifrs-cor_2022-03-24.xsd#ifrs-full_ComponentsOfEquityAxis::ssmt-mfrs-cor_2022-12-31.xsd#ssmt-mfrs_ConsolidatedReserveMember | T53: full_ifrs-cor_2022-03-24.xsd#ifrs-full_StatementOfChangesInEquityTable::full_ifrs-cor_2022-03-24.xsd#ifrs-full_ComponentsOfEquityAxis::ssmt-mfrs-cor_2022-12-31.xsd#ssmt-mfrs_WarrantyReserveMember | U53: full_ifrs-cor_2022-03-24.xsd#ifrs-full_StatementOfChangesInEquityTable::full_ifrs-cor_2022-03-24.xsd#ifrs-full_ComponentsOfEquityAxis::ssmt-mfrs-cor_2022-12-31.xsd#ssmt-mfrs_OtherDistributableReserveMember | V53: full_ifrs-cor_2022-03-24.xsd#ifrs-full_StatementOfChangesInEquityTable::full_ifrs-cor_2022-03-24.xsd#ifrs-full_ComponentsOfEquityAxis::ssmt-cor_2022-12-31.xsd#ssmt_DistributableReservesMember | W53: full_ifrs-cor_2022-03-24.xsd#ifrs-full_StatementOfChangesInEquityTable::full_ifrs-cor_2022-03-24.xsd#ifrs-full_ComponentsOfEquityAxis::full_ifrs-cor_2022-03-24.xsd#ifrs-full_OtherReservesMember | X53: full_ifrs-cor_2022-03-24.xsd#ifrs-full_StatementOfChangesInEquityTable::full_ifrs-cor_2022-03-24.xsd#ifrs-full_ComponentsOfEquityAxis::full_ifrs-cor_2022-03-24.xsd#ifrs-full_EquityAttributableToOwnersOfParentMember | Y53: full_ifrs-cor_2022-03-24.xsd#ifrs-full_StatementOfChangesInEquityTable::full_ifrs-cor_2022-03-24.xsd#ifrs-full_ComponentsOfEquityAxis::ssmt-mfrs-cor_2022-12-31.xsd#ssmt-mfrs_OtherComponentsOfEquityMember | Z53: full_ifrs-cor_2022-03-24.xsd#ifrs-full_StatementOfChangesInEquityTable::full_ifrs-cor_2022-03-24.xsd#ifrs-full_ComponentsOfEquityAxis::full_ifrs-cor_2022-03-24.xsd#ifrs-full_NoncontrollingInterestsMember | AA53: 0
C54: #LAYOUTSCSR# | D54: #PRIM# | AB54: #TABLE# | AC54: #LAYOUTECSR#
B55: full_ifrs-cor_2022-03-24.xsd#ifrs-full_StatementOfChangesInEquityTable::full_ifrs-cor_2022-03-24.xsd#ifrs-full_ComponentsOfEquityAxis | C55: #DOM# | D55: Edit Components of equity | E55: Issued capital | F55: Retained earnings | G55: Treasury shares | H55: Capital reserve | I55: Hedging reserve | J55: Foreign currency translation reserve | K55: Reserve of share-based payments | L55: Revaluation surplus | M55: Statutory reserve | N55: Warrant reserve | O55: Other non-distributable reserves | P55: Sub-total of non-distributable reserves | Q55: Fair value reserve | R55: Reserve of non-current assets classified as held for sale | S55: Consolidation reserve | T55: Warranty reserve | U55: Other distributable reserves | V55: Sub-Total of distributable reserves | W55: Reserves | X55: Equity attributable to owners | Y55: Equity, others components | Z55: Non-controlling interests | AA55: Total
C56: #STDTENDTDATE# | E56: =TEXT(DATE(MID(E58,7,4),MID(E58,4,2),MID(E58,1,2)),"dd/MM/yyyy")&" - "&TEXT(DATE(MID(E59,7,4),MID(E59,4,2),MID(E59,1,2)),"dd/MM/yyyy") -> 01/01/2023 - 31/12/2023 | F56: =TEXT(DATE(MID(F58,7,4),MID(F58,4,2),MID(F58,1,2)),"dd/MM/yyyy")&" - "&TEXT(DATE(MID(F59,7,4),MID(F59,4,2),MID(F59,1,2)),"dd/MM/yyyy") -> 01/01/2023 - 31/12/2023 | G56: =TEXT(DATE(MID(G58,7,4),MID(G58,4,2),MID(G58,1,2)),"dd/MM/yyyy")&" - "&TEXT(DATE(MID(G59,7,4),MID(G59,4,2),MID(G59,1,2)),"dd/MM/yyyy") -> 01/01/2023 - 31/12/2023 | H56: =TEXT(DATE(MID(H58,7,4),MID(H58,4,2),MID(H58,1,2)),"dd/MM/yyyy")&" - "&TEXT(DATE(MID(H59,7,4),MID(H59,4,2),MID(H59,1,2)),"dd/MM/yyyy") -> 01/01/2023 - 31/12/2023 | I56: =TEXT(DATE(MID(I58,7,4),MID(I58,4,2),MID(I58,1,2)),"dd/MM/yyyy")&" - "&TEXT(DATE(MID(I59,7,4),MID(I59,4,2),MID(I59,1,2)),"dd/MM/yyyy") -> 01/01/2023 - 31/12/2023 | J56: =TEXT(DATE(MID(J58,7,4),MID(J58,4,2),MID(J58,1,2)),"dd/MM/yyyy")&" - "&TEXT(DATE(MID(J59,7,4),MID(J59,4,2),MID(J59,1,2)),"dd/MM/yyyy") -> 01/01/2023 - 31/12/2023 | K56: =TEXT(DATE(MID(K58,7,4),MID(K58,4,2),MID(K58,1,2)),"dd/MM/yyyy")&" - "&TEXT(DATE(MID(K59,7,4),MID(K59,4,2),MID(K59,1,2)),"dd/MM/yyyy") -> 01/01/2023 - 31/12/2023 | L56: =TEXT(DATE(MID(L58,7,4),MID(L58,4,2),MID(L58,1,2)),"dd/MM/yyyy")&" - "&TEXT(DATE(MID(L59,7,4),MID(L59,4,2),MID(L59,1,2)),"dd/MM/yyyy") -> 01/01/2023 - 31/12/2023 | ... AA56: =TEXT(DATE(MID(AA58,7,4),MID(AA58,4,2),MID(AA58,1,2)),"dd/MM/yyyy")&" - "&TEXT(DATE(MID(AA59,7,4),MID(AA59,4,2),MID(AA59,1,2)),"dd/MM/yyyy") -> 01/01/2023 - 31/12/2023
C57: #UNITSCALE# | E57: =StartUp!$E$8 -> MYR'000 | F57: =StartUp!$E$8 -> MYR'000 | G57: =StartUp!$E$8 -> MYR'000 | H57: =StartUp!$E$8 -> MYR'000 | I57: =StartUp!$E$8 -> MYR'000 | J57: =StartUp!$E$8 -> MYR'000 | K57: =StartUp!$E$8 -> MYR'000 | L57: =StartUp!$E$8 -> MYR'000 | ... AA57: =StartUp!$E$8 -> MYR'000
C58: #STDT# | E58: =StartUp!$D$10 -> 01/01/2023 | F58: =StartUp!$D$10 -> 01/01/2023 | G58: =StartUp!$D$10 -> 01/01/2023 | H58: =StartUp!$D$10 -> 01/01/2023 | I58: =StartUp!$D$10 -> 01/01/2023 | J58: =StartUp!$D$10 -> 01/01/2023 | K58: =StartUp!$D$10 -> 01/01/2023 | L58: =StartUp!$D$10 -> 01/01/2023 | ... AA58: =StartUp!$D$10 -> 01/01/2023
C59: #ENDT# | E59: =StartUp!$D$11 -> 31/12/2023 | F59: =StartUp!$D$11 -> 31/12/2023 | G59: =StartUp!$D$11 -> 31/12/2023 | H59: =StartUp!$D$11 -> 31/12/2023 | I59: =StartUp!$D$11 -> 31/12/2023 | J59: =StartUp!$D$11 -> 31/12/2023 | K59: =StartUp!$D$11 -> 31/12/2023 | L59: =StartUp!$D$11 -> 31/12/2023 | ... AA59: =StartUp!$D$11 -> 31/12/2023
C60: #TABLE#
A61: full_ifrs-cor_2022-03-24.xsd#ifrs-full_StatementOfChangesInEquityAbstract | D61: Statement of changes in equity
A62: full_ifrs-cor_2022-03-24.xsd#ifrs-full_StatementOfChangesInEquityLineItems | D62: Statement of changes in equity
A63: full_ifrs-cor_2022-03-24.xsd#ifrs-full_Equity@http://www.xbrl.org/2003/role/periodStartLabel | D63: *Equity at beginning of period
A64: ssmt-mfrs-cor_2022-12-31.xsd#ssmt-mfrs_ImpactOfChangeInAccountingStandards | D64: *Impact of changes in accounting policies
A65: ssmt-mfrs-cor_2022-12-31.xsd#ssmt-mfrs_EquityBalanceRestated@http://xbrl.ssm.com.my/role/ssm/fs/mfrs/lab_rol_ssmt-fs-mfrs_2022-12-31/ReportingPeriodStartLabel | D65: *Equity at beginning of period, restated | E65: =SOCIE!E63+SOCIE!E64 -> 0 | F65: =SOCIE!F63+SOCIE!F64 -> 0 | G65: =SOCIE!G63+SOCIE!G64 -> 0 | H65: =SOCIE!H63+SOCIE!H64 -> 0 | I65: =SOCIE!I63+SOCIE!I64 -> 0 | J65: =SOCIE!J63+SOCIE!J64 -> 0 | K65: =SOCIE!K63+SOCIE!K64 -> 0 | L65: =SOCIE!L63+SOCIE!L64 -> 0 | ... AA65: =SOCIE!AA63+SOCIE!AA64 -> 0
A66: full_ifrs-cor_2022-03-24.xsd#ifrs-full_ChangesInEquityAbstract | D66: Changes in equity
A67: full_ifrs-cor_2022-03-24.xsd#ifrs-full_ComprehensiveIncomeAbstract | D67: Comprehensive income
A68: full_ifrs-cor_2022-03-24.xsd#ifrs-full_ProfitLoss | D68: *Profit (loss)
A69: full_ifrs-cor_2022-03-24.xsd#ifrs-full_OtherComprehensiveIncome@http://www.xbrl.org/2003/role/totalLabel | D69: *Total other comprehensive income
A70: full_ifrs-cor_2022-03-24.xsd#ifrs-full_ComprehensiveIncome@http://www.xbrl.org/2003/role/totalLabel | D70: *Total comprehensive income | E70: =1*E68+1*E69 -> 0 | F70: =1*F68+1*F69 -> 0 | G70: =1*G68+1*G69 -> 0 | H70: =1*H68+1*H69 -> 0 | I70: =1*I68+1*I69 -> 0 | J70: =1*J68+1*J69 -> 0 | K70: =1*K68+1*K69 -> 0 | L70: =1*L68+1*L69 -> 0 | ... AA70: =1*AA68+1*AA69 -> 0
A71: ssmt-mfrs-cor_2022-12-31.xsd#ssmt-mfrs_ContributionsByAndDistributionsToOwnersAbstract | D71: Contributions by and distributions to owners
A72: full_ifrs-cor_2022-03-24.xsd#ifrs-full_IncreaseDecreaseThroughAcquisitionOfSubsidiary@http://xbrl.ssm.com.my/role/ssm/lab_rol_ssmt-fs-mfrs_2022-12-31/ReportingLabel | D72: Acquisition (dilution) of equity interest in subsidiaries
A73: full_ifrs-cor_2022-03-24.xsd#ifrs-full_IncreaseDecreaseThroughConversionOfConvertibleInstruments@http://xbrl.ssm.com.my/role/ssm/lab_rol_ssmt-fs-mfrs_2022-12-31/ReportingLabel | D73: Arising from conversion of Irredeemable Convertible Unsecured Loan Stock (ICULS)
A74: full_ifrs-cor_2022-03-24.xsd#ifrs-full_DividendsPaid@http://xbrl.ssm.com.my/role/ssm/lab_rol_ssmt-fs-mfrs_2022-12-31/ReportingLabel | D74: Dividends paid
A75: full_ifrs-cor_2022-03-24.xsd#ifrs-full_IssueOfEquity@http://xbrl.ssm.com.my/role/ssm/lab_rol_ssmt-fs-mfrs_2022-12-31/ReportingLabel | D75: Issuance of shares
A76: full_ifrs-cor_2022-03-24.xsd#ifrs-full_IssueOfConvertibleInstruments@http://xbrl.ssm.com.my/role/ssm/lab_rol_ssmt-fs-mfrs_2022-12-31/ReportingLabel | D76: Issue of convertible notes, net of tax
A77: full_ifrs-cor_2022-03-24.xsd#ifrs-full_IncreaseDecreaseThroughSharebasedPaymentTransactions | D77: Increase (decrease) through share-based payment transactions, equity
A78: full_ifrs-cor_2022-03-24.xsd#ifrs-full_IncreaseDecreaseThroughTreasuryShareTransactions@http://xbrl.ssm.com.my/role/ssm/lab_rol_ssmt-fs-mfrs_2022-12-31/ReportingLabel | D78: Treasury shares transactions
A79: full_ifrs-cor_2022-03-24.xsd#ifrs-full_IncreaseDecreaseThroughTransactionsWithOwners@http://xbrl.ssm.com.my/role/ssm/lab_rol_ssmt-fs-mfrs_2022-12-31/ReportingLabel | D79: Other transactions with owners
A80: full_ifrs-cor_2022-03-24.xsd#ifrs-full_IncreaseDecreaseThroughTransfersAndOtherChangesEquity | D80: Increase (decrease) through other changes, equity
A81: full_ifrs-cor_2022-03-24.xsd#ifrs-full_ChangesInEquity@http://www.xbrl.org/2003/role/totalLabel | D81: *Total increase (decrease) in equity | E81: =1*E70+1*E72+1*E73+-1*E74+1*E75+1*E76+1*E77+1*E78+1*E79+1*E80 -> 0 | F81: =1*F70+1*F72+1*F73+-1*F74+1*F75+1*F76+1*F77+1*F78+1*F79+1*F80 -> 0 | G81: =1*G70+1*G72+1*G73+-1*G74+1*G75+1*G76+1*G77+1*G78+1*G79+1*G80 -> 0 | H81: =1*H70+1*H72+1*H73+-1*H74+1*H75+1*H76+1*H77+1*H78+1*H79+1*H80 -> 0 | I81: =1*I70+1*I72+1*I73+-1*I74+1*I75+1*I76+1*I77+1*I78+1*I79+1*I80 -> 0 | J81: =1*J70+1*J72+1*J73+-1*J74+1*J75+1*J76+1*J77+1*J78+1*J79+1*J80 -> 0 | K81: =1*K70+1*K72+1*K73+-1*K74+1*K75+1*K76+1*K77+1*K78+1*K79+1*K80 -> 0 | L81: =1*L70+1*L72+1*L73+-1*L74+1*L75+1*L76+1*L77+1*L78+1*L79+1*L80 -> 0 | ... AA81: =1*AA70+1*AA72+1*AA73+-1*AA74+1*AA75+1*AA76+1*AA77+1*AA78+1*AA79+1*AA80 -> 0
A82: full_ifrs-cor_2022-03-24.xsd#ifrs-full_Equity@http://www.xbrl.org/2003/role/periodEndLabel | D82: *Equity at end of period | E82: =SOCIE!E65+SOCIE!E81 -> 0 | F82: =SOCIE!F65+SOCIE!F81 -> 0 | G82: =SOCIE!G65+SOCIE!G81 -> 0 | H82: =SOCIE!H65+SOCIE!H81 -> 0 | I82: =SOCIE!I65+SOCIE!I81 -> 0 | J82: =SOCIE!J65+SOCIE!J81 -> 0 | K82: =SOCIE!K65+SOCIE!K81 -> 0 | L82: =SOCIE!L65+SOCIE!L81 -> 0 | ... AA82: =SOCIE!AA65+SOCIE!AA81 -> 0
C83: #TABLE#
C84: #LAYOUTSCER# | AC84: #LAYOUTECER#

Sheet Notes-CI
A1: 5069e8ec-c0a1-46eb-94a0-64db788ac3d5:~:AtleastOneValueInAnyLayout:~:True:~:<?xml version="1.0" encoding="utf-16"?>_x000D_ <Customization xmlns:xsi="http://www.w3.org/2001/XMLSchema-instance" xmlns:xsd="http://www.w3.org/2001/XMLSchema" ComparitiveDate="False" LayoutByDate="False" LayoutByCompany="False" ShowAllDomains="False" TotalDomain="True" DefaultDates="1" />:~:http://xbrl.ssm.com.my/role/ssm/rol_ssmt-fs-mfrs_2022-12-31/ssmt-fs-mfrs_2022-12-31_role-710000:~:None
D2: FS-MFRS Notes - Corporate information
D3: * denotes mandatory items to be reported
C5: 662ab443-f8d8-452e-874f-2a6740e8439b:~:Notes-CI_1_TBLYT:~:NotMandatory:~:False:~:0:~:True:~:<?xml version="1.0" encoding="utf-16"?>_x000D_ <Customization xmlns:xsi="http://www.w3.org/2001/XMLSchema-instance" xmlns:xsd="http://www.w3.org/2001/XMLSchema" ComparitiveDate="False" LayoutByDate="False" LayoutByCompany="False" ShowAllDomains="False" TotalDomain="True" DefaultDates="1" />:~:LytTxb:~::~:False:~:True:~:ssmt-mfrs-cor_2022-12-31.xsd#ssmt-mfrs_DisclosureOnCorporateInformationAbstract@http://www.xbrl.org/2003/role/label:~:
C8: #LAYOUTSCSR# | D8: #PRIM# | F8: #TABLE# | G8: #LAYOUTECSR#
C9: #TABLE#
A10: ssmt-mfrs-cor_2022-12-31.xsd#ssmt-mfrs_DisclosureOnCorporateInformationAbstract | D10: Disclosure on corporate information
A11: ssmt-mfrs-cor_2022-12-31.xsd#ssmt-mfrs_CorporateInformationAbstract | D11: Corporate information
A12: ssmt-mfrs-cor_2022-12-31.xsd#ssmt-mfrs_DisclosureOfCorporateInformationExplanatory | D12: *Disclosure of corporate information
A13: ssmt-mfrs-cor_2022-12-31.xsd#ssmt-mfrs_FinancialReportingStatusAbstract | D13: Financial reporting status
A14: ssmt-mfrs-cor_2022-12-31.xsd#ssmt-mfrs_ExplanationOfReasonsForRestatementOfPreviousFinancialStatementsFiguresExplanatory | D14: Explanation of reasons for the restatement of previous financial statements figures
A15: ssmt-mfrs-cor_2022-12-31.xsd#ssmt-mfrs_ExplanationOfReasonsForReclassificationOfPreviousFinancialStatementsFiguresExplanatory | D15: Explanation of reasons for the reclassification of previous financial statements figures
A16: ssmt-mfrs-cor_2022-12-31.xsd#ssmt-mfrs_ExplanationOfReasonsForUsingLongerOrShorterReportingPeriodExplanatory | D16: Explanation of reasons for using longer or shorter reporting period
C17: #TABLE#
C18: #LAYOUTSCER# | G18: #LAYOUTECER#

Sheet Notes-SummaryofAccPol
A1: a90f1e21-7e3e-42dc-9704-2f963deabe82:~:AtleastOneValueInAnyLayout:~:True:~:<?xml version="1.0" encoding="utf-16"?>_x000D_ <Customization xmlns:xsi="http://www.w3.org/2001/XMLSchema-instance" xmlns:xsd="http://www.w3.org/2001/XMLSchema" ComparitiveDate="False" LayoutByDate="False" LayoutByCompany="False" ShowAllDomains="False" TotalDomain="True" DefaultDates="1" />:~:http://xbrl.ssm.com.my/role/ssm/rol_ssmt-fs-mfrs_2022-12-31/ssmt-fs-mfrs_2022-12-31_role-720000:~:None
D2: FS-MFRS Notes - Summary of material accounting policies
D3: * denotes mandatory items to be reported
C5: e490abaa-19a8-448a-ac8f-2c875e12833d:~:Notes-SummaryofAccPol_1_TBLYT:~:NotMandatory:~:False:~:0:~:True:~:<?xml version="1.0" encoding="utf-16"?>_x000D_ <Customization xmlns:xsi="http://www.w3.org/2001/XMLSchema-instance" xmlns:xsd="http://www.w3.org/2001/XMLSchema" ComparitiveDate="False" LayoutByDate="False" LayoutByCompany="False" ShowAllDomains="False" TotalDomain="True" DefaultDates="1" />:~:LytTxb:~::~:False:~:True:~:ssmt-cor_2022-12-31.xsd#ssmt_DisclosureOnSummaryOfMaterialAccountingPoliciesAbstract@http://www.xbrl.org/2003/role/label:~:
C8: #LAYOUTSCSR# | D8: #PRIM# | F8: #TABLE# | G8: #LAYOUTECSR#
C9: #TABLE#
A10: ssmt-cor_2022-12-31.xsd#ssmt_DisclosureOnSummaryOfMaterialAccountingPoliciesAbstract | D10: Disclosure on summary of material accounting policies
A11: full_ifrs-cor_2022-03-24.xsd#ifrs-full_DisclosureOfMaterialAccountingPolicyInformationExplanatory | D11: *Disclosure of material accounting policy information
A12: full_ifrs-cor_2022-03-24.xsd#ifrs-full_DescriptionOfAccountingPolicyForBiologicalAssetsExplanatory | D12: Description of accounting policy for biological assets
A13: full_ifrs-cor_2022-03-24.xsd#ifrs-full_DescriptionOfAccountingPolicyForBorrowingCostsExplanatory | D13: Description of accounting policy for borrowing costs
A14: full_ifrs-cor_2022-03-24.xsd#ifrs-full_DescriptionOfAccountingPolicyForBorrowingsExplanatory | D14: Description of accounting policy for borrowings
A15: full_ifrs-cor_2022-03-24.xsd#ifrs-full_DescriptionOfAccountingPolicyForBusinessCombinationsExplanatory | D15: Description of accounting policy for business combinations
A16: full_ifrs-cor_2022-03-24.xsd#ifrs-full_DescriptionOfAccountingPolicyForCashFlowsExplanatory@http://xbrl.ssm.com.my/role/ssm/lab_rol_ssmt-fs-mfrs_2022-12-31/ReportingLabel | D16: Description of accounting policy for cash and cash equivalents
A17: ssmt-mfrs-cor_2022-12-31.xsd#ssmt-mfrs_DescriptionOfAccountingPolicyForCommodityFutureAndForwardContractsExplanatory | D17: Description of accounting policy for commodity future and forward contracts
A18: ssmt-mfrs-cor_2022-12-31.xsd#ssmt-mfrs_DescriptionOfAccountingPolicyForConstructionContractExplanatory | D18: Description of accounting policy for construction contracts
A19: full_ifrs-cor_2022-03-24.xsd#ifrs-full_DescriptionOfAccountingPolicyForConstructionInProgressExplanatory | D19: Description of accounting policy for construction in progress
A20: full_ifrs-cor_2022-03-24.xsd#ifrs-full_DescriptionOfAccountingPolicyForContingentLiabilitiesAndContingentAssetsExplanatory | D20: Description of accounting policy for contingent liabilities and contingent assets
A21: full_ifrs-cor_2022-03-24.xsd#ifrs-full_DescriptionOfAccountingPolicyForCustomerLoyaltyProgrammesExplanatory | D21: Description of accounting policy for customer loyalty programmes
... A64: ssmt-mfrs-cor_2022-12-31.xsd#ssmt-mfrs_DescriptionOfAccountingPolicyForOtherSignificantAccountingPoliciesRelevantToUnderstandingOfFinancialStatementsExplanatory@http://xbrl.ssm.com.my/role/ssm/lab_rol_ssmt-fs-mfrs_2022-12-31/ReportingLabel | D64: Description of other material accounting policies relevant to understanding of financial statements
C65: #TABLE#
C66: #LAYOUTSCER# | G66: #LAYOUTECER#

Sheet Notes-Listofnotes
A1: db14f0c7-814d-4a6c-a41b-3a0a6beb4d4b:~:AtleastOneValueInAnyLayout:~:True:~:<?xml version="1.0" encoding="utf-16"?>_x000D_ <Customization xmlns:xsi="http://www.w3.org/2001/XMLSchema-instance" xmlns:xsd="http://www.w3.org/2001/XMLSchema" ComparitiveDate="False" LayoutByDate="False" LayoutByCompany="False" ShowAllDomains="False" TotalDomain="True" DefaultDates="1" />:~:http://xbrl.ssm.com.my/role/ssm/rol_ssmt-fs-mfrs_2022-12-31/ssmt-fs-mfrs_2022-12-31_role-730000:~:None
D2: FS-MFRS Notes - List of notes
D3: * denotes mandatory items to be reported
C5: e0cebb24-6153-4b96-b15e-e337c57b86b3:~:Notes-Listofnotes_1_TBLYT:~:NotMandatory:~:False:~:0:~:True:~:<?xml version="1.0" encoding="utf-16"?>_x000D_ <Customization xmlns:xsi="http://www.w3.org/2001/XMLSchema-instance" xmlns:xsd="http://www.w3.org/2001/XMLSchema" ComparitiveDate="False" LayoutByDate="False" LayoutByCompany="False" ShowAllDomains="False" TotalDomain="True" DefaultDates="1" />:~:LytTxb:~::~:False:~:True:~:ssmt-mfrs-cor_2022-12-31.xsd#ssmt-mfrs_DisclosureOfNotesAndOtherExplanatoryInformationAbstract@http://www.xbrl.org/2003/role/label:~:
C8: #LAYOUTSCSR# | D8: #PRIM# | F8: #TABLE# | G8: #LAYOUTECSR#
C9: #TABLE#
A10: ssmt-mfrs-cor_2022-12-31.xsd#ssmt-mfrs_DisclosureOfNotesAndOtherExplanatoryInformationAbstract | D10: Disclosure of notes and other explanatory information
A11: full_ifrs-cor_2022-03-24.xsd#ifrs-full_DisclosureOfAccruedExpensesAndOtherLiabilitiesExplanatory | D11: Disclosure of accrued expenses and other liabilities
A12: ssmt-mfrs-cor_2022-12-31.xsd#ssmt-mfrs_DisclosureOfAcquisitionsAndDisposalsExplanatory | D12: Disclosure of acquisitions and disposals
A13: full_ifrs-cor_2022-03-24.xsd#ifrs-full_DisclosureOfAllowanceForCreditLossesExplanatory | D13: Disclosure of allowance for credit losses
A14: ssmt-mfrs-cor_2022-12-31.xsd#ssmt-mfrs_DisclosureOfAmendmentsToMFRSandPronouncementsIssuedByMASBExplanatory | D14: Disclosure of amendments to MFRS and pronouncements issued by MASB
A15: full_ifrs-cor_2022-03-24.xsd#ifrs-full_DisclosureOfAuditorsRemunerationExplanatory | D15: Disclosure of auditors' remuneration
A16: full_ifrs-cor_2022-03-24.xsd#ifrs-full_DisclosureOfAuthorisationOfFinancialStatementsExplanatory | D16: Disclosure of authorisation of financial statements
A17: full_ifrs-cor_2022-03-24.xsd#ifrs-full_DisclosureOfBasisOfPreparationOfFinancialStatementsExplanatory | D17: Disclosure of basis of preparation of financial statements
A18: full_ifrs-cor_2022-03-24.xsd#ifrs-full_DisclosureOfBiologicalAssetsAndGovernmentGrantsForAgriculturalActivityExplanatory@http://xbrl.ssm.com.my/role/ssm/lab_rol_ssmt-fs-mfrs_2022-12-31/ReportingLabel | D18: Disclosure of biological assets
A19: ssmt-mfrs-cor_2022-12-31.xsd#ssmt-mfrs_DisclosureOfBondsExplanatory | D19: Disclosure of bonds
A20: full_ifrs-cor_2022-03-24.xsd#ifrs-full_DisclosureOfBorrowingsExplanatory | D20: Disclosure of borrowings
A21: full_ifrs-cor_2022-03-24.xsd#ifrs-full_DisclosureOfBusinessCombinationsExplanatory | D21: Disclosure of business combinations
... A148: full_ifrs-cor_2022-03-24.xsd#ifrs-full_DisclosureOfTreasurySharesExplanatory | D148: Disclosure of treasury shares
C149: #TABLE#
C150: #LAYOUTSCER# | G150: #LAYOUTECER#

Sheet Notes-Issuedcapital
A1: 428c7dea-9785-4935-b7d4-66083c5db0a9:~:AtleastOneValueInAnyLayout:~:True:~:<?xml version="1.0" encoding="utf-16"?>_x000D_ <Customization xmlns:xsi="http://www.w3.org/2001/XMLSchema-instance" xmlns:xsd="http://www.w3.org/2001/XMLSchema" ComparitiveDate="False" LayoutByDate="True" LayoutByCompany="True" ShowAllDomains="True" TotalDomain="True" DefaultDates="1" />:~:http://xbrl.ssm.com.my/role/ssm/rol_ssmt-fs-mfrs_2022-12-31/ssmt-fs-mfrs_2022-12-31_role-740000:~:None
D2: FS-MFRS Notes - Issued capital
D3: * denotes mandatory items to be reported
C5: adc201c8-3e3c-486f-bcc1-7c5c8dd15610:~:Notes-Issuedcapital_1_TBLYT:~:NotMandatory:~:False:~:0:~:True:~:<?xml version="1.0" encoding="utf-16"?>_x000D_ <Customization xmlns:xsi="http://www.w3.org/2001/XMLSchema-instance" xmlns:xsd="http://www.w3.org/2001/XMLSchema" ComparitiveDate="False" LayoutByDate="True" LayoutByCompany="True" ShowAllDomains="True" TotalDomain="True" DefaultDates="1" />:~:LytTxb:~::~:False:~:True:~:ssmt-mfrs-cor_2022-12-31.xsd#ssmt-mfrs_DisclosureOnIssuedCapitalAbstract@http://www.xbrl.org/2003/role/label:~:
C8: #LAYOUTSCSR# | D8: #PRIM# | F8: #TABLE# | G8: #LAYOUTECSR#
C9: #TABLE#
A10: ssmt-mfrs-cor_2022-12-31.xsd#ssmt-mfrs_DisclosureOnIssuedCapitalAbstract | D10: Disclosure on issued capital
A11: full_ifrs-cor_2022-03-24.xsd#ifrs-full_DisclosureOfClassesOfShareCapitalExplanatory | D11: *Disclosure of classes of share capital
C12: #TABLE#
C13: #LAYOUTSCER# | G13: #LAYOUTECER#
C16: a6d2b091-04ff-4588-a2d9-3dc5fc5fa988:~:Notes-Issuedcapital_2:~:NotMandatory:~:False:~:1:~:True:~:<?xml version="1.0" encoding="utf-16"?>_x000D_ <Customization xmlns:xsi="http://www.w3.org/2001/XMLSchema-instance" xmlns:xsd="http://www.w3.org/2001/XMLSchema" ComparitiveDate="False" LayoutByDate="True" LayoutByCompany="True" ShowAllDomains="True" TotalDomain="True" DefaultDates="1" />:~:LytHyc:~:full_ifrs-cor_2022-03-24.xsd#ifrs-full_DisclosureOfClassesOfShareCapitalTable:~:False:~:True:~:ssmt-mfrs-cor_2022-12-31.xsd#ssmt-mfrs_DisclosureOnIssuedCapitalAbstract@http://www.xbrl.org/2003/role/label::full_ifrs-cor_2022-03-24.xsd#ifrs-full_DisclosureOfClassesOfShareCapitalAbstract@http://www.xbrl.org/2003/role/label::full_ifrs-cor_2022-03-24.xsd#ifrs-full_DisclosureOfClassesOfShareCapitalLineItems@http://www.xbrl.org/2003/role/label:~:full_ifrs-cor_2022-03-24.xsd#ifrs-full_DisclosureOfClassesOfShareCapitalTable
E18: full_ifrs-cor_2022-03-24.xsd#ifrs-full_DisclosureOfClassesOfShareCapitalTable::full_ifrs-cor_2022-03-24.xsd#ifrs-full_ClassesOfShareCapitalAxis::full_ifrs-cor_2022-03-24.xsd#ifrs-full_OrdinarySharesMember | F18: full_ifrs-cor_2022-03-24.xsd#ifrs-full_DisclosureOfClassesOfShareCapitalTable::full_ifrs-cor_2022-03-24.xsd#ifrs-full_ClassesOfShareCapitalAxis::ssmt-mfrs-cor_2022-12-31.xsd#ssmt-mfrs_RedeemablePreferenceSharesMember | G18: full_ifrs-cor_2022-03-24.xsd#ifrs-full_DisclosureOfClassesOfShareCapitalTable::full_ifrs-cor_2022-03-24.xsd#ifrs-full_ClassesOfShareCapitalAxis::ssmt-mfrs-cor_2022-12-31.xsd#ssmt-mfrs_NonredeemablePreferenceSharesMember | H18: 0
C19: #LAYOUTSCSR# | D19: #PRIM# | I19: #TABLE# | J19: #LAYOUTECSR#
B20: full_ifrs-cor_2022-03-24.xsd#ifrs-full_DisclosureOfClassesOfShareCapitalTable::full_ifrs-cor_2022-03-24.xsd#ifrs-full_ClassesOfShareCapitalAxis | C20: #DOM# | D20: Edit Classes of share capital | E20: Ordinary shares | F20: Redeemable preference shares | G20: Non-redeemable preference shares | H20: Total
C21: #STDTENDTDATE# | E21: =TEXT(DATE(MID(E23,7,4),MID(E23,4,2),MID(E23,1,2)),"dd/MM/yyyy")&" - "&TEXT(DATE(MID(E24,7,4),MID(E24,4,2),MID(E24,1,2)),"dd/MM/yyyy") -> 01/01/2024 - 31/12/2024 | F21: =TEXT(DATE(MID(F23,7,4),MID(F23,4,2),MID(F23,1,2)),"dd/MM/yyyy")&" - "&TEXT(DATE(MID(F24,7,4),MID(F24,4,2),MID(F24,1,2)),"dd/MM/yyyy") -> 01/01/2024 - 31/12/2024 | G21: =TEXT(DATE(MID(G23,7,4),MID(G23,4,2),MID(G23,1,2)),"dd/MM/yyyy")&" - "&TEXT(DATE(MID(G24,7,4),MID(G24,4,2),MID(G24,1,2)),"dd/MM/yyyy") -> 01/01/2024 - 31/12/2024 | H21: =TEXT(DATE(MID(H23,7,4),MID(H23,4,2),MID(H23,1,2)),"dd/MM/yyyy")&" - "&TEXT(DATE(MID(H24,7,4),MID(H24,4,2),MID(H24,1,2)),"dd/MM/yyyy") -> 01/01/2024 - 31/12/2024
C22: #UNITSCALE# | E22: =StartUp!$E$8 -> MYR'000 | F22: =StartUp!$E$8 -> MYR'000 | G22: =StartUp!$E$8 -> MYR'000 | H22: =StartUp!$E$8 -> MYR'000
C23: #STDT# | E23: =StartUp!$D$8 -> 01/01/2024 | F23: =StartUp!$D$8 -> 01/01/2024 | G23: =StartUp!$D$8 -> 01/01/2024 | H23: =StartUp!$D$8 -> 01/01/2024
C24: #ENDT# | E24: =StartUp!$D$9 -> 31/12/2024 | F24: =StartUp!$D$9 -> 31/12/2024 | G24: =StartUp!$D$9 -> 31/12/2024 | H24: =StartUp!$D$9 -> 31/12/2024
C25: #TABLE#
A26: full_ifrs-cor_2022-03-24.xsd#ifrs-full_DisclosureOfClassesOfShareCapitalAbstract | D26: Disclosure of classes of share capital
A27: full_ifrs-cor_2022-03-24.xsd#ifrs-full_DisclosureOfClassesOfShareCapitalLineItems | D27: Disclosure of classes of share capital
A28: ssmt-mfrs-cor_2022-12-31.xsd#ssmt-mfrs_IssuedCapitalAbstract | D28: Issued capital
A29: ssmt-mfrs-cor_2022-12-31.xsd#ssmt-mfrs_SharesIssuedAndFullyPaidAbstract | D29: Shares issued and fully paid
A30: ssmt-mfrs-cor_2022-12-31.xsd#ssmt-mfrs_NumberOfSharessIssuedAndFullyPaidAbstract | D30: Number of shares issued and fully paid
A31: full_ifrs-cor_2022-03-24.xsd#ifrs-full_NumberOfSharesIssuedAndFullyPaid | D31: *Number of shares issued and fully paid
A32: ssmt-mfrs-cor_2022-12-31.xsd#ssmt-mfrs_OtherChangesInNumberOfSharesIssuedAndFullyPaid | D32: *Other changes in number of shares issued and fully paid
A33: ssmt-mfrs-cor_2022-12-31.xsd#ssmt-mfrs_AmountOfSharesIssuedAndFullyPaidAbstract | D33: Amount of shares issued and fully paid
A34: ssmt-mfrs-cor_2022-12-31.xsd#ssmt-mfrs_AmountOfSharesIssuedAndFullyPaidOutstanding@http://xbrl.ssm.com.my/role/ssm/fs/mfrs/lab_rol_ssmt-fs-mfrs_2022-12-31/ReportingPeriodStartLabel | D34: Balance at the beginning of period
A35: ssmt-mfrs-cor_2022-12-31.xsd#ssmt-mfrs_AmountOfSharesIssuedAndFullyPaidDuringPeriod@http://xbrl.ssm.com.my/role/ssm/lab_rol_ssmt-fs-mfrs_2022-12-31/ReportingLabel | D35: Shares issued during financial year
A36: ssmt-mfrs-cor_2022-12-31.xsd#ssmt-mfrs_AmountOfSharesIssuedForCashUnderESOS@http://xbrl.ssm.com.my/role/ssm/lab_rol_ssmt-fs-mfrs_2022-12-31/ReportingLabel | D36: Issued for cash under ESOS
A37: ssmt-mfrs-cor_2022-12-31.xsd#ssmt-mfrs_AmountOfSharesIssuedForCashUnderPrivatePlacement@http://xbrl.ssm.com.my/role/ssm/lab_rol_ssmt-fs-mfrs_2022-12-31/ReportingLabel | D37: Issued for cash under private placement
... A58: ssmt-mfrs-cor_2022-12-31.xsd#ssmt-mfrs_AmountOfSharesOutstanding@http://xbrl.ssm.com.my/role/ssm/fs/mfrs/lab_rol_ssmt-fs-mfrs_2022-12-31/ReportingPeriodEndLabel | D58: *Amount of shares outstanding at end of period
C59: #TABLE#
C60: #LAYOUTSCER# | J60: #LAYOUTECER#

Sheet Notes-RelatedPartytran
A1: 2e75cab3-4000-4835-bc53-354fa8a4860b:~:AtleastOneValueInAnyLayout:~:True:~:<?xml version="1.0" encoding="utf-16"?>_x000D_ <Customization xmlns:xsi="http://www.w3.org/2001/XMLSchema-instance" xmlns:xsd="http://www.w3.org/2001/XMLSchema" ComparitiveDate="False" LayoutByDate="True" LayoutByCompany="True" ShowAllDomains="True" TotalDomain="True" DefaultDates="1" />:~:http://xbrl.ssm.com.my/role/ssm/rol_ssmt-fs-mfrs_2022-12-31/ssmt-fs-mfrs_2022-12-31_role-750000:~:None
D2: FS-MFRS Notes - Related party transactions
D3: * denotes mandatory items to be reported
C5: 77e4b6cf-a856-4597-b6e2-6a7b717037f9:~:Notes-RelatedPartytran_1_TBLYT:~:NotMandatory:~:False:~:0:~:True:~:<?xml version="1.0" encoding="utf-16"?>_x000D_ <Customization xmlns:xsi="http://www.w3.org/2001/XMLSchema-instance" xmlns:xsd="http://www.w3.org/2001/XMLSchema" ComparitiveDate="False" LayoutByDate="True" LayoutByCompany="True" ShowAllDomains="True" TotalDomain="True" DefaultDates="1" />:~:LytTxb:~::~:False:~:True:~:ssmt-mfrs-cor_2022-12-31.xsd#ssmt-mfrs_DisclosureOnRelatedPartyTransactionsAbstract@http://www.xbrl.org/2003/role/label:~:
C8: #LAYOUTSCSR# | D8: #PRIM# | F8: #TABLE# | G8: #LAYOUTECSR#
C9: #TABLE#
A10: ssmt-mfrs-cor_2022-12-31.xsd#ssmt-mfrs_DisclosureOnRelatedPartyTransactionsAbstract | D10: Disclosure on related party transactions
A11: full_ifrs-cor_2022-03-24.xsd#ifrs-full_DisclosureOfTransactionsBetweenRelatedPartiesExplanatory | D11: *Disclosure of transactions between related parties
C12: #TABLE#
C13: #LAYOUTSCER# | G13: #LAYOUTECER#
C16: 42cc5ee6-efd5-48b6-a8a4-36b9dadeb1d9:~:Notes-RelatedPartytran_2:~:NotMandatory:~:False:~:1:~:True:~:<?xml version="1.0" encoding="utf-16"?>_x000D_ <Customization xmlns:xsi="http://www.w3.org/2001/XMLSchema-instance" xmlns:xsd="http://www.w3.org/2001/XMLSchema" ComparitiveDate="False" LayoutByDate="True" LayoutByCompany="True" ShowAllDomains="True" TotalDomain="True" DefaultDates="1" />:~:LytHyc:~:full_ifrs-cor_2022-03-24.xsd#ifrs-full_DisclosureOfTransactionsBetweenRelatedPartiesTable:~:False:~:True:~:ssmt-mfrs-cor_2022-12-31.xsd#ssmt-mfrs_DisclosureOnRelatedPartyTransactionsAbstract@http://www.xbrl.org/2003/role/label::full_ifrs-cor_2022-03-24.xsd#ifrs-full_DisclosureOfTransactionsBetweenRelatedPartiesAbstract@http://www.xbrl.org/2003/role/label::full_ifrs-cor_2022-03-24.xsd#ifrs-full_DisclosureOfTransactionsBetweenRelatedPartiesLineItems@http://www.xbrl.org/2003/role/label:~:full_ifrs-cor_2022-03-24.xsd#ifrs-full_DisclosureOfTransactionsBetweenRelatedPartiesTable
E18: full_ifrs-cor_2022-03-24.xsd#ifrs-full_DisclosureOfTransactionsBetweenRelatedPartiesTable::full_ifrs-cor_2022-03-24.xsd#ifrs-full_CategoriesOfRelatedPartiesAxis::full_ifrs-cor_2022-03-24.xsd#ifrs-full_ParentMember | F18: full_ifrs-cor_2022-03-24.xsd#ifrs-full_DisclosureOfTransactionsBetweenRelatedPartiesTable::full_ifrs-cor_2022-03-24.xsd#ifrs-full_CategoriesOfRelatedPartiesAxis::full_ifrs-cor_2022-03-24.xsd#ifrs-full_JointControlOrSignificantInfluenceMember | G18: full_ifrs-cor_2022-03-24.xsd#ifrs-full_DisclosureOfTransactionsBetweenRelatedPartiesTable::full_ifrs-cor_2022-03-24.xsd#ifrs-full_CategoriesOfRelatedPartiesAxis::full_ifrs-cor_2022-03-24.xsd#ifrs-full_SubsidiariesMember | H18: full_ifrs-cor_2022-03-24.xsd#ifrs-full_DisclosureOfTransactionsBetweenRelatedPartiesTable::full_ifrs-cor_2022-03-24.xsd#ifrs-full_CategoriesOfRelatedPartiesAxis::full_ifrs-cor_2022-03-24.xsd#ifrs-full_AssociatesMember | I18: full_ifrs-cor_2022-03-24.xsd#ifrs-full_DisclosureOfTransactionsBetweenRelatedPartiesTable::full_ifrs-cor_2022-03-24.xsd#ifrs-full_CategoriesOfRelatedPartiesAxis::full_ifrs-cor_2022-03-24.xsd#ifrs-full_JointVenturesWhereEntityIsVenturerMember | J18: full_ifrs-cor_2022-03-24.xsd#ifrs-full_DisclosureOfTransactionsBetweenRelatedPartiesTable::full_ifrs-cor_2022-03-24.xsd#ifrs-full_CategoriesOfRelatedPartiesAxis::full_ifrs-cor_2022-03-24.xsd#ifrs-full_KeyManagementPersonnelOfEntityOrParentMember | K18: full_ifrs-cor_2022-03-24.xsd#ifrs-full_DisclosureOfTransactionsBetweenRelatedPartiesTable::full_ifrs-cor_2022-03-24.xsd#ifrs-full_CategoriesOfRelatedPartiesAxis::full_ifrs-cor_2022-03-24.xsd#ifrs-full_OtherRelatedPartiesMember | L18: 0
C19: #LAYOUTSCSR# | D19: #PRIM# | M19: #TABLE# | N19: #LAYOUTECSR#
B20: full_ifrs-cor_2022-03-24.xsd#ifrs-full_DisclosureOfTransactionsBetweenRelatedPartiesTable::full_ifrs-cor_2022-03-24.xsd#ifrs-full_CategoriesOfRelatedPartiesAxis | C20: #DOM# | D20: Edit Categories of related parties | E20: Parent | F20: Entities with joint control or significant influence over entity | G20: Subsidiaries | H20: Associates | I20: Joint ventures where entity is venturer | J20: Key management personnel of entity or parent | K20: Other related parties | L20: Total
C21: #STDTENDTDATE# | E21: =TEXT(DATE(MID(E23,7,4),MID(E23,4,2),MID(E23,1,2)),"dd/MM/yyyy")&" - "&TEXT(DATE(MID(E24,7,4),MID(E24,4,2),MID(E24,1,2)),"dd/MM/yyyy") -> 01/01/2024 - 31/12/2024 | F21: =TEXT(DATE(MID(F23,7,4),MID(F23,4,2),MID(F23,1,2)),"dd/MM/yyyy")&" - "&TEXT(DATE(MID(F24,7,4),MID(F24,4,2),MID(F24,1,2)),"dd/MM/yyyy") -> 01/01/2024 - 31/12/2024 | G21: =TEXT(DATE(MID(G23,7,4),MID(G23,4,2),MID(G23,1,2)),"dd/MM/yyyy")&" - "&TEXT(DATE(MID(G24,7,4),MID(G24,4,2),MID(G24,1,2)),"dd/MM/yyyy") -> 01/01/2024 - 31/12/2024 | H21: =TEXT(DATE(MID(H23,7,4),MID(H23,4,2),MID(H23,1,2)),"dd/MM/yyyy")&" - "&TEXT(DATE(MID(H24,7,4),MID(H24,4,2),MID(H24,1,2)),"dd/MM/yyyy") -> 01/01/2024 - 31/12/2024 | I21: =TEXT(DATE(MID(I23,7,4),MID(I23,4,2),MID(I23,1,2)),"dd/MM/yyyy")&" - "&TEXT(DATE(MID(I24,7,4),MID(I24,4,2),MID(I24,1,2)),"dd/MM/yyyy") -> 01/01/2024 - 31/12/2024 | J21: =TEXT(DATE(MID(J23,7,4),MID(J23,4,2),MID(J23,1,2)),"dd/MM/yyyy")&" - "&TEXT(DATE(MID(J24,7,4),MID(J24,4,2),MID(J24,1,2)),"dd/MM/yyyy") -> 01/01/2024 - 31/12/2024 | K21: =TEXT(DATE(MID(K23,7,4),MID(K23,4,2),MID(K23,1,2)),"dd/MM/yyyy")&" - "&TEXT(DATE(MID(K24,7,4),MID(K24,4,2),MID(K24,1,2)),"dd/MM/yyyy") -> 01/01/2024 - 31/12/2024 | L21: =TEXT(DATE(MID(L23,7,4),MID(L23,4,2),MID(L23,1,2)),"dd/MM/yyyy")&" - "&TEXT(DATE(MID(L24,7,4),MID(L24,4,2),MID(L24,1,2)),"dd/MM/yyyy") -> 01/01/2024 - 31/12/2024
C22: #UNITSCALE# | E22: =StartUp!$E$8 -> MYR'000 | F22: =StartUp!$E$8 -> MYR'000 | G22: =StartUp!$E$8 -> MYR'000 | H22: =StartUp!$E$8 -> MYR'000 | I22: =StartUp!$E$8 -> MYR'000 | J22: =StartUp!$E$8 -> MYR'000 | K22: =StartUp!$E$8 -> MYR'000 | L22: =StartUp!$E$8 -> MYR'000
C23: #STDT# | E23: =StartUp!$D$8 -> 01/01/2024 | F23: =StartUp!$D$8 -> 01/01/2024 | G23: =StartUp!$D$8 -> 01/01/2024 | H23: =StartUp!$D$8 -> 01/01/2024 | I23: =StartUp!$D$8 -> 01/01/2024 | J23: =StartUp!$D$8 -> 01/01/2024 | K23: =StartUp!$D$8 -> 01/01/2024 | L23: =StartUp!$D$8 -> 01/01/2024
C24: #ENDT# | E24: =StartUp!$D$9 -> 31/12/2024 | F24: =StartUp!$D$9 -> 31/12/2024 | G24: =StartUp!$D$9 -> 31/12/2024 | H24: =StartUp!$D$9 -> 31/12/2024 | I24: =StartUp!$D$9 -> 31/12/2024 | J24: =StartUp!$D$9 -> 31/12/2024 | K24: =StartUp!$D$9 -> 31/12/2024 | L24: =StartUp!$D$9 -> 31/12/2024
C25: #TABLE#
A26: full_ifrs-cor_2022-03-24.xsd#ifrs-full_DisclosureOfTransactionsBetweenRelatedPartiesAbstract | D26: Disclosure of transactions between related parties
A27: full_ifrs-cor_2022-03-24.xsd#ifrs-full_DisclosureOfTransactionsBetweenRelatedPartiesLineItems | D27: Disclosure of transactions between related parties
A28: full_ifrs-cor_2022-03-24.xsd#ifrs-full_RelatedPartyTransactionsAbstract | D28: Related party transactions
A29: ssmt-mfrs-cor_2022-12-31.xsd#ssmt-mfrs_RelatedPartyTransactionsContributionToFund@http://xbrl.ssm.com.my/role/ssm/lab_rol_ssmt-fs-mfrs_2022-12-31/ReportingLabel | D29: Contribution to fund
A30: ssmt-mfrs-cor_2022-12-31.xsd#ssmt-mfrs_RelatedPartyTransactionsDisposalOfSubsidiaries@http://xbrl.ssm.com.my/role/ssm/lab_rol_ssmt-fs-mfrs_2022-12-31/ReportingLabel | D30: Disposal of subsidiaries
A31: ssmt-mfrs-cor_2022-12-31.xsd#ssmt-mfrs_DividendIncomeRelatedPartyTransactions@http://xbrl.ssm.com.my/role/ssm/lab_rol_ssmt-fs-mfrs_2022-12-31/ReportingLabel | D31: Dividend income
A32: ssmt-mfrs-cor_2022-12-31.xsd#ssmt-mfrs_InterestIncomeRelatedPartyTransactions@http://xbrl.ssm.com.my/role/ssm/lab_rol_ssmt-fs-mfrs_2022-12-31/ReportingLabel | D32: Interest income
A33: ssmt-mfrs-cor_2022-12-31.xsd#ssmt-mfrs_RelatedPartyTransactionsIssueOfSharesForExchangeableBonds@http://xbrl.ssm.com.my/role/ssm/lab_rol_ssmt-fs-mfrs_2022-12-31/ReportingLabel | D33: Issue of shares for exchangeable bonds
A34: full_ifrs-cor_2022-03-24.xsd#ifrs-full_KeyManagementPersonnelCompensation@http://xbrl.ssm.com.my/role/ssm/lab_rol_ssmt-fs-mfrs_2022-12-31/ReportingLabel | D34: Key management personnel
A35: ssmt-mfrs-cor_2022-12-31.xsd#ssmt-mfrs_RelatedPartyTransactionsKeyManagementPersonnelServiceFees@http://xbrl.ssm.com.my/role/ssm/lab_rol_ssmt-fs-mfrs_2022-12-31/ReportingLabel | D35: Key management personnel services fee
A36: ssmt-mfrs-cor_2022-12-31.xsd#ssmt-mfrs_RelatedPartyTransactionsManagementFees@http://xbrl.ssm.com.my/role/ssm/lab_rol_ssmt-fs-mfrs_2022-12-31/ReportingLabel | D36: Management fees
A37: ssmt-mfrs-cor_2022-12-31.xsd#ssmt-mfrs_OtherExpensesRecognisedForTransactionsWithRelatedParties | D37: Other expenses
... A60: ssmt-mfrs-cor_2022-12-31.xsd#ssmt-mfrs_OtherBalancesWithRelatedParties@http://xbrl.ssm.com.my/role/ssm/lab_rol_ssmt-fs-mfrs_2022-12-31/ReportingLabel | D60: *Other outstanding balances
C61: #TABLE#
C62: #LAYOUTSCER# | N62: #LAYOUTECER#

Sheet +Lineitems

Sheet StartUp
K1: ssmt-dei_NewCompanyRegistrationNumber | L1: 197501000529
K2: ssmt-dei_CompanyRegistrationNumber
K3: ssmt-dei_NameOfReportingEntity | L3: AMWAY (MALAYSIA) SDN BHD
K4: ssmt-dei_FormerNameOfCompany
K5: ssmt-dei_OriginOfCompany | L5: Incorporated in Malaysia
D6: Malaysian Ringgit (MYR) | E6: Malaysian Ringgit (MYR) | K6: ssmt-dei_StatusOfCompany | L6: Private company
D7: In thousands ('000') | E7: In thousands ('000') | K7: ssmt-dei_TypeOfCompany | L7: Company limited by shares
D8: 01/01/2024 | E8: MYR'000 | K8: ssmt-dei_ApplicationOfSubmission | L8: Ordinary filing
D9: 31/12/2024 | K9: ssmt-dei_StatutoryDeclarationForRectification
D10: 01/01/2023 | K10: ssmt-dei_CourtOrderReferenceNumber
D11: 31/12/2023 | K11: ssmt-dei_DisclosureOfFinancialStatementsPreparationForCurrentSubmission | L11: Subsequent preparation of financial statements
D12: 197501000529 | K12: ssmt-dei_CompanyCurrentFinancialYearStartDate | L12: 01/01/2024
K13: ssmt-dei_CompanyCurrentFinancialYearEndDate | L13: 31/12/2024
K14: ssmt-dei_CompanyPreviousFinancialYearStartDate | L14: 01/01/2023
K15: ssmt-dei_CompanyPreviousFinancialYearEndDate | L15: 31/12/2023
K16: ssmt-dei_StatusOfCarryingOnBusinessDuringFinancialYear | L16: Carrying on business activities
K17: ssmt-dei_DisclosureOfFinancialStatementsAuditStatus | L17: Audited
K18: ssmt-dei_AuditExemptionCategory
K19: ssmt-dei_BasisOfAccountingStandardsAppliedToPrepareFinancialStatements | L19: Malaysian Financial Reporting Standards
K20: ssmt-dei_DisclosureOfOtherAccountingStandardsApplied
K21: ssmt-dei_TypeOfSubmission | L21: FS-MFRS
K22: MPERS:ssmt-dei-ee-mpers_NatureOfFinancialStatements,MFRS:ssmt-dei-ee-mfrs_NatureOfFinancialStatements,FS1965:ssmt-dei-1965_NatureOfFinancialStatements | L22: Separate
K23: ssmt-dei-ee-mfrs_NatureOfFinancialStatements | L23: Separate
K24: ssmt-dei_DescriptionOfPresentationCurrency | L24: Malaysian Ringgit (MYR)
K25: ssmt-dei_DescriptionOfFunctionalCurrency
K26: ssmt-dei_LevelOfRoundingUsedInFinancialStatements | L26: In thousands ('000')
K27: ssmt-dei_NameAndVersionOfSoftwareUsedToGenerateXBRLFile | L27: MBRS_Preparation_Tool v2.2
K28: ssmt-dei_TaxonomyVersion | L28: SSMxT_2022v1.0
K29: ssmt_DisclosureOnWhetherCompanysSharesAreTradedOnAnyOfficialStockExchange | L29: Listed
K30: ssmt_DisclosureOfWhetherCompanyRegulatedByBankNegaraMalaysiaAtFinancialYearEnd | L30: Company not regulated by Bank Negara Malaysia
K31: ssmt_DescriptionOnWhetherCompanyHadAppliedForAnyExemptionWaiverReliefOrExtensionOfTimeWithRegardToAnnualReturnOrFinancialStatementsAndReportsFromRegistrarOrMinister | L31: No
K32: ssmt_MethodUsedForPreparingStatementOfFinancialPosition | L32: Current-Noncurrent
K33: ssmt_MethodUsedForPreparingStatementOfProfitOrLoss | L33: Function of expense
K34: ssmt_MethodUsedForPreparingStatementOfComprehensiveIncome | L34: Before tax
K35: ssmt_MethodUsedForRepresentingChangesInAnEntitysEquity
K36: ssmt_MethodUsedForPreparingStatementOfCashFlows | L36: Indirect
K37: ssmt_DisclosureOnWhetherComparativePeriodValuesAreRestated | L37: No
K38: TaxonomyVersion | L38: 1.0
K39: TaxonomyPath | L39: https/mbrs.ssm.com.my/taxonomy/SSMxT2022v1.0/rep/ssm/ca-2016/fs/mfrs/ssmt-fs-mfrs_2022-12-31_entry_point.xsd
K40: ToolLanguage | L40: en
K41: PackageName | L41: FS
K42: CreateTemplate | L42: 1
K43: IsImport | L43: 0

Sheet Data
O1: AF | Q1: SGD
O2: AX | Q2: USD
O3: AL | Q3: EUR
O4: DZ | Q4: JPY
O5: AS | Q5: CNY
O6: AD | Q6: GBP
O7: AO | Q7: MYR
O8: AI | Q8: AFN
O9: AQ | Q9: ALL
O10: AG | Q10: DZD
O11: AR | Q11: AOA
O12: AM | Q12: ARS
... O172: PG | Q172: ZWD
O173: PY
O174: PE
O175: PH
O176: PN
O177: PL
O178: PT
O179: PR
O180: QA
O181: RE
O182: RO
O183: RU
O184: RW
... O249: ZW

Sheet +FootnoteTexts0

Sheet +FootnoteTexts1

Sheet +FootnoteTexts2

Sheet +FootnoteTexts3

Sheet +FootnoteTexts4

Sheet +FootnoteTexts

Sheet +Elements

Sheet MainSheet
A1: <ProjectConfig>_x000D_ <add key="PackageName" value="Acra Financial Report" />_x000D_ <add key="PackageDescription" value="Acra financial report" />_x000D_ <add key="PackageAuthor" value="IRIS" />_x000D_ <add key="CreatedOn" value="" />_x000D_ <add key="PackageVersion" value="v1.0" />_x000D_ <add key="SecurityCode" value="C/80XPI8QeMTwtvtvxKnJxstnXJafZ3NalBUOFsU0T0=" />_x000D_ <add key="TaxonomyPath" value="C:\SSM XBRL Preparation Tool\Taxonomy\https\mbrs.ssm.com.my\taxonomy\SSMxT2022v1.0\rep\ssm\ca-2016\fs\mfrs\ssmt-fs-mfrs_2022-12-31_entry_point.xsd" />_x000D_ <add key="PublishPath" value="" />_x000D_ <add key="Culture" value="en-GB" />_x000D_ <add key="Scheme" value="" />_x000D_ <add key="ProjectMode" value="Package" />_x000D_ <add key="StartupSheet" value="Introduction" />_x000D_ <add key="VersionNo" value="2.2" />_x000D_ <add key="IsTriggered" value="false" />_x000D_ <add key="IsAnnexture" value="False" />_x000D_ <add key="AnnextureName" value="" />_x000D_ </ProjectConfig> | D1: #LEND# | F1: #SEND# | X1: 1 | Y1: SOPL-Function | Z1: {9D464D58-4FAD-4758-A826-6A433BFB4418}
A6: <PrefixNamespace>_x000D_ <add key="Prefix" value="cmp" />_x000D_ <add key="Namespace" value="" />_x000D_ <add key="Scheme" value="" />_x000D_ <add key="SchemaFileName" value="" />_x000D_ </PrefixNamespace>
A10: <GroupSheets> <Sheet GroupName="Finance" SheetName="Financial Pos Curr Non Curr" Name="[210000] Statement of financial position, current/non-current" color="1" DependantSelection=""/> <Sheet GroupName="Finance" SheetName="Financial Pos Ord of Liq" Name="[220000] Statement of financial position, order of liquidity" color="1" DependantSelection=""/> <Sheet GroupName="Income Statement" SheetName="Income Statement - Function" Name="[310000] Income statement, by function of expense" color="2" DependantSelection="[800210] Notes - Analysis of lncome and expense by function"/> <Sheet GroupName="Income Statement" SheetName="Income Statement - Nature" Name="[320000] Income statement, by nature of expense" color="2" DependantSelection="[800220] Notes - Analysis of lncome and expense by nature"/> <Sheet GroupName="Analysis of Income Statement" SheetName="Analysis of IS - Function" Name="[800210] Notes - Analysis of lncome and expense by function" color="3" DependantSelection=""/> <Sheet GroupName="Analysis of Income Statement" SheetName="Analysis of IS - Nature" Name="[800220] Notes - Analysis of lncome and expense by nature" color="3" DependantSelection=""/> <Sheet GroupName="SCI" SheetName="SCI - Net of Tax" Name="[410000] Statement of comprehensive income, OCI components presented net of tax" color="4" DependantSelection=""/> <Sheet GroupName="SCI" SheetName="SCI - before tax" Name="[420000] Statement of comprehensive income, OCI components presented before tax" color="4" DependantSelection=""/> <Sheet GroupName="Cash Flow" SheetName="Cash Flow - Direct" Name="[510000] Statement of cash flows, direct method" color="5" DependantSelection=""/> <Sheet GroupName="Cash Flow" SheetName="Cash Flow - Indirect" Name="[520000] Statement of cash flows, indirect method" color="5" DependantSelection=""/> </GroupSheets>
C17: ssmt-cor_2022-12-31.xsd#ssmt_AmountOfIndebtednessInForeignCurrency | D17: ssmt-cor_2022-12-31.xsd#ssmt_EquivalentAmountOfIndebtednessOfForeignCurrencyInLocalCurrency
C20: Amount of the indebtedness in foreign currency | D20: Equivalent amount of the indebtedness of foreign currency in MYR
