Workbook

Sheet SOPL-Nature
B1: 01/01/YYYY - 31/12/YYYY | C1: 01/01/YYYY - 31/12/YYYY | D1: Source
A3: Statement of profit or loss, by nature of expense
A4: Statement of Profit or Loss [abstract]
A5: Statement of profit or loss [line items]
A6: Continuing operations [abstract]
A7: Total revenue | B7: ='SOPL-Analysis-Nature'!B40 | C7: ='SOPL-Analysis-Nature'!C40
A8: Other income | B8: ='SOPL-Analysis-Nature'!B83 | C8: ='SOPL-Analysis-Nature'!C83
A9: Decrease (increase) in inventories of finished goods and work in progress
A10: Other work performed by entity and capitalised
A11: Raw materials and consumables used
A12: Total depreciation, amortisation and impairment loss (reversal of impairment loss) recognised in profit or loss
A13: Total employee benefits expense, by nature | B13: ='SOPL-Analysis-Nature'!B95 | C13: ='SOPL-Analysis-Nature'!C95
A14: Other expenses, by nature | B14: ='SOPL-Analysis-Nature'!B128 | C14: ='SOPL-Analysis-Nature'!C128
A15: Profit (loss) from operating activities | B15: =1*B7+1*B8+-1*B9+1*B10+-1*B11+-1*B12+-1*B13+-1*B14 | C15: =1*C7+1*C8+-1*C9+1*C10+-1*C11+-1*C12+-1*C13+-1*C14
A16: Finance income | B16: ='SOPL-Analysis-Nature'!B132 | C16: ='SOPL-Analysis-Nature'!C132
A17: Finance costs
A18: Total share of profit (loss) of associates and joint ventures accounted for using equity method
A19: Profit (loss) before tax | B19: =1*B7+1*B8+-1*B9+1*B10+-1*B11+-1*B12+-1*B13+-1*B14+1*B16+-1*B17+1*B18 | C19: =1*C7+1*C8+-1*C9+1*C10+-1*C11+-1*C12+-1*C13+-1*C14+1*C16+-1*C17+1*C18
A20: Total tax expense (income)
A21: Contribution of zakat
A22: Profit (loss) from continuing operations | B22: =1*B19+-1*B20+-1*B21 | C22: =1*C19+-1*C20+-1*C21
A23: Discontinued operations [abstract]
A24: Profit (loss) from discontinued operations
A25: Profit (loss) | B25: =1*B22+1*B24 | C25: =1*C22+1*C24
A26: Profit (loss), attributable to [abstract]
A27: Profit (loss), attributable to owners of parent
A28: Profit (loss) attributable to equity other components
A29: Profit (loss), attributable to non-controlling interests
A30: Profit (loss) | B30: =1*B27+1*B28+1*B29 | C30: =1*C27+1*C28+1*C29
A31: Earnings per share [abstract]
A32: Basic earnings per share [abstract]
A33: Basic earnings (loss) per share from continuing operations
A34: Basic earnings (loss) per share from discontinued operations
A35: Total basic earnings (loss) per share | B35: =1*B33+1*B34 | C35: =1*C33+1*C34
A36: Diluted earnings per share [abstract]
A37: Diluted earnings (loss) per share from continuing operations
A38: Diluted earnings (loss) per share from discontinued operations
A39: Total diluted earnings (loss) per share | B39: =1*B37+1*B38 | C39: =1*C37+1*C38

Sheet SOPL-Analysis-Nature
B1: 01/01/YYYY - 31/12/YYYY | C1: 01/01/YYYY - 31/12/YYYY | D1: Source
A3: Analysis of profit or loss, by nature of expense
A4: Analysis of profit or loss [abstract]
A5: Statement of profit or loss [line items]
A6: Revenue [abstract]
A7: Revenue from sale of goods [abstract]
A8: Revenue from sale of telecommunication equipment
A9: Revenue from sale of property
A10: Revenue from sale of construction contracts
A11: Revenue from sale of clean water, treatment and disposal of waste water
A12: Revenue from sale of food and beverage
A13: Revenue from sale of agricultural produce
A14: Revenue from sale of oil and gas products
A15: Revenue from sale of other goods
A16: Revenue from sale of goods | B16: =1*B8+1*B9+1*B10+1*B11+1*B12+1*B13+1*B14+1*B15 | C16: =1*C8+1*C9+1*C10+1*C11+1*C12+1*C13+1*C14+1*C15
A17: Revenue from rendering of services [abstract]
A18: Revenue from rendering of entertainment services
A19: Total revenue from rendering of telecommunication services
A20: Revenue from rendering of transport services
A21: Revenue from rendering of information technology services
A22: Revenue from rendering of educational services
A23: Revenue from rendering of healthcare services
A24: Revenue from rendering of cargo and mail transport services
A25: Revenue from rendering of other services
A26: Revenue from rendering of services | B26: =1*B18+1*B19+1*B20+1*B21+1*B22+1*B23+1*B24+1*B25 | C26: =1*C18+1*C19+1*C20+1*C21+1*C22+1*C23+1*C24+1*C25
A27: Interest income [abstract]
A28: Interest income on loans and receivables
A29: Interest income on other financial assets
A30: Interest income | B30: =1*B28+1*B29 | C30: =1*C28+1*C29
A31: Fee and commission income [abstract]
A32: Brokerage fee income
A33: Portfolio and other management fee income
A34: Other fee and commission income
A35: Total fee and commission income | B35: =1*B32+1*B33+1*B34 | C35: =1*C32+1*C33+1*C34
A36: Dividend income
A37: Rental income
A38: Royalty income
A39: Other revenue
A40: Total revenue | B40: =1*B16+1*B26+1*B30+1*B35+1*B36+1*B37+1*B38+1*B39 | C40: =1*C16+1*C26+1*C30+1*C35+1*C36+1*C37+1*C38+1*C39
A41: Other income [abstract]
A42: Deferred income
A43: Bad debts recovered
A44: Other income dividend
A45: Other income royalty and franchise
A46: Write back of fuel cost
A47: Income from reimbursements under insurance policies
A48: Grant or incentives by Malaysian government or it's agencies
A49: Grant or incentives by foreign government or it's agencies
A50: Contributions by local contributor
A51: Contributions by foreign contributor
A52: Contributions by unknown contributor
... A55: Unrealised gain on foreign exchange
A56: Gains on foreign exchange | B56: =1*B54+1*B55 | C56: =1*C54+1*C55
A57: Gain on disposal of subsidiaries, associates and joint ventures [abstract]
A58: Gain on disposal of subsidiaries
A59: Gain on disposal of associates
A60: Gain on disposal of joint ventures
A61: Gain from disposal of a subsidiary, joint ventures and associates | B61: =1*B58+1*B59+1*B60 | C61: =1*C58+1*C59+1*C60
A62: Gain on disposal from other investments
A63: Gains on disposals of property, plant and equipment
A64: Gains on disposals of non-current assets
A65: Other gains recognised in profit or loss, fair value measurement, assets
A66: Reversal of impairment loss recognised in profit or loss [abstract]
A67: Reversal of impairment loss recognised in profit or loss, loans and advances
A68: Reversal of impairment loss recognised in profit or loss, investment property
A69: Reversal of impairment in land held for development
A70: Reversal of impairment loss recognised in profit or loss, property, plant and equipment
A71: Reversal of impairment in other assets
A72: Reversal of impairment loss recognised in profit or loss | B72: =1*B67+1*B68+1*B69+1*B70+1*B71 | C72: =1*C67+1*C68+1*C69+1*C70+1*C71
A73: Reversal of inventory write-down
A74: Other interest income
A75: Income from management fees
A76: Net deposits recognised
A77: Gains on change in fair value of derivatives
A78: Fair value gain on recycle of forex reserve upon disposal of subsidiaries
A79: Other fees and commission income
A80: Other rental income
A81: Other rental income on land and buildings
A82: Miscellaneous other operating income
A83: Other income | B83: =1*B42+1*B43+1*B44+1*B45+1*B46+1*B47+1*B48+1*B49+1*B50+1*B51+1*B52+1*B56+1*B61+1*B62+1*B63+1*B64+1*B65+1*B72+1*B73+1*B74+1*B75+1*B76+1*B77+1*B78+1*B79+1*B80+1*B81+1*B82 | C83: =1*C42+1*C43+1*C44+1*C45+1*C46+1*C47+1*C48+1*C49+1*C50+1*C51+1*C52+1*C56+1*C61+1*C62+1*C63+1*C64+1*C65+1*C72+1*C73+1*C74+1*C75+1*C76+1*C77+1*C78+1*C79+1*C80+1*C81+1*C82
A84: Employee benefits expense [abstract]
A85: Wages and salaries
A86: Bonus
A87: Expense from share-based payment transactions with employees
A88: Employee share-based payment
A89: Social security contributions
A90: Total post-employment benefit expense in profit or loss, defined benefit plans
A91: Post-employment benefit expense, defined contribution plans
A92: Other long-term employee benefits
A93: Other short-term employee benefits
A94: Other employee expense
A95: Total employee benefits expense, by nature | B95: =1*B85+1*B86+1*B87+1*B88+1*B89+1*B90+1*B91+1*B92+1*B93+1*B94 | C95: =1*C85+1*C86+1*C87+1*C88+1*C89+1*C90+1*C91+1*C92+1*C93+1*C94
A96: Other expenses [abstract]
A97: Auditor's remuneration [abstract]
A98: Auditor's remuneration for audit services
A99: Auditor's remuneration for other services
A100: Total auditor's remuneration | B100: =1*B98+1*B99 | C100: =1*C98+1*C99
A101: Amortisation expense
A102: Depreciation, property, plant and equipment
A103: Natural disaster related expenses
...
