Workbook

Sheet SOFP-CuNonCu
B1: 01/01/YYYY - 31/12/YYYY | C1: 01/01/YYYY - 31/12/YYYY | D1: Source
A3: Disclosure on statement of financial position
A4: Statement of financial position
A5: Assets
A6: Non-current assets
A7: Property, plant and equipment | B7: ='SOFP-Sub-CuNonCu'!B26 | C7: ='SOFP-Sub-CuNonCu'!C26
A8: Investment properties | B8: ='SOFP-Sub-CuNonCu'!B36 | C8: ='SOFP-Sub-CuNonCu'!C36
A9: Right-of-use assets
A10: Intangible assets | B10: ='SOFP-Sub-CuNonCu'!B44 | C10: ='SOFP-Sub-CuNonCu'!C44
A11: Investment in subsidiaries | B11: ='SOFP-Sub-CuNonCu'!B49 | C11: ='SOFP-Sub-CuNonCu'!C49
A12: Investments in associates | B12: ='SOFP-Sub-CuNonCu'!B55 | C12: ='SOFP-Sub-CuNonCu'!C55
A13: Investments in joint ventures | B13: ='SOFP-Sub-CuNonCu'!B62 | C13: ='SOFP-Sub-CuNonCu'!C62
A14: Other investments
A15: Trade and other non-current receivables | B15: ='SOFP-Sub-CuNonCu'!B80 | C15: ='SOFP-Sub-CuNonCu'!C80
A16: Contract assets
A17: Deferred tax assets
A18: Other non-current assets | B18: ='SOFP-Sub-CuNonCu'!B85 | C18: ='SOFP-Sub-CuNonCu'!C85
A19: *Total non-current assets | B19: =1*B7+1*B8+1*B9+1*B10+1*B11+1*B12+1*B13+1*B14+1*B15+1*B16+1*B17+1*B18 | C19: =1*C7+1*C8+1*C9+1*C10+1*C11+1*C12+1*C13+1*C14+1*C15+1*C16+1*C17+1*C18
A20: Current assets
A21: Inventories | B21: ='SOFP-Sub-CuNonCu'!B92 | C21: ='SOFP-Sub-CuNonCu'!C92
A22: Other investments
A23: Current tax assets
A24: Trade and other current receivables | B24: ='SOFP-Sub-CuNonCu'!B117 | C24: ='SOFP-Sub-CuNonCu'!C117
A25: Contract assets
A26: Cash and cash equivalents | B26: ='SOFP-Sub-CuNonCu'!B131 | C26: ='SOFP-Sub-CuNonCu'!C131
A27: Other current assets
A28: Total current assets other than assets held for sale
A29: Assets or disposal group classified as held for sale or as held for distribution to owners
A30: *Total current assets | B30: =1*B21+1*B22+1*B23+1*B24+1*B25+1*B26+1*B27+1*B28+1*B29 | C30: =1*C21+1*C22+1*C23+1*C24+1*C25+1*C26+1*C27+1*C28+1*C29
A31: *Total assets | B31: =1*B19+1*B30 | C31: =1*C19+1*C30
A32: Fund/Equity and Liabilities
A33: Fund/Equity and reserves
A34: Accumulated funds (deficit)
A35: Contribution from members
A36: Reserves | B36: ='SOFP-Sub-CuNonCu'!B143 | C36: ='SOFP-Sub-CuNonCu'!C143
A37: *Total fund/equity and reserves attributable to owners | B37: =1*B34+1*B35+1*B36 | C37: =1*C34+1*C35+1*C36
A38: Non-controlling interests
A39: *Total fund/equity and reserve | B39: =1*B37+1*B38 | C39: =1*C37+1*C38
A40: Liabilities
A41: Non-current liabilities
A42: Borrowings | B42: ='SOFP-Sub-CuNonCu'!B158 | C42: ='SOFP-Sub-CuNonCu'!C158
A43: Lease liabilities
A44: Employee benefit liabilities
A45: Provisions
A46: Trade and other non-current payables | B46: ='SOFP-Sub-CuNonCu'!B177 | C46: ='SOFP-Sub-CuNonCu'!C177
A47: Contract liabilities
A48: Deferred tax liabilities
A49: Other non-current liabilities
A50: *Total non-current liabilities | B50: =1*B42+1*B43+1*B44+1*B45+1*B46+1*B47+1*B48+1*B49 | C50: =1*C42+1*C43+1*C44+1*C45+1*C46+1*C47+1*C48+1*C49
A51: Current liabilities
A52: Borrowings | B52: ='SOFP-Sub-CuNonCu'!B192 | C52: ='SOFP-Sub-CuNonCu'!C192
A53: Lease liabilities
A54: Employee benefit liabilities
A55: Provisions
A56: Current tax liabilities
A57: Trade and other current payables | B57: ='SOFP-Sub-CuNonCu'!B212 | C57: ='SOFP-Sub-CuNonCu'!C212
A58: Contract liabilities
A59: Other current liabilities
A60: *Total current liabilities other than liabilities held for sale | B60: =1*B52+1*B53+1*B54+1*B55+1*B56+1*B57+1*B58+1*B59 | C60: =1*C52+1*C53+1*C54+1*C55+1*C56+1*C57+1*C58+1*C59
A61: Liabilities included in disposal groups classified as held for sale
A62: *Total current liabilities | B62: =1*B60+1*B61 | C62: =1*C60+1*C61
A63: *Total liabilities | B63: =1*B50+1*B62 | C63: =1*C50+1*C62
A64: *Total fund/equity and liabilities | B64: =1*B39+1*B63 | C64: =1*C39+1*C63

Sheet SOFP-Sub-CuNonCu
B1: 01/01/YYYY - 31/12/YYYY | C1: 01/01/YYYY - 31/12/YYYY | D1: Source
A3: Disclosure on sub-classification of assets, liabilities and equity
A4: Statement on sub-classification of assets, liabilities and equity
A5: Sub-classification of assets, liabilities and equity
A6: Property, plant and equipment
A7: Land and buildings
A8: Land
A9: Freehold land
A10: Long term leasehold land
A11: Short term leasehold land
A12: *Total land | B12: =1*B9+1*B10+1*B11 | C12: =1*C9+1*C10+1*C11
A13: Buildings
A14: Building on freehold land
A15: Building on long term leasehold land
A16: Building on short term leasehold land
A17: Leased properties
A18: *Total buildings | B18: =1*B14+1*B15+1*B16+1*B17 | C18: =1*C14+1*C15+1*C16+1*C17
A19: *Total land and buildings | B19: =1*B12+1*B18 | C19: =1*C12+1*C18
A20: Vehicles
A21: Plant and equipment
A22: Office equipment, fixture and fittings
A23: Computer software and hardware
A24: Construction in progress/Asset work-in progress
A25: Other property, plant and equipment
A26: *Total property, plant and equipment | B26: =1*B19+1*B20+1*B21+1*B22+1*B23+1*B24+1*B25 | C26: =1*C19+1*C20+1*C21+1*C22+1*C23+1*C24+1*C25
A27: Investment property
A28: Investment properties completed, at carrying value
A29: Freehold land and building
A30: Leasehold land and building
A31: *Total investment properties completed, at carrying value | B31: =1*B29+1*B30 | C31: =1*C29+1*C30
A32: Investment properties under construction or development, at cost
A33: Building under construction
A34: *Total investment properties under construction or development, at cost | B34: =1*B33 | C34: =1*C33
A35: Other investment property
A36: *Total investment properties | B36: =1*B31+1*B34+1*B35 | C36: =1*C31+1*C34+1*C35
A37: Intangible assets and goodwill
A38: Intangible assets other than goodwill
A39: Copyrights, patents and other industrial property rights, service and operating rights
A40: Computer software
A41: Other intangible assets
A42: *Total intangible assets other than goodwill | B42: =1*B39+1*B40+1*B41 | C42: =1*C39+1*C40+1*C41
A43: Goodwill
A44: *Total intangible assets and goodwill | B44: =1*B42+1*B43 | C44: =1*C42+1*C43
A45: Investments in subsidiaries
A46: Unquoted shares, net of impairment losses
A47: Quoted shares
A48: Other investments in subsidiaries
A49: *Total investments in subsidiaries | B49: =1*B46+1*B47+1*B48 | C49: =1*C46+1*C47+1*C48
A50: Investments in associates
A51: Unquoted shares, net of impairment losses
A52: Quoted shares
A53: Share of post-acquisition profits and reserves
A54: Other investments in associates
A55: *Total investments in associates | B55: =1*B51+1*B52+1*B53+1*B54 | C55: =1*C51+1*C52+1*C53+1*C54
A56: Investments in joint ventures
A57: Unquoted shares, net of impairment losses
A58: Quoted shares
A59: Share of post-acquisition profits and reserves
A60: Unrealised profit on transactions with joint ventures
A61: Other investments in joint ventures
A62: *Total investments in joint ventures | B62: =1*B57+1*B58+1*B59+1*B60+1*B61 | C62: =1*C57+1*C58+1*C59+1*C60+1*C61
A63: Trade and other non-current receivables
A64: Non-current trade receivables
A65: Trade receivables
A66: Trade receivables due from related parties
A67: Other non-current trade receivables
A68: *Total non-current trade receivables | B68: =1*B65+1*B66+1*B67 | C68: =1*C65+1*C66+1*C67
A69: Other non-current receivables
A70: Other non-current receivables due from related parties
A71: Other receivables due from related parties
A72: Other receivables due from trustees
A73: *Total other non-current receivables due from related parties | B73: =1*B71+1*B72 | C73: =1*C71+1*C72
A74: Other non-current non-trade receivables
A75: Accrued income
A76: Lease and hire purchase receivables
A77: Miscellaneous other non-current non-trade receivables
A78: *Total other non-current non-trade receivables | B78: =1*B75+1*B76+1*B77 | C78: =1*C75+1*C76+1*C77
A79: *Total other non-current receivables | B79: =1*B73+1*B78 | C79: =1*C73+1*C78
A80: *Total trade and other non-current receivables | B80: =1*B68+1*B79 | C80: =1*C68+1*C79
A81: Other non-current assets
A82: Prepaid rental of buildings and facilities
A83: Prepaid land lease
A84: Other non-current assets
A85: *Total other non-current assets | B85: =1*B82+1*B83+1*B84 | C85: =1*C82+1*C83+1*C84
A86: Inventories
A87: Raw materials
A88: Work in progress
A89: Finished goods
A90: Spare parts
A91: Other inventories
A92: *Total inventories | B92: =1*B87+1*B88+1*B89+1*B90+1*B91 | C92: =1*C87+1*C88+1*C89+1*C90+1*C91
A93: Trade and other current receivables
A94: Current trade receivables
A95: Trade receivables
A96: Trade receivables due from related parties
A97: Other current trade receivables
A98: *Total current trade receivables | B98: =1*B95+1*B96+1*B97 | C98: =1*C95+1*C96+1*C97
A99: Other current receivables
A100: Current other receivables due from related parties
A101: Other receivables due from related parties
...
