Workbook

Sheet SOPL-Function
B1: 01/01/YYYY - 31/12/YYYY | C1: 01/01/YYYY - 31/12/YYYY | D1: Source
A3: Disclosure on statement of profit or loss | B3: ='SOPL-Analysis-Function'!B3 | C3: ='SOPL-Analysis-Function'!C3
A4: Analysis of profit or loss | B4: ='SOPL-Analysis-Function'!B4 | C4: ='SOPL-Analysis-Function'!C4
A5: Continuing operations
A6: Revenue | B6: ='SOPL-Analysis-Function'!B39 | C6: ='SOPL-Analysis-Function'!C39
A7: Cost of sales | B7: ='SOPL-Analysis-Function'!B46 | C7: ='SOPL-Analysis-Function'!C46
A8: *Gross profit | B8: =1*B6+-1*B7 | C8: =1*C6+-1*C7
A9: Other income | B9: ='SOPL-Analysis-Function'!B88 | C9: ='SOPL-Analysis-Function'!C88
A10: Selling and distribution expenses
A11: Administrative expenses
A12: Research and development expense
A13: Other expenses | B13: ='SOPL-Analysis-Function'!B135 | C13: ='SOPL-Analysis-Function'!C135
A14: *Profit (loss) from operating activities | B14: =1*B6+-1*B7+1*B9+-1*B10+-1*B11+-1*B12+-1*B13 | C14: =1*C6+-1*C7+1*C9+-1*C10+-1*C11+-1*C12+-1*C13
A15: Finance income | B15: ='SOPL-Analysis-Function'!B139 | C15: ='SOPL-Analysis-Function'!C139
A16: Finance costs
A17: Share of profit (loss) of associates and joint ventures accounted for using equity method
A18: *Profit (loss) before tax | B18: =1*B6+-1*B7+1*B9+-1*B10+-1*B11+-1*B12+-1*B13+1*B15+-1*B16+1*B17 | C18: =1*C6+-1*C7+1*C9+-1*C10+-1*C11+-1*C12+-1*C13+1*C15+-1*C16+1*C17
A19: Tax expense
A20: Contribution to zakat
A21: *Profit (loss) from continuing operations, net | B21: =1*B18+-1*B19+-1*B20 | C21: =1*C18+-1*C19+-1*C20
A22: Discontinued operations
A23: Profit (loss) before tax, from discontinued operation
A24: *Profit (loss) | B24: =1*B21+1*B23 | C24: =1*C21+1*C23
A25: Profit (loss), attributable to
A26: Profit (loss), attributable to owners of parent
A27: Profit (loss), attributable to equity other components
A28: Profit (loss), attributable to non-controlling interests
A29: *Total Profit (Loss) | B29: =1*B26+1*B27+1*B28 | C29: =1*C26+1*C27+1*C28

Sheet SOPL-Analysis-Function
B1: 01/01/YYYY - 31/12/YYYY | C1: 01/01/YYYY - 31/12/YYYY | D1: Source
A3: Disclosure on statement of profit or loss
A4: Analysis of profit or loss
A5: Revenue
A6: Revenue from sale of goods
A7: Revenue from sale of broadband and telecommunication
A8: Revenue from property development
A9: Revenue from construction contracts
A10: Revenue from sale of clean water, treatment and disposal of waste water
A11: Revenue from sale of food and beverage
A12: Revenue from sale of agricultural produce
A13: Revenue from sale of oil and gas products
A14: Other revenue from sale of goods
A15: *Total revenue from sale of goods | B15: =1*B7+1*B8+1*B9+1*B10+1*B11+1*B12+1*B13+1*B14 | C15: =1*C7+1*C8+1*C9+1*C10+1*C11+1*C12+1*C13+1*C14
A16: Revenue from rendering of services
A17: Income from entertainment operations
A18: Revenue from rendering of telecommunication services
A19: Revenue from rendering of transportation services
A20: Revenue from rendering of information technology services
A21: Education services income
A22: Healthcare services income
A23: Revenue from rendering of shipping and shipping related services
A24: Other revenue from rendering of services
A25: *Total revenue from rendering of services | B25: =1*B17+1*B18+1*B19+1*B20+1*B21+1*B22+1*B23+1*B24 | C25: =1*C17+1*C18+1*C19+1*C20+1*C21+1*C22+1*C23+1*C24
A26: Interest income
A27: Interest income on loans, advances and financing
A28: Interest income on other financial assets
A29: *Total interest income | B29: =1*B27+1*B28 | C29: =1*C27+1*C28
A30: Other fee and commission income
A31: Gross brokerage and other charges
A32: Underwriting commissions and fund management income
A33: Other fee and commission
A34: *Total other fee and commission income | B34: =1*B31+1*B32+1*B33 | C34: =1*C31+1*C32+1*C33
A35: Dividend income
A36: Rental income
A37: Royalty income
A38: Other revenue
A39: *Total revenue | B39: =1*B15+1*B25+1*B29+1*B34+1*B35+1*B36+1*B37+1*B38 | C39: =1*C15+1*C25+1*C29+1*C34+1*C35+1*C36+1*C37+1*C38
A40: Cost of sales
A41: Cost of inventories
A42: Construction contract costs
A43: Energy costs
A44: Property development costs
A45: Other cost of sales
A46: *Total cost of sales | B46: =1*B41+1*B42+1*B43+1*B44+1*B45 | C46: =1*C41+1*C42+1*C43+1*C44+1*C45
A47: Other income
A48: Deferred income
A49: Bad debts recovered
A50: Dividend, other income
A51: Foreign exchange gain
A52: Realised foreign currencies exchange gain transferred from equity
A53: Unrealised gain on foreign exchange
A54: *Total foreign exchange gain | B54: =1*B52+1*B53 | C54: =1*C52+1*C53
A55: Gain on disposal of subsidiaries, associates and joint ventures
A56: Gain on disposal of subsidiaries
A57: Gain on disposal of associates
A58: Gain on disposal of joint ventures
A59: *Total gain on disposal of subsidiaries, associates and joint ventures | B59: =1*B56+1*B57+1*B58 | C59: =1*C56+1*C57+1*C58
A60: Gain on disposal from other investments
A61: Gain on disposals of property, plant and equipment
A62: Gains on disposal of other non-current assets
A63: Gain on revaluation
A64: Interest income
A65: Management fees, other income
A66: Net fair value gain on derivatives
A67: Net fair value gain on recycle of forex reserve upon disposal of subsidiaries
A68: Other fee and commission, other income
A69: Other rental income
A70: Rental income on land and buildings
A71: Reversal of impairment loss recognised in profit or loss
... A79: Reversal of impairment loss on other assets
A80: *Total reversal of impairment loss recognised in profit or loss | B80: =1*B72+1*B73+1*B74+1*B76+1*B77+1*B78+1*B79+1*B75 | C80: =1*C72+1*C73+1*C74+1*C76+1*C77+1*C78+1*C79+1*C75
A81: Royalty/franchise income
A82: Grant or incentives by Malaysian government or it's agencies
A83: Grant or incentives by foreign government or it's agencies
A84: Contributions or donations by local contributor
A85: Contributions or donations by foreign contributor
A86: Contributions or donations by unknown contributor
A87: Miscellaneous other operating income
A88: *Total other income | B88: =1*B48+1*B49+1*B50+1*B54+1*B59+1*B60+1*B61+1*B62+1*B63+1*B64+1*B65+1*B68+1*B69+1*B70+1*B80+1*B81+1*B82+1*B83+1*B84+1*B85+1*B86+1*B87+1*B66+1*B67 | C88: =1*C48+1*C49+1*C50+1*C54+1*C59+1*C60+1*C61+1*C62+1*C63+1*C64+1*C65+1*C68+1*C69+1*C70+1*C80+1*C81+1*C82+1*C83+1*C84+1*C85+1*C86+1*C87+1*C66+1*C67
A89: Other expenses
A90: Auditor's remuneration
A91: Auditor's remuneration for audit services
A92: Auditor's remuneration for other services
A93: *Total auditor's remuneration | B93: =1*B91+1*B92 | C93: =1*C91+1*C92
A94: Amortisation expense
A95: Depreciation of property, plant and equipment
A96: Natural disaster related expenses
A97: Loss on disposal of subsidiaries, associates and joint ventures
A98: Loss on disposal of subsidiaries
A99: Loss on disposal of associates
A100: Loss on disposal of joint ventures
A101: *Total loss on disposal of subsidiaries, associates and joint ventures | B101: =1*B98+1*B99+1*B100 | C101: =1*C98+1*C99+1*C100
A102: Loss on disposal from other investments
A103: Loss on disposal of property, plant and equipment
A104: Loss on disposal of other non-current assets
A105: Loss on revaluation
A106: Provision for liabilities and charges
A107: Provision of warranties and guarantees
A108: Rental expenses
...
