Workbook

Sheet SOFP-CuNonCu
B1: Group | D1: Company | F1: Source
B2: 01/01/YYYY - 31/12/YYYY | C2: 01/01/YYYY - 31/12/YYYY | D2: 01/01/YYYY - 31/12/YYYY | E2: 01/01/YYYY - 31/12/YYYY
A3: Disclosure on statement of financial position
A4: Statement of financial position
A5: Assets
A6: Non-current assets
A7: Property, plant and equipment | B7: ='SOFP-Sub-CuNonCu'!B26 | C7: ='SOFP-Sub-CuNonCu'!C26 | D7: ='SOFP-Sub-CuNonCu'!D26 | E7: ='SOFP-Sub-CuNonCu'!E26
A8: Investment properties | B8: ='SOFP-Sub-CuNonCu'!B33 | C8: ='SOFP-Sub-CuNonCu'!C33 | D8: ='SOFP-Sub-CuNonCu'!D33 | E8: ='SOFP-Sub-CuNonCu'!E33
A9: Biological assets
A10: Intangible assets | B10: ='SOFP-Sub-CuNonCu'!B40 | C10: ='SOFP-Sub-CuNonCu'!C40 | D10: ='SOFP-Sub-CuNonCu'!D40 | E10: ='SOFP-Sub-CuNonCu'!E40
A11: Investments in subsidiaries | B11: ='SOFP-Sub-CuNonCu'!B46 | C11: ='SOFP-Sub-CuNonCu'!C46 | D11: ='SOFP-Sub-CuNonCu'!D46 | E11: ='SOFP-Sub-CuNonCu'!E46
A12: Investments in associates | B12: ='SOFP-Sub-CuNonCu'!B53 | C12: ='SOFP-Sub-CuNonCu'!C53 | D12: ='SOFP-Sub-CuNonCu'!D53 | E12: ='SOFP-Sub-CuNonCu'!E53
A13: Investments in joint ventures | B13: ='SOFP-Sub-CuNonCu'!B60 | C13: ='SOFP-Sub-CuNonCu'!C60 | D13: ='SOFP-Sub-CuNonCu'!D60 | E13: ='SOFP-Sub-CuNonCu'!E60
A14: Other investments
A15: Trade and other non-current receivables | B15: ='SOFP-Sub-CuNonCu'!B84 | C15: ='SOFP-Sub-CuNonCu'!C84 | D15: ='SOFP-Sub-CuNonCu'!D84 | E15: ='SOFP-Sub-CuNonCu'!E84
A16: Deferred tax assets
A17: Other non-current assets
A18: *Total non-current assets | B18: =1*B7+1*B8+1*B9+1*B10+1*B11+1*B12+1*B13+1*B14+1*B15+1*B16+1*B17 | C18: =1*C7+1*C8+1*C9+1*C10+1*C11+1*C12+1*C13+1*C14+1*C15+1*C16+1*C17 | D18: =1*D7+1*D8+1*D9+1*D10+1*D11+1*D12+1*D13+1*D14+1*D15+1*D16+1*D17 | E18: =1*E7+1*E8+1*E9+1*E10+1*E11+1*E12+1*E13+1*E14+1*E15+1*E16+1*E17
A19: Current assets
A20: Inventories | B20: ='SOFP-Sub-CuNonCu'!B91 | C20: ='SOFP-Sub-CuNonCu'!C91 | D20: ='SOFP-Sub-CuNonCu'!D91 | E20: ='SOFP-Sub-CuNonCu'!E91
A21: Biological assets
A22: Other investments
A23: Trade and other current receivables | B23: ='SOFP-Sub-CuNonCu'!B122 | C23: ='SOFP-Sub-CuNonCu'!C122 | D23: ='SOFP-Sub-CuNonCu'!D122 | E23: ='SOFP-Sub-CuNonCu'!E122
A24: Current tax assets
A25: Derivative financial assets
A26: Cash and cash equivalents | B26: ='SOFP-Sub-CuNonCu'!B138 | C26: ='SOFP-Sub-CuNonCu'!C138 | D26: ='SOFP-Sub-CuNonCu'!D138 | E26: ='SOFP-Sub-CuNonCu'!E138
A27: Other current assets
A28: *Total current assets | B28: =1*B20+1*B21+1*B22+1*B23+1*B24+1*B25+1*B26+1*B27 | C28: =1*C20+1*C21+1*C22+1*C23+1*C24+1*C25+1*C26+1*C27 | D28: =1*D20+1*D21+1*D22+1*D23+1*D24+1*D25+1*D26+1*D27 | E28: =1*E20+1*E21+1*E22+1*E23+1*E24+1*E25+1*E26+1*E27
A29: *Total assets | B29: =1*B7+1*B8+1*B11+1*B12+1*B13+1*B14+1*B15+1*B16+1*B17+1*B20+1*B22+1*B23+1*B24+1*B25+1*B26+1*B27+1*B10+1*B9+1*B21 | C29: =1*C7+1*C8+1*C11+1*C12+1*C13+1*C14+1*C15+1*C16+1*C17+1*C20+1*C22+1*C23+1*C24+1*C25+1*C26+1*C27+1*C10+1*C9+1*C21 | D29: =1*D7+1*D8+1*D11+1*D12+1*D13+1*D14+1*D15+1*D16+1*D17+1*D20+1*D22+1*D23+1*D24+1*D25+1*D26+1*D27+1*D10+1*D9+1*D21 | E29: =1*E7+1*E8+1*E11+1*E12+1*E13+1*E14+1*E15+1*E16+1*E17+1*E20+1*E22+1*E23+1*E24+1*E25+1*E26+1*E27+1*E10+1*E9+1*E21
A30: Equity and liabilities
A31: Equity
A32: Issued capital | B32: ='SOFP-Sub-CuNonCu'!B143 | C32: ='SOFP-Sub-CuNonCu'!C143 | D32: ='SOFP-Sub-CuNonCu'!D143 | E32: ='SOFP-Sub-CuNonCu'!E143
A33: Retained earnings
A34: Treasury shares
A35: Reserves | B35: ='SOFP-Sub-CuNonCu'!B154 | C35: ='SOFP-Sub-CuNonCu'!C154 | D35: ='SOFP-Sub-CuNonCu'!D154 | E35: ='SOFP-Sub-CuNonCu'!E154
A36: *Total equity attributable to owners | B36: =1*B32+1*B33+-1*B34+1*B35 | C36: =1*C32+1*C33+-1*C34+1*C35 | D36: =1*D32+1*D33+-1*D34+1*D35 | E36: =1*E32+1*E33+-1*E34+1*E35
A37: Equity - other components | B37: ='SOFP-Sub-CuNonCu'!B160 | C37: ='SOFP-Sub-CuNonCu'!C160 | D37: ='SOFP-Sub-CuNonCu'!D160 | E37: ='SOFP-Sub-CuNonCu'!E160
A38: Non-controlling interests
A39: *Total equity | B39: =1*B32+1*B33+-1*B34+1*B35+1*B37+1*B38 | C39: =1*C32+1*C33+-1*C34+1*C35+1*C37+1*C38 | D39: =1*D32+1*D33+-1*D34+1*D35+1*D37+1*D38 | E39: =1*E32+1*E33+-1*E34+1*E35+1*E37+1*E38
A40: Liabilities
A41: Non-current liabilities
A42: Loans and borrowings | B42: ='SOFP-Sub-CuNonCu'!B176 | C42: ='SOFP-Sub-CuNonCu'!C176 | D42: ='SOFP-Sub-CuNonCu'!D176 | E42: ='SOFP-Sub-CuNonCu'!E176
A43: Employee benefits | B43: ='SOFP-Sub-CuNonCu'!B184 | C43: ='SOFP-Sub-CuNonCu'!C184 | D43: ='SOFP-Sub-CuNonCu'!D184 | E43: ='SOFP-Sub-CuNonCu'!E184
A44: Provisions | B44: ='SOFP-Sub-CuNonCu'!B192 | C44: ='SOFP-Sub-CuNonCu'!C192 | D44: ='SOFP-Sub-CuNonCu'!D192 | E44: ='SOFP-Sub-CuNonCu'!E192
A45: Deferred tax liabilities
A46: Trade and other non-current payables | B46: ='SOFP-Sub-CuNonCu'!B217 | C46: ='SOFP-Sub-CuNonCu'!C217 | D46: ='SOFP-Sub-CuNonCu'!D217 | E46: ='SOFP-Sub-CuNonCu'!E217
A47: Other non-current liabilities
A48: *Total non-current liabilities | B48: =1*B42+1*B43+1*B44+1*B45+1*B46+1*B47 | C48: =1*C42+1*C43+1*C44+1*C45+1*C46+1*C47 | D48: =1*D42+1*D43+1*D44+1*D45+1*D46+1*D47 | E48: =1*E42+1*E43+1*E44+1*E45+1*E46+1*E47
A49: Current liabilities
A50: Loans and borrowings | B50: ='SOFP-Sub-CuNonCu'!B235 | C50: ='SOFP-Sub-CuNonCu'!C235 | D50: ='SOFP-Sub-CuNonCu'!D235 | E50: ='SOFP-Sub-CuNonCu'!E235
A51: Employee benefits | B51: ='SOFP-Sub-CuNonCu'!B243 | C51: ='SOFP-Sub-CuNonCu'!C243 | D51: ='SOFP-Sub-CuNonCu'!D243 | E51: ='SOFP-Sub-CuNonCu'!E243
A52: Provisions | B52: ='SOFP-Sub-CuNonCu'!B251 | C52: ='SOFP-Sub-CuNonCu'!C251 | D52: ='SOFP-Sub-CuNonCu'!D251 | E52: ='SOFP-Sub-CuNonCu'!E251
A53: Trade and other current payables | B53: ='SOFP-Sub-CuNonCu'!B277 | C53: ='SOFP-Sub-CuNonCu'!C277 | D53: ='SOFP-Sub-CuNonCu'!D277 | E53: ='SOFP-Sub-CuNonCu'!E277
A54: Current tax liabilities
A55: Derivative financial liabilities
A56: Other current liabilities
A57: *Total current liabilities | B57: =1*B50+1*B51+1*B52+1*B53+1*B54+1*B55+1*B56 | C57: =1*C50+1*C51+1*C52+1*C53+1*C54+1*C55+1*C56 | D57: =1*D50+1*D51+1*D52+1*D53+1*D54+1*D55+1*D56 | E57: =1*E50+1*E51+1*E52+1*E53+1*E54+1*E55+1*E56
A58: *Total liabilities | B58: =1*B50+1*B51+1*B52+1*B53+1*B54+1*B55+1*B56+1*B42+1*B43+1*B44+1*B45+1*B46+1*B47 | C58: =1*C50+1*C51+1*C52+1*C53+1*C54+1*C55+1*C56+1*C42+1*C43+1*C44+1*C45+1*C46+1*C47 | D58: =1*D50+1*D51+1*D52+1*D53+1*D54+1*D55+1*D56+1*D42+1*D43+1*D44+1*D45+1*D46+1*D47 | E58: =1*E50+1*E51+1*E52+1*E53+1*E54+1*E55+1*E56+1*E42+1*E43+1*E44+1*E45+1*E46+1*E47
A59: *Total equity and liabilities | B59: =1*B39+1*B58 | C59: =1*C39+1*C58 | D59: =1*D39+1*D58 | E59: =1*E39+1*E58

Sheet SOFP-Sub-CuNonCu
B1: Group | D1: Company | F1: Source
B2: 01/01/YYYY - 31/12/YYYY | C2: 01/01/YYYY - 31/12/YYYY | D2: 01/01/YYYY - 31/12/YYYY | E2: 01/01/YYYY - 31/12/YYYY
A3: Disclosure on sub-classification of assets, liabilities and equity
A4: Statement on sub-classification of assets, liabilities and equity
A5: Sub-classification of assets, liabilities and equity
A6: Property, plant and equipment
A7: Land and buildings
A8: Land
A9: Freehold land
A10: Long term leasehold land | B10: 12420 | C10: 12688 | D10: 12420 | E10: 12688
A11: Short term leasehold land
A12: *Total land | B12: =1*B9+1*B10+1*B11 | C12: =1*C9+1*C10+1*C11 | D12: =1*D9+1*D10+1*D11 | E12: =1*E9+1*E10+1*E11
A13: Buildings
A14: Building on freehold land
A15: Building on long term leasehold land | B15: 23345 | C15: 23978 | D15: 23345 | E15: 23978
A16: Building on short term leasehold land
A17: Leased properties
A18: *Total buildings | B18: =1*B14+1*B15+1*B16+1*B17 | C18: =1*C14+1*C15+1*C16+1*C17 | D18: =1*D14+1*D15+1*D16+1*D17 | E18: =1*E14+1*E15+1*E16+1*E17
A19: *Total land and buildings | B19: =1*B12+1*B18 | C19: =1*C12+1*C18 | D19: =1*D12+1*D18 | E19: =1*E12+1*E18
A20: Machinery
A21: Vehicles
A22: Office equipment, fixture and fittings | B22: 16958 | C22: 9906 | D22: 16958 | E22: 9906
A23: Plant and equipment
A24: Construction in progress/Asset work-in progress | B24: 2275 | D24: 2275
A25: Other property, plant and equipment | B25: 9525 | C25: 9592 | D25: 9525 | E25: 9592
A26: *Total property, plant and equipment | B26: =1*B19+1*B20+1*B21+1*B22+1*B23+1*B24+1*B25 | C26: =1*C19+1*C20+1*C21+1*C22+1*C23+1*C24+1*C25 | D26: =1*D19+1*D20+1*D21+1*D22+1*D23+1*D24+1*D25 | E26: =1*E19+1*E20+1*E21+1*E22+1*E23+1*E24+1*E25
A27: Investment properties
A28: Freehold land
A29: Long term leasehold land
A30: Short term leasehold land
A31: Buildings
A32: Other investment property
A33: *Total investment properties | B33: =1*B28+1*B29+1*B30+1*B31+1*B32 | C33: =1*C28+1*C29+1*C30+1*C31+1*C32 | D33: =1*D28+1*D29+1*D30+1*D31+1*D32 | E33: =1*E28+1*E29+1*E30+1*E31+1*E32
A34: Intangible assets and goodwill
A35: Intangible assets other than goodwill
A36: Copyrights, patents and other industrial property rights, service and operating rights
A37: Other intangible assets
A38: *Total intangible assets other than goodwill | B38: =1*B36+1*B37 | C38: =1*C36+1*C37 | D38: =1*D36+1*D37 | E38: =1*E36+1*E37
A39: Goodwill
A40: *Total intangible assets and goodwill | B40: =1*B39+1*B38 | C40: =1*C39+1*C38 | D40: =1*D39+1*D38 | E40: =1*E39+1*E38
A41: Investments in subsidiaries
A42: Unquoted shares, net of impairment losses | B42: 7648 | C42: 7648 | D42: 7648 | E42: 7648
A43: Quoted shares in Malaysia
A44: Quoted shares outside Malaysia
A45: Other investments in subsidiaries
A46: *Total investments in subsidiaries | B46: =1*B42+1*B43+1*B44+1*B45 | C46: =1*C42+1*C43+1*C44+1*C45 | D46: =1*D42+1*D43+1*D44+1*D45 | E46: =1*E42+1*E43+1*E44+1*E45
A47: Investments in associates
A48: Unquoted shares, net of impairment losses
A49: Quoted shares in Malaysia
A50: Quoted shares outside Malaysia
A51: Share of post-acquisition profits and reserves
A52: Other investments in associates
A53: *Total investments in associates | B53: =1*B48+1*B49+1*B50+1*B51+1*B52 | C53: =1*C48+1*C49+1*C50+1*C51+1*C52 | D53: =1*D48+1*D49+1*D50+1*D51+1*D52 | E53: =1*E48+1*E49+1*E50+1*E51+1*E52
A54: Investments in joint ventures
A55: Unquoted shares, net of impairment losses
A56: Quoted shares in Malaysia
A57: Quoted shares outside Malaysia
A58: Share of post-acquisition profits and reserves
A59: Other investments in joint ventures
A60: *Total of investments in joint ventures | B60: =1*B55+1*B56+1*B57+1*B58+1*B59 | C60: =1*C55+1*C56+1*C57+1*C58+1*C59 | D60: =1*D55+1*D56+1*D57+1*D58+1*D59 | E60: =1*E55+1*E56+1*E57+1*E58+1*E59
A61: Trade and other non-current receivables
A62: Non-current trade receivables
A63: Trade receivables due from holding company
A64: Trade receivables due from subsidiaries
A65: Trade receivables from associates
A66: Trade receivables due from joint ventures
A67: Trade receivables due from other related parties
A68: Other non-current trade receivables
A69: *Total non-current trade receivables | B69: =1*B63+1*B64+1*B65+1*B66+1*B67+1*B68 | C69: =1*C63+1*C64+1*C65+1*C66+1*C67+1*C68 | D69: =1*D63+1*D64+1*D65+1*D66+1*D67+1*D68 | E69: =1*E63+1*E64+1*E65+1*E66+1*E67+1*E68
A70: Other non-current receivables
A71: Other non-current receivables due from related parties
A72: Other receivables due from holding company
A73: Other receivables due from subsidiaries
A74: Other receivables due from associates
A75: Other receivables due from joint ventures
A76: Other receivables due from other related parties
A77: *Total other non-current receivables due from related parties | B77: =1*B72+1*B73+1*B74+1*B75+1*B76 | C77: =1*C72+1*C73+1*C74+1*C75+1*C76 | D77: =1*D72+1*D73+1*D74+1*D75+1*D76 | E77: =1*E72+1*E73+1*E74+1*E75+1*E76
A78: Non-current non-trade receivables
A79: Accrued income
A80: Lease and hire purchase receivables
A81: Other non-current non-trade receivables
A82: *Total other non-current non-trade receivables | B82: =1*B79+1*B80+1*B81 | C82: =1*C79+1*C80+1*C81 | D82: =1*D79+1*D80+1*D81 | E82: =1*E79+1*E80+1*E81
A83: *Total other non-current receivables | B83: =1*B82 | C83: =1*C82 | D83: =1*D82 | E83: =1*E82
A84: *Total trade and other non-current receivables | B84: =1*B69+1*B83+1*B77 | C84: =1*C69+1*C83+1*C77 | D84: =1*D69+1*D83+1*D77 | E84: =1*E69+1*E83+1*E77
A85: Inventories
A86: Raw materials
A87: Work in progress
A88: Finished goods
A89: Spare parts
A90: Other inventories | B90: 159389 | C90: 120685 | D90: 159389 | E90: 120685
A91: *Total inventories | B91: =1*B86+1*B87+1*B88+1*B89+1*B90 | C91: =1*C86+1*C87+1*C88+1*C89+1*C90 | D91: =1*D86+1*D87+1*D88+1*D89+1*D90 | E91: =1*E86+1*E87+1*E88+1*E89+1*E90
A92: Trade and other current receivables
A93: Current trade receivables
A94: Trade receivables due from contract customers
A95: Trade receivables due from holding company
A96: Trade receivables due from subsidiaries
A97: Trade receivables due from associates
A98: Trade receivables due from joint ventures
A99: Trade receivables due from other related parties
A100: Other current trade receivables
...
