Workbook

Sheet SOPL-Function
B1: Group | D1: Company | F1: Source
B2: 01/01/YYYY - 31/12/YYYY | C2: 01/01/YYYY - 31/12/YYYY | D2: 01/01/YYYY - 31/12/YYYY | E2: 01/01/YYYY - 31/12/YYYY
A3: Statement of profit or loss, by function of expense
A4: Statement of Profit or Loss
A5: Statement of profit or loss
A6: Continuing operations
A7: *Revenue | B7: ='SOPL-Analysis-Function'!B40 -> 0 | C7: ='SOPL-Analysis-Function'!C40 -> 0 | D7: ='SOPL-Analysis-Function'!D40 -> 0 | E7: ='SOPL-Analysis-Function'!E40 -> 0
A8: *Cost of sales | B8: ='SOPL-Analysis-Function'!B47 -> 0 | C8: ='SOPL-Analysis-Function'!C47 -> 0 | D8: ='SOPL-Analysis-Function'!D47 -> 0 | E8: ='SOPL-Analysis-Function'!E47 -> 0
A9: *Gross profit | B9: =1*B7+-1*B8 -> 0 | C9: =1*C7+-1*C8 -> 0 | D9: =1*D7+-1*D8 -> 0 | E9: =1*E7+-1*E8 -> 0
A10: *Other income | B10: ='SOPL-Analysis-Function'!B90 -> 0 | C10: ='SOPL-Analysis-Function'!C90 -> 0 | D10: ='SOPL-Analysis-Function'!D90 -> 0 | E10: ='SOPL-Analysis-Function'!E90 -> 0
A11: Selling and distribution expenses
A12: *Administrative expenses
A13: Research and development expense
A14: *Other expenses | B14: ='SOPL-Analysis-Function'!B134 -> 0 | C14: ='SOPL-Analysis-Function'!C134 -> 0 | D14: ='SOPL-Analysis-Function'!D134 -> 0 | E14: ='SOPL-Analysis-Function'!E134 -> 0
A15: *Profit (loss) from operating activities | B15: =1*B7+-1*B8+1*B10+-1*B11+-1*B12+-1*B13+-1*B14 -> 0 | C15: =1*C7+-1*C8+1*C10+-1*C11+-1*C12+-1*C13+-1*C14 -> 0 | D15: =1*D7+-1*D8+1*D10+-1*D11+-1*D12+-1*D13+-1*D14 -> 0 | E15: =1*E7+-1*E8+1*E10+-1*E11+-1*E12+-1*E13+-1*E14 -> 0
A16: *Finance income | B16: ='SOPL-Analysis-Function'!B138 -> 0 | C16: ='SOPL-Analysis-Function'!C138 -> 0 | D16: ='SOPL-Analysis-Function'!D138 -> 0 | E16: ='SOPL-Analysis-Function'!E138 -> 0
A17: *Finance costs
A18: Share of profit (loss) of associates and joint ventures accounted for using equity method
A19: Fair valuation gain (loss) arising from distribution of non-cash assets to owners
A20: *Profit (loss) before tax | B20: =1*B7+-1*B8+1*B10+-1*B11+-1*B12+-1*B13+-1*B14+1*B16+-1*B17+1*B18+1*B19 -> 0 | C20: =1*C7+-1*C8+1*C10+-1*C11+-1*C12+-1*C13+-1*C14+1*C16+-1*C17+1*C18+1*C19 -> 0 | D20: =1*D7+-1*D8+1*D10+-1*D11+-1*D12+-1*D13+-1*D14+1*D16+-1*D17+1*D18+1*D19 -> 0 | E20: =1*E7+-1*E8+1*E10+-1*E11+-1*E12+-1*E13+-1*E14+1*E16+-1*E17+1*E18+1*E19 -> 0
A21: *Tax expense
A22: Contribution of zakat
A23: *Profit (loss) from continuing operations | B23: =1*B20+-1*B21+-1*B22 -> 0 | C23: =1*C20+-1*C21+-1*C22 -> 0 | D23: =1*D20+-1*D21+-1*D22 -> 0 | E23: =1*E20+-1*E21+-1*E22 -> 0
A24: Discontinued operations
A25: Profit (loss) from discontinued operations, net of tax
A26: *Profit (loss) | B26: =1*B23+1*B25 -> 0 | C26: =1*C23+1*C25 -> 0 | D26: =1*D23+1*D25 -> 0 | E26: =1*E23+1*E25 -> 0
A27: Profit (loss), attributable to
A28: Profit (loss), attributable to owners of parent
A29: Profit (loss) attributable to equity other components
A30: Profit (loss), attributable to non-controlling interests
A31: *Total profit (loss) | B31: =1*B28+1*B29+1*B30 -> 0 | C31: =1*C28+1*C29+1*C30 -> 0 | D31: =1*D28+1*D29+1*D30 -> 0 | E31: =1*E28+1*E29+1*E30 -> 0
A32: Earnings per share
A33: Basic earnings per share
A34: Basic earnings (loss) per share from continuing operations
A35: Basic earnings (loss) per share from discontinued operations
A36: *Total basic earnings (loss) per share | B36: =1*B35 -> 0 | C36: =1*C35 -> 0 | D36: =1*D35 -> 0 | E36: =1*E35 -> 0
A37: Diluted earnings per share
A38: Diluted earnings (loss) per share from continuing operations
A39: Diluted earnings (loss) per share from discontinued operations
A40: *Total diluted earnings (loss) per share | B40: =1*B39 -> 0 | C40: =1*C39 -> 0 | D40: =1*D39 -> 0 | E40: =1*E39 -> 0

Sheet SOPL-Analysis-Function
B1: Group | D1: Company | F1: Source
B2: 01/01/YYYY - 31/12/YYYY | C2: 01/01/YYYY - 31/12/YYYY | D2: 01/01/YYYY - 31/12/YYYY | E2: 01/01/YYYY - 31/12/YYYY
A3: Analysis of profit or loss, by function of expense
A4: Analysis of profit or loss
A5: Statement of profit or loss
A6: Revenue
A7: Revenue from sale of goods
A8: Revenue from sale of broadband and telecommunication
A9: Revenue from property development
A10: Revenue from construction contracts
A11: Revenue from clean water, treatment and disposal of waste water
A12: Revenue from sale of food and beverage
A13: Revenue from sale of agricultural produce
A14: Revenue from sale of oil and gas products
A15: Revenue from sale of other goods
A16: Total revenue from sale of goods | B16: =1*B8+1*B9+1*B10+1*B11+1*B12+1*B13+1*B14+1*B15 -> 0 | C16: =1*C8+1*C9+1*C10+1*C11+1*C12+1*C13+1*C14+1*C15 -> 0 | D16: =1*D8+1*D9+1*D10+1*D11+1*D12+1*D13+1*D14+1*D15 -> 0 | E16: =1*E8+1*E9+1*E10+1*E11+1*E12+1*E13+1*E14+1*E15 -> 0
A17: Revenue from rendering of services
A18: Revenue from rendering of entertainment services
A19: Revenue from rendering of telecommunication services
A20: Revenue from rendering of transport services
A21: Revenue from rendering of information technology services
A22: Revenue from rendering of educational services
A23: Revenue from rendering of healthcare services
A24: Revenue from rendering of shipping and shipping related services
A25: Revenue from rendering of other services
A26: Total revenue from rendering of services | B26: =1*B18+1*B19+1*B20+1*B21+1*B22+1*B23+1*B24+1*B25 -> 0 | C26: =1*C18+1*C19+1*C20+1*C21+1*C22+1*C23+1*C24+1*C25 -> 0 | D26: =1*D18+1*D19+1*D20+1*D21+1*D22+1*D23+1*D24+1*D25 -> 0 | E26: =1*E18+1*E19+1*E20+1*E21+1*E22+1*E23+1*E24+1*E25 -> 0
A27: Interest income
A28: Interest income on loans, advances and financing
A29: Interest income on other financial assets
A30: Total interest income | B30: =1*B28+1*B29 -> 0 | C30: =1*C28+1*C29 -> 0 | D30: =1*D28+1*D29 -> 0 | E30: =1*E28+1*E29 -> 0
A31: Other fee and commission income
A32: Gross brokerage and other charges
A33: Underwriting commissions and fund management income
A34: Other fee and commission income
A35: Total other fee and commission income | B35: =1*B32+1*B33+1*B34 -> 0 | C35: =1*C32+1*C33+1*C34 -> 0 | D35: =1*D32+1*D33+1*D34 -> 0 | E35: =1*E32+1*E33+1*E34 -> 0
A36: Dividend income
A37: Rental income
A38: Royalty income
A39: Other revenue
A40: *Total revenue | B40: =1*B16+1*B26+1*B30+1*B35+1*B36+1*B37+1*B38+1*B39 -> 0 | C40: =1*C16+1*C26+1*C30+1*C35+1*C36+1*C37+1*C38+1*C39 -> 0 | D40: =1*D16+1*D26+1*D30+1*D35+1*D36+1*D37+1*D38+1*D39 -> 0 | E40: =1*E16+1*E26+1*E30+1*E35+1*E36+1*E37+1*E38+1*E39 -> 0
A41: Cost of sales
A42: Cost of inventories
A43: Construction contract costs
A44: Energy costs
A45: Property development costs
A46: Other cost of sales
A47: *Total cost of sales | B47: =1*B42+1*B43+1*B44+1*B45+1*B46 -> 0 | C47: =1*C42+1*C43+1*C44+1*C45+1*C46 -> 0 | D47: =1*D42+1*D43+1*D44+1*D45+1*D46 -> 0 | E47: =1*E42+1*E43+1*E44+1*E45+1*E46 -> 0
A48: Other income
A49: Deferred income
A50: Bad debts recovered
A51: Dividend income
A52: Royalty/franchise income
A53: Write back of fuel cost
A54: Income from reimbursements under insurance policies
A55: Grant or incentives by Malaysian government or it's agencies
A56: Grant or incentives by foreign government or it's agencies
A57: Contributions or donations by local contributor
A58: Contributions or donations by foreign contributor
A59: Contributions or donations by unknown contributor
... A62: Unrealised gain on foreign exchange
A63: Total foreign exchange gain | B63: =1*B61+1*B62 -> 0 | C63: =1*C61+1*C62 -> 0 | D63: =1*D61+1*D62 -> 0 | E63: =1*E61+1*E62 -> 0
A64: Gain on disposal of subsidiaries, associates and joint ventures
A65: Gain on disposal of subsidiaries
A66: Gain on disposal of associates
A67: Gain on disposal of joint ventures
A68: Total gain on disposal of subsidiaries, associates and joint ventures | B68: =1*B65+1*B66+1*B67 -> 0 | C68: =1*C65+1*C66+1*C67 -> 0 | D68: =1*D65+1*D66+1*D67 -> 0 | E68: =1*E65+1*E66+1*E67 -> 0
A69: Gain on disposal from other investments
A70: Gains on disposals of property, plant and equipment
A71: Gains on disposals of other non-current assets
A72: Other gains recognised in profit or loss, fair value measurement, assets
A73: Reversal of impairment loss recognised in profit or loss
A74: Reversal of impairment loss on receivables
A75: Reversal of impairment in development expenditure
A76: Reversal of impairment in land held for property development
A77: Reversal of impairment in property, plant and equipment
A78: Reversal of impairment in other assets
A79: Total reversal of impairment loss recognised in profit or loss | B79: =1*B75+1*B76+1*B77+1*B78 -> 0 | C79: =1*C75+1*C76+1*C77+1*C78 -> 0 | D79: =1*D75+1*D76+1*D77+1*D78 -> 0 | E79: =1*E75+1*E76+1*E77+1*E78 -> 0
A80: Reversal of inventories written down to net realisable value
A81: Interest income
A82: Management fees
A83: Net deposits recognised
A84: Net fair value gain on derivatives
A85: Net fair value gain on recycle of forex reserve upon disposal of subsidiaries
A86: Other fee and commission
A87: Other rental income
A88: Rental income on land and buildings
A89: Other miscellaneous income
A90: *Total other income | B90: =1*B49+1*B50+1*B51+1*B52+1*B53+1*B54+1*B55+1*B56+1*B57+1*B58+1*B59+1*B63+1*B68+1*B69+1*B70+1*B71+1*B72+1*B99+1*B80+1*B81+1*B82+1*B85+1*B86+1*B87+1*B88+1*B89+1*B84+1*B83 -> 0 | C90: =1*C49+1*C50+1*C51+1*C52+1*C53+1*C54+1*C55+1*C56+1*C57+1*C58+1*C59+1*C63+1*C68+1*C69+1*C70+1*C71+1*C72+1*C99+1*C80+1*C81+1*C82+1*C85+1*C86+1*C87+1*C88+1*C89+1*C84+1*C83 -> 0 | D90: =1*D49+1*D50+1*D51+1*D52+1*D53+1*D54+1*D55+1*D56+1*D57+1*D58+1*D59+1*D63+1*D68+1*D69+1*D70+1*D71+1*D72+1*D99+1*D80+1*D81+1*D82+1*D85+1*D86+1*D87+1*D88+1*D89+1*D84+1*D83 -> 0 | E90: =1*E49+1*E50+1*E51+1*E52+1*E53+1*E54+1*E55+1*E56+1*E57+1*E58+1*E59+1*E63+1*E68+1*E69+1*E70+1*E71+1*E72+1*E99+1*E80+1*E81+1*E82+1*E85+1*E86+1*E87+1*E88+1*E89+1*E84+1*E83 -> 0
A91: Other expenses
A92: Auditor's remuneration
A93: Auditor's remuneration for audit services
A94: Auditor's remuneration for other services
A95: *Total auditor's remuneration | B95: =1*B93+1*B94 -> 0 | C95: =1*C93+1*C94 -> 0 | D95: =1*D93+1*D94 -> 0 | E95: =1*E93+1*E94 -> 0
A96: Amortisation expense
A97: Depreciation, property, plant and equipment
A98: Natural disaster related expenses
A99: Loss on disposal of subsidiaries, associates and joint ventures
A100: Loss on disposal of subsidiaries
A101: Loss on disposal of associates
A102: Loss on disposal of joint ventures
...
